Classfile /F:/My_Minecraft_Expansion_3/_forge_mod_dev/test_mod/_temp_decomp/Block$BlockStatePairKey.class
  Last modified Jun 2, 2022; size 1315 bytes
  SHA-256 checksum 2be0865dbb38dc0f88bbb4b61731bbf9cfddd4ac83bc518076c7e50537e975c8
  Compiled from "Block.java"
public final class net.minecraft.world.level.block.Block$BlockStatePairKey
  minor version: 0
  major version: 61
  flags: (0x0031) ACC_PUBLIC, ACC_FINAL, ACC_SUPER
  this_class: #8                          // net/minecraft/world/level/block/Block$BlockStatePairKey
  super_class: #2                         // java/lang/Object
  interfaces: 0, fields: 3, methods: 3, attributes: 3
Constant pool:
   #1 = Methodref          #2.#3          // java/lang/Object."<init>":()V
   #2 = Class              #4             // java/lang/Object
   #3 = NameAndType        #5:#6          // "<init>":()V
   #4 = Utf8               java/lang/Object
   #5 = Utf8               <init>
   #6 = Utf8               ()V
   #7 = Fieldref           #8.#9          // net/minecraft/world/level/block/Block$BlockStatePairKey.first:Lnet/minecraft/world/level/block/state/BlockState;
   #8 = Class              #10            // net/minecraft/world/level/block/Block$BlockStatePairKey
   #9 = NameAndType        #11:#12        // first:Lnet/minecraft/world/level/block/state/BlockState;
  #10 = Utf8               net/minecraft/world/level/block/Block$BlockStatePairKey
  #11 = Utf8               first
  #12 = Utf8               Lnet/minecraft/world/level/block/state/BlockState;
  #13 = Fieldref           #8.#14         // net/minecraft/world/level/block/Block$BlockStatePairKey.second:Lnet/minecraft/world/level/block/state/BlockState;
  #14 = NameAndType        #15:#12        // second:Lnet/minecraft/world/level/block/state/BlockState;
  #15 = Utf8               second
  #16 = Fieldref           #8.#17         // net/minecraft/world/level/block/Block$BlockStatePairKey.direction:Lnet/minecraft/core/Direction;
  #17 = NameAndType        #18:#19        // direction:Lnet/minecraft/core/Direction;
  #18 = Utf8               direction
  #19 = Utf8               Lnet/minecraft/core/Direction;
  #20 = Methodref          #2.#21         // java/lang/Object.hashCode:()I
  #21 = NameAndType        #22:#23        // hashCode:()I
  #22 = Utf8               hashCode
  #23 = Utf8               ()I
  #24 = Methodref          #25.#21        // net/minecraft/core/Direction.hashCode:()I
  #25 = Class              #26            // net/minecraft/core/Direction
  #26 = Utf8               net/minecraft/core/Direction
  #27 = Utf8               (Lnet/minecraft/world/level/block/state/BlockState;Lnet/minecraft/world/level/block/state/BlockState;Lnet/minecraft/core/Direction;)V
  #28 = Utf8               Code
  #29 = Utf8               LineNumberTable
  #30 = Utf8               LocalVariableTable
  #31 = Utf8               this
  #32 = Utf8               Lnet/minecraft/world/level/block/Block$BlockStatePairKey;
  #33 = Utf8               p_49984_
  #34 = Utf8               p_49985_
  #35 = Utf8               p_49986_
  #36 = Utf8               equals
  #37 = Utf8               (Ljava/lang/Object;)Z
  #38 = Utf8               block$blockstatepairkey
  #39 = Utf8               p_49988_
  #40 = Utf8               Ljava/lang/Object;
  #41 = Utf8               StackMapTable
  #42 = Utf8               i
  #43 = Utf8               I
  #44 = Utf8               SourceFile
  #45 = Utf8               Block.java
  #46 = Utf8               NestHost
  #47 = Class              #48            // net/minecraft/world/level/block/Block
  #48 = Utf8               net/minecraft/world/level/block/Block
  #49 = Utf8               InnerClasses
  #50 = Utf8               BlockStatePairKey
{
  private final net.minecraft.world.level.block.state.BlockState first;
    descriptor: Lnet/minecraft/world/level/block/state/BlockState;
    flags: (0x0012) ACC_PRIVATE, ACC_FINAL

  private final net.minecraft.world.level.block.state.BlockState second;
    descriptor: Lnet/minecraft/world/level/block/state/BlockState;
    flags: (0x0012) ACC_PRIVATE, ACC_FINAL

  private final net.minecraft.core.Direction direction;
    descriptor: Lnet/minecraft/core/Direction;
    flags: (0x0012) ACC_PRIVATE, ACC_FINAL

  public net.minecraft.world.level.block.Block$BlockStatePairKey(net.minecraft.world.level.block.state.BlockState, net.minecraft.world.level.block.state.BlockState, net.minecraft.core.Direction);
    descriptor: (Lnet/minecraft/world/level/block/state/BlockState;Lnet/minecraft/world/level/block/state/BlockState;Lnet/minecraft/core/Direction;)V
    flags: (0x0001) ACC_PUBLIC
    Code:
      stack=2, locals=4, args_size=4
         0: aload_0
         1: invokespecial #1                  // Method java/lang/Object."<init>":()V
         4: aload_0
         5: aload_1
         6: putfield      #7                  // Field first:Lnet/minecraft/world/level/block/state/BlockState;
         9: aload_0
        10: aload_2
        11: putfield      #13                 // Field second:Lnet/minecraft/world/level/block/state/BlockState;
        14: aload_0
        15: aload_3
        16: putfield      #16                 // Field direction:Lnet/minecraft/core/Direction;
        19: return
      LineNumberTable:
        line 580: 0
        line 581: 4
        line 582: 9
        line 583: 14
        line 584: 19
      LocalVariableTable:
        Start  Length  Slot  Name   Signature
            0      20     0  this   Lnet/minecraft/world/level/block/Block$BlockStatePairKey;
            0      20     1 p_49984_   Lnet/minecraft/world/level/block/state/BlockState;
            0      20     2 p_49985_   Lnet/minecraft/world/level/block/state/BlockState;
            0      20     3 p_49986_   Lnet/minecraft/core/Direction;

  public boolean equals(java.lang.Object);
    descriptor: (Ljava/lang/Object;)Z
    flags: (0x0001) ACC_PUBLIC
    Code:
      stack=2, locals=3, args_size=2
         0: aload_0
         1: aload_1
         2: if_acmpne     7
         5: iconst_1
         6: ireturn
         7: aload_1
         8: instanceof    #8                  // class net/minecraft/world/level/block/Block$BlockStatePairKey
        11: ifne          16
        14: iconst_0
        15: ireturn
        16: aload_1
        17: checkcast     #8                  // class net/minecraft/world/level/block/Block$BlockStatePairKey
        20: astore_2
        21: aload_0
        22: getfield      #7                  // Field first:Lnet/minecraft/world/level/block/state/BlockState;
        25: aload_2
        26: getfield      #7                  // Field first:Lnet/minecraft/world/level/block/state/BlockState;
        29: if_acmpne     58
        32: aload_0
        33: getfield      #13                 // Field second:Lnet/minecraft/world/level/block/state/BlockState;
        36: aload_2
        37: getfield      #13                 // Field second:Lnet/minecraft/world/level/block/state/BlockState;
        40: if_acmpne     58
        43: aload_0
        44: getfield      #16                 // Field direction:Lnet/minecraft/core/Direction;
        47: aload_2
        48: getfield      #16                 // Field direction:Lnet/minecraft/core/Direction;
        51: if_acmpne     58
        54: iconst_1
        55: goto          59
        58: iconst_0
        59: ireturn
      LineNumberTable:
        line 587: 0
        line 588: 5
        line 589: 7
        line 590: 14
        line 592: 16
        line 593: 21
      LocalVariableTable:
        Start  Length  Slot  Name   Signature
           21      39     2 block$blockstatepairkey   Lnet/minecraft/world/level/block/Block$BlockStatePairKey;
            0      60     0  this   Lnet/minecraft/world/level/block/Block$BlockStatePairKey;
            0      60     1 p_49988_   Ljava/lang/Object;
      StackMapTable: number_of_entries = 4
        frame_type = 7 /* same */
        frame_type = 8 /* same */
        frame_type = 252 /* append */
          offset_delta = 41
          locals = [ class net/minecraft/world/level/block/Block$BlockStatePairKey ]
        frame_type = 64 /* same_locals_1_stack_item */
          stack = [ int ]

  public int hashCode();
    descriptor: ()I
    flags: (0x0001) ACC_PUBLIC
    Code:
      stack=2, locals=2, args_size=1
         0: aload_0
         1: getfield      #7                  // Field first:Lnet/minecraft/world/level/block/state/BlockState;
         4: invokevirtual #20                 // Method java/lang/Object.hashCode:()I
         7: istore_1
         8: bipush        31
        10: iload_1
        11: imul
        12: aload_0
        13: getfield      #13                 // Field second:Lnet/minecraft/world/level/block/state/BlockState;
        16: invokevirtual #20                 // Method java/lang/Object.hashCode:()I
        19: iadd
        20: istore_1
        21: bipush        31
        23: iload_1
        24: imul
        25: aload_0
        26: getfield      #16                 // Field direction:Lnet/minecraft/core/Direction;
        29: invokevirtual #24                 // Method net/minecraft/core/Direction.hashCode:()I
        32: iadd
        33: ireturn
      LineNumberTable:
        line 598: 0
        line 599: 8
        line 600: 21
      LocalVariableTable:
        Start  Length  Slot  Name   Signature
            0      34     0  this   Lnet/minecraft/world/level/block/Block$BlockStatePairKey;
            8      26     1     i   I
}
SourceFile: "Block.java"
NestHost: class net/minecraft/world/level/block/Block
InnerClasses:
  public static final #50= #8 of #47;     // BlockStatePairKey=class net/minecraft/world/level/block/Block$BlockStatePairKey of class net/minecraft/world/level/block/Block
