Classfile /F:/My_Minecraft_Expansion_3/_forge_mod_dev/test_mod/_temp_decomp/Block$1.class
  Last modified Jun 2, 2022; size 1490 bytes
  SHA-256 checksum 5debfe5ca119fc1a8ed66ad646e3bebe98b70bd2ece1725744b024ca8ecc8e63
  Compiled from "Block.java"
class net.minecraft.world.level.block.Block$1 extends com.google.common.cache.CacheLoader<net.minecraft.world.phys.shapes.VoxelShape, java.lang.Boolean>
  minor version: 0
  major version: 61
  flags: (0x0020) ACC_SUPER
  this_class: #32                         // net/minecraft/world/level/block/Block$1
  super_class: #2                         // com/google/common/cache/CacheLoader
  interfaces: 0, fields: 0, methods: 3, attributes: 5
Constant pool:
   #1 = Methodref          #2.#3          // com/google/common/cache/CacheLoader."<init>":()V
   #2 = Class              #4             // com/google/common/cache/CacheLoader
   #3 = NameAndType        #5:#6          // "<init>":()V
   #4 = Utf8               com/google/common/cache/CacheLoader
   #5 = Utf8               <init>
   #6 = Utf8               ()V
   #7 = Methodref          #8.#9          // net/minecraft/world/phys/shapes/Shapes.block:()Lnet/minecraft/world/phys/shapes/VoxelShape;
   #8 = Class              #10            // net/minecraft/world/phys/shapes/Shapes
   #9 = NameAndType        #11:#12        // block:()Lnet/minecraft/world/phys/shapes/VoxelShape;
  #10 = Utf8               net/minecraft/world/phys/shapes/Shapes
  #11 = Utf8               block
  #12 = Utf8               ()Lnet/minecraft/world/phys/shapes/VoxelShape;
  #13 = Fieldref           #14.#15        // net/minecraft/world/phys/shapes/BooleanOp.NOT_SAME:Lnet/minecraft/world/phys/shapes/BooleanOp;
  #14 = Class              #16            // net/minecraft/world/phys/shapes/BooleanOp
  #15 = NameAndType        #17:#18        // NOT_SAME:Lnet/minecraft/world/phys/shapes/BooleanOp;
  #16 = Utf8               net/minecraft/world/phys/shapes/BooleanOp
  #17 = Utf8               NOT_SAME
  #18 = Utf8               Lnet/minecraft/world/phys/shapes/BooleanOp;
  #19 = Methodref          #8.#20         // net/minecraft/world/phys/shapes/Shapes.joinIsNotEmpty:(Lnet/minecraft/world/phys/shapes/VoxelShape;Lnet/minecraft/world/phys/shapes/VoxelShape;Lnet/minecraft/world/phys/shapes/BooleanOp;)Z
  #20 = NameAndType        #21:#22        // joinIsNotEmpty:(Lnet/minecraft/world/phys/shapes/VoxelShape;Lnet/minecraft/world/phys/shapes/VoxelShape;Lnet/minecraft/world/phys/shapes/BooleanOp;)Z
  #21 = Utf8               joinIsNotEmpty
  #22 = Utf8               (Lnet/minecraft/world/phys/shapes/VoxelShape;Lnet/minecraft/world/phys/shapes/VoxelShape;Lnet/minecraft/world/phys/shapes/BooleanOp;)Z
  #23 = Methodref          #24.#25        // java/lang/Boolean.valueOf:(Z)Ljava/lang/Boolean;
  #24 = Class              #26            // java/lang/Boolean
  #25 = NameAndType        #27:#28        // valueOf:(Z)Ljava/lang/Boolean;
  #26 = Utf8               java/lang/Boolean
  #27 = Utf8               valueOf
  #28 = Utf8               (Z)Ljava/lang/Boolean;
  #29 = Class              #30            // net/minecraft/world/phys/shapes/VoxelShape
  #30 = Utf8               net/minecraft/world/phys/shapes/VoxelShape
  #31 = Methodref          #32.#33        // net/minecraft/world/level/block/Block$1.load:(Lnet/minecraft/world/phys/shapes/VoxelShape;)Ljava/lang/Boolean;
  #32 = Class              #34            // net/minecraft/world/level/block/Block$1
  #33 = NameAndType        #35:#36        // load:(Lnet/minecraft/world/phys/shapes/VoxelShape;)Ljava/lang/Boolean;
  #34 = Utf8               net/minecraft/world/level/block/Block$1
  #35 = Utf8               load
  #36 = Utf8               (Lnet/minecraft/world/phys/shapes/VoxelShape;)Ljava/lang/Boolean;
  #37 = Utf8               Code
  #38 = Utf8               LineNumberTable
  #39 = Utf8               LocalVariableTable
  #40 = Utf8               this
  #41 = Utf8               Lnet/minecraft/world/level/block/Block$1;
  #42 = Utf8               p_49972_
  #43 = Utf8               Lnet/minecraft/world/phys/shapes/VoxelShape;
  #44 = Utf8               StackMapTable
  #45 = Utf8               (Ljava/lang/Object;)Ljava/lang/Object;
  #46 = Utf8               Exceptions
  #47 = Class              #48            // java/lang/Exception
  #48 = Utf8               java/lang/Exception
  #49 = Utf8               Signature
  #50 = Utf8               Lcom/google/common/cache/CacheLoader<Lnet/minecraft/world/phys/shapes/VoxelShape;Ljava/lang/Boolean;>;
  #51 = Utf8               SourceFile
  #52 = Utf8               Block.java
  #53 = Utf8               EnclosingMethod
  #54 = Class              #55            // net/minecraft/world/level/block/Block
  #55 = Utf8               net/minecraft/world/level/block/Block
  #56 = Utf8               NestHost
  #57 = Utf8               InnerClasses
{
  net.minecraft.world.level.block.Block$1();
    descriptor: ()V
    flags: (0x0000)
    Code:
      stack=1, locals=1, args_size=1
         0: aload_0
         1: invokespecial #1                  // Method com/google/common/cache/CacheLoader."<init>":()V
         4: return
      LineNumberTable:
        line 70: 0
      LocalVariableTable:
        Start  Length  Slot  Name   Signature
            0       5     0  this   Lnet/minecraft/world/level/block/Block$1;

  public java.lang.Boolean load(net.minecraft.world.phys.shapes.VoxelShape);
    descriptor: (Lnet/minecraft/world/phys/shapes/VoxelShape;)Ljava/lang/Boolean;
    flags: (0x0001) ACC_PUBLIC
    Code:
      stack=3, locals=2, args_size=2
         0: invokestatic  #7                  // Method net/minecraft/world/phys/shapes/Shapes.block:()Lnet/minecraft/world/phys/shapes/VoxelShape;
         3: aload_1
         4: getstatic     #13                 // Field net/minecraft/world/phys/shapes/BooleanOp.NOT_SAME:Lnet/minecraft/world/phys/shapes/BooleanOp;
         7: invokestatic  #19                 // Method net/minecraft/world/phys/shapes/Shapes.joinIsNotEmpty:(Lnet/minecraft/world/phys/shapes/VoxelShape;Lnet/minecraft/world/phys/shapes/VoxelShape;Lnet/minecraft/world/phys/shapes/BooleanOp;)Z
        10: ifne          17
        13: iconst_1
        14: goto          18
        17: iconst_0
        18: invokestatic  #23                 // Method java/lang/Boolean.valueOf:(Z)Ljava/lang/Boolean;
        21: areturn
      LineNumberTable:
        line 72: 0
      LocalVariableTable:
        Start  Length  Slot  Name   Signature
            0      22     0  this   Lnet/minecraft/world/level/block/Block$1;
            0      22     1 p_49972_   Lnet/minecraft/world/phys/shapes/VoxelShape;
      StackMapTable: number_of_entries = 2
        frame_type = 17 /* same */
        frame_type = 64 /* same_locals_1_stack_item */
          stack = [ int ]

  public java.lang.Object load(java.lang.Object) throws java.lang.Exception;
    descriptor: (Ljava/lang/Object;)Ljava/lang/Object;
    flags: (0x1041) ACC_PUBLIC, ACC_BRIDGE, ACC_SYNTHETIC
    Code:
      stack=2, locals=2, args_size=2
         0: aload_0
         1: aload_1
         2: checkcast     #29                 // class net/minecraft/world/phys/shapes/VoxelShape
         5: invokevirtual #31                 // Method load:(Lnet/minecraft/world/phys/shapes/VoxelShape;)Ljava/lang/Boolean;
         8: areturn
      LineNumberTable:
        line 70: 0
      LocalVariableTable:
        Start  Length  Slot  Name   Signature
            0       9     0  this   Lnet/minecraft/world/level/block/Block$1;
    Exceptions:
      throws java.lang.Exception
}
Signature: #50                          // Lcom/google/common/cache/CacheLoader<Lnet/minecraft/world/phys/shapes/VoxelShape;Ljava/lang/Boolean;>;
SourceFile: "Block.java"
EnclosingMethod: #54.#0                 // net.minecraft.world.level.block.Block
NestHost: class net/minecraft/world/level/block/Block
InnerClasses:
  #32;                                    // class net/minecraft/world/level/block/Block$1
