Classfile /F:/My_Minecraft_Expansion_3/_forge_mod_dev/test_mod/_temp_decomp/Block$2.class
  Last modified Jun 2, 2022; size 864 bytes
  SHA-256 checksum 9a9511a39474a695806bbb2a51db70189c5fd8d8be794043471decb66184be93
  Compiled from "Block.java"
class net.minecraft.world.level.block.Block$2 extends it.unimi.dsi.fastutil.objects.Object2ByteLinkedOpenHashMap<net.minecraft.world.level.block.Block$BlockStatePairKey>
  minor version: 0
  major version: 61
  flags: (0x0020) ACC_SUPER
  this_class: #7                          // net/minecraft/world/level/block/Block$2
  super_class: #2                         // it/unimi/dsi/fastutil/objects/Object2ByteLinkedOpenHashMap
  interfaces: 0, fields: 0, methods: 2, attributes: 5
Constant pool:
   #1 = Methodref          #2.#3          // it/unimi/dsi/fastutil/objects/Object2ByteLinkedOpenHashMap."<init>":(IF)V
   #2 = Class              #4             // it/unimi/dsi/fastutil/objects/Object2ByteLinkedOpenHashMap
   #3 = NameAndType        #5:#6          // "<init>":(IF)V
   #4 = Utf8               it/unimi/dsi/fastutil/objects/Object2ByteLinkedOpenHashMap
   #5 = Utf8               <init>
   #6 = Utf8               (IF)V
   #7 = Class              #8             // net/minecraft/world/level/block/Block$2
   #8 = Utf8               net/minecraft/world/level/block/Block$2
   #9 = Utf8               Code
  #10 = Utf8               LineNumberTable
  #11 = Utf8               LocalVariableTable
  #12 = Utf8               this
  #13 = Utf8               Lnet/minecraft/world/level/block/Block$2;
  #14 = Utf8               arg0
  #15 = Utf8               I
  #16 = Utf8               arg1
  #17 = Utf8               F
  #18 = Utf8               rehash
  #19 = Utf8               (I)V
  #20 = Utf8               p_49979_
  #21 = Utf8               Signature
  #22 = Utf8               Lit/unimi/dsi/fastutil/objects/Object2ByteLinkedOpenHashMap<Lnet/minecraft/world/level/block/Block$BlockStatePairKey;>;
  #23 = Utf8               SourceFile
  #24 = Utf8               Block.java
  #25 = Utf8               EnclosingMethod
  #26 = Class              #27            // net/minecraft/world/level/block/Block
  #27 = Utf8               net/minecraft/world/level/block/Block
  #28 = NameAndType        #29:#30        // "<clinit>":()V
  #29 = Utf8               <clinit>
  #30 = Utf8               ()V
  #31 = Utf8               NestHost
  #32 = Utf8               InnerClasses
  #33 = Class              #34            // net/minecraft/world/level/block/Block$BlockStatePairKey
  #34 = Utf8               net/minecraft/world/level/block/Block$BlockStatePairKey
  #35 = Utf8               BlockStatePairKey
{
  net.minecraft.world.level.block.Block$2(int, float);
    descriptor: (IF)V
    flags: (0x0000)
    Code:
      stack=3, locals=3, args_size=3
         0: aload_0
         1: iload_1
         2: fload_2
         3: invokespecial #1                  // Method it/unimi/dsi/fastutil/objects/Object2ByteLinkedOpenHashMap."<init>":(IF)V
         6: return
      LineNumberTable:
        line 97: 0
      LocalVariableTable:
        Start  Length  Slot  Name   Signature
            0       7     0  this   Lnet/minecraft/world/level/block/Block$2;
            0       7     1  arg0   I
            0       7     2  arg1   F

  protected void rehash(int);
    descriptor: (I)V
    flags: (0x0004) ACC_PROTECTED
    Code:
      stack=0, locals=2, args_size=2
         0: return
      LineNumberTable:
        line 99: 0
      LocalVariableTable:
        Start  Length  Slot  Name   Signature
            0       1     0  this   Lnet/minecraft/world/level/block/Block$2;
            0       1     1 p_49979_   I
}
Signature: #22                          // Lit/unimi/dsi/fastutil/objects/Object2ByteLinkedOpenHashMap<Lnet/minecraft/world/level/block/Block$BlockStatePairKey;>;
SourceFile: "Block.java"
EnclosingMethod: #26.#28                // net.minecraft.world.level.block.Block.<clinit>
NestHost: class net/minecraft/world/level/block/Block
InnerClasses:
  #7;                                     // class net/minecraft/world/level/block/Block$2
  public static final #35= #33 of #26;    // BlockStatePairKey=class net/minecraft/world/level/block/Block$BlockStatePairKey of class net/minecraft/world/level/block/Block
