Classfile /F:/My_Minecraft_Expansion_3/_forge_mod_dev/test_mod/_temp_decomp/StateHolder$1.class
  Last modified Jun 2, 2022; size 2885 bytes
  SHA-256 checksum 4c3a234aab064500db353dbbd1742be5a8bb5e3e7d6b112aefe6b05b0e72b0b2
  Compiled from "StateHolder.java"
class net.minecraft.world.level.block.state.StateHolder$1 extends java.lang.Object implements java.util.function.Function<java.util.Map$Entry<net.minecraft.world.level.block.state.properties.Property<?>, java.lang.Comparable<?>>, java.lang.String>
  minor version: 0
  major version: 61
  flags: (0x0020) ACC_SUPER
  this_class: #27                         // net/minecraft/world/level/block/state/StateHolder$1
  super_class: #2                         // java/lang/Object
  interfaces: 1, fields: 0, methods: 4, attributes: 6
Constant pool:
   #1 = Methodref          #2.#3          // java/lang/Object."<init>":()V
   #2 = Class              #4             // java/lang/Object
   #3 = NameAndType        #5:#6          // "<init>":()V
   #4 = Utf8               java/lang/Object
   #5 = Utf8               <init>
   #6 = Utf8               ()V
   #7 = String             #8             // <NULL>
   #8 = Utf8               <NULL>
   #9 = InterfaceMethodref #10.#11        // java/util/Map$Entry.getKey:()Ljava/lang/Object;
  #10 = Class              #12            // java/util/Map$Entry
  #11 = NameAndType        #13:#14        // getKey:()Ljava/lang/Object;
  #12 = Utf8               java/util/Map$Entry
  #13 = Utf8               getKey
  #14 = Utf8               ()Ljava/lang/Object;
  #15 = Class              #16            // net/minecraft/world/level/block/state/properties/Property
  #16 = Utf8               net/minecraft/world/level/block/state/properties/Property
  #17 = Methodref          #15.#18        // net/minecraft/world/level/block/state/properties/Property.getName:()Ljava/lang/String;
  #18 = NameAndType        #19:#20        // getName:()Ljava/lang/String;
  #19 = Utf8               getName
  #20 = Utf8               ()Ljava/lang/String;
  #21 = InterfaceMethodref #10.#22        // java/util/Map$Entry.getValue:()Ljava/lang/Object;
  #22 = NameAndType        #23:#14        // getValue:()Ljava/lang/Object;
  #23 = Utf8               getValue
  #24 = Class              #25            // java/lang/Comparable
  #25 = Utf8               java/lang/Comparable
  #26 = Methodref          #27.#28        // net/minecraft/world/level/block/state/StateHolder$1.getName:(Lnet/minecraft/world/level/block/state/properties/Property;Ljava/lang/Comparable;)Ljava/lang/String;
  #27 = Class              #29            // net/minecraft/world/level/block/state/StateHolder$1
  #28 = NameAndType        #19:#30        // getName:(Lnet/minecraft/world/level/block/state/properties/Property;Ljava/lang/Comparable;)Ljava/lang/String;
  #29 = Utf8               net/minecraft/world/level/block/state/StateHolder$1
  #30 = Utf8               (Lnet/minecraft/world/level/block/state/properties/Property;Ljava/lang/Comparable;)Ljava/lang/String;
  #31 = InvokeDynamic      #0:#32         // #0:makeConcatWithConstants:(Ljava/lang/String;Ljava/lang/String;)Ljava/lang/String;
  #32 = NameAndType        #33:#34        // makeConcatWithConstants:(Ljava/lang/String;Ljava/lang/String;)Ljava/lang/String;
  #33 = Utf8               makeConcatWithConstants
  #34 = Utf8               (Ljava/lang/String;Ljava/lang/String;)Ljava/lang/String;
  #35 = Methodref          #15.#36        // net/minecraft/world/level/block/state/properties/Property.getName:(Ljava/lang/Comparable;)Ljava/lang/String;
  #36 = NameAndType        #19:#37        // getName:(Ljava/lang/Comparable;)Ljava/lang/String;
  #37 = Utf8               (Ljava/lang/Comparable;)Ljava/lang/String;
  #38 = Methodref          #27.#39        // net/minecraft/world/level/block/state/StateHolder$1.apply:(Ljava/util/Map$Entry;)Ljava/lang/String;
  #39 = NameAndType        #40:#41        // apply:(Ljava/util/Map$Entry;)Ljava/lang/String;
  #40 = Utf8               apply
  #41 = Utf8               (Ljava/util/Map$Entry;)Ljava/lang/String;
  #42 = Class              #43            // java/util/function/Function
  #43 = Utf8               java/util/function/Function
  #44 = Utf8               Code
  #45 = Utf8               LineNumberTable
  #46 = Utf8               LocalVariableTable
  #47 = Utf8               this
  #48 = Utf8               Lnet/minecraft/world/level/block/state/StateHolder$1;
  #49 = Utf8               property
  #50 = Utf8               Lnet/minecraft/world/level/block/state/properties/Property;
  #51 = Utf8               p_61155_
  #52 = Utf8               Ljava/util/Map$Entry;
  #53 = Utf8               LocalVariableTypeTable
  #54 = Utf8               Lnet/minecraft/world/level/block/state/properties/Property<*>;
  #55 = Utf8               Ljava/util/Map$Entry<Lnet/minecraft/world/level/block/state/properties/Property<*>;Ljava/lang/Comparable<*>;>;
  #56 = Utf8               StackMapTable
  #57 = Utf8               Signature
  #58 = Utf8               (Ljava/util/Map$Entry<Lnet/minecraft/world/level/block/state/properties/Property<*>;Ljava/lang/Comparable<*>;>;)Ljava/lang/String;
  #59 = Utf8               RuntimeVisibleParameterAnnotations
  #60 = Utf8               Ljavax/annotation/Nullable;
  #61 = Utf8               p_61152_
  #62 = Utf8               p_61153_
  #63 = Utf8               Ljava/lang/Comparable;
  #64 = Utf8               Lnet/minecraft/world/level/block/state/properties/Property<TT;>;
  #65 = Utf8               Ljava/lang/Comparable<*>;
  #66 = Utf8               <T::Ljava/lang/Comparable<TT;>;>(Lnet/minecraft/world/level/block/state/properties/Property<TT;>;Ljava/lang/Comparable<*>;)Ljava/lang/String;
  #67 = Utf8               (Ljava/lang/Object;)Ljava/lang/Object;
  #68 = Utf8               Ljava/lang/Object;Ljava/util/function/Function<Ljava/util/Map$Entry<Lnet/minecraft/world/level/block/state/properties/Property<*>;Ljava/lang/Comparable<*>;>;Ljava/lang/String;>;
  #69 = Utf8               SourceFile
  #70 = Utf8               StateHolder.java
  #71 = Utf8               EnclosingMethod
  #72 = Class              #73            // net/minecraft/world/level/block/state/StateHolder
  #73 = Utf8               net/minecraft/world/level/block/state/StateHolder
  #74 = Utf8               NestHost
  #75 = Utf8               BootstrapMethods
  #76 = MethodHandle       6:#77          // REF_invokeStatic java/lang/invoke/StringConcatFactory.makeConcatWithConstants:(Ljava/lang/invoke/MethodHandles$Lookup;Ljava/lang/String;Ljava/lang/invoke/MethodType;Ljava/lang/String;[Ljava/lang/Object;)Ljava/lang/invoke/CallSite;
  #77 = Methodref          #78.#79        // java/lang/invoke/StringConcatFactory.makeConcatWithConstants:(Ljava/lang/invoke/MethodHandles$Lookup;Ljava/lang/String;Ljava/lang/invoke/MethodType;Ljava/lang/String;[Ljava/lang/Object;)Ljava/lang/invoke/CallSite;
  #78 = Class              #80            // java/lang/invoke/StringConcatFactory
  #79 = NameAndType        #33:#81        // makeConcatWithConstants:(Ljava/lang/invoke/MethodHandles$Lookup;Ljava/lang/String;Ljava/lang/invoke/MethodType;Ljava/lang/String;[Ljava/lang/Object;)Ljava/lang/invoke/CallSite;
  #80 = Utf8               java/lang/invoke/StringConcatFactory
  #81 = Utf8               (Ljava/lang/invoke/MethodHandles$Lookup;Ljava/lang/String;Ljava/lang/invoke/MethodType;Ljava/lang/String;[Ljava/lang/Object;)Ljava/lang/invoke/CallSite;
  #82 = String             #83            // \u0001=\u0001
  #83 = Utf8               \u0001=\u0001
  #84 = Utf8               InnerClasses
  #85 = Class              #86            // java/util/Map
  #86 = Utf8               java/util/Map
  #87 = Utf8               Entry
  #88 = Class              #89            // java/lang/invoke/MethodHandles$Lookup
  #89 = Utf8               java/lang/invoke/MethodHandles$Lookup
  #90 = Class              #91            // java/lang/invoke/MethodHandles
  #91 = Utf8               java/lang/invoke/MethodHandles
  #92 = Utf8               Lookup
{
  net.minecraft.world.level.block.state.StateHolder$1();
    descriptor: ()V
    flags: (0x0000)
    Code:
      stack=1, locals=1, args_size=1
         0: aload_0
         1: invokespecial #1                  // Method java/lang/Object."<init>":()V
         4: return
      LineNumberTable:
        line 24: 0
      LocalVariableTable:
        Start  Length  Slot  Name   Signature
            0       5     0  this   Lnet/minecraft/world/level/block/state/StateHolder$1;

  public java.lang.String apply(java.util.Map$Entry<net.minecraft.world.level.block.state.properties.Property<?>, java.lang.Comparable<?>>);
    descriptor: (Ljava/util/Map$Entry;)Ljava/lang/String;
    flags: (0x0001) ACC_PUBLIC
    Code:
      stack=4, locals=3, args_size=2
         0: aload_1
         1: ifnonnull     7
         4: ldc           #7                  // String <NULL>
         6: areturn
         7: aload_1
         8: invokeinterface #9,  1            // InterfaceMethod java/util/Map$Entry.getKey:()Ljava/lang/Object;
        13: checkcast     #15                 // class net/minecraft/world/level/block/state/properties/Property
        16: astore_2
        17: aload_2
        18: invokevirtual #17                 // Method net/minecraft/world/level/block/state/properties/Property.getName:()Ljava/lang/String;
        21: aload_0
        22: aload_2
        23: aload_1
        24: invokeinterface #21,  1           // InterfaceMethod java/util/Map$Entry.getValue:()Ljava/lang/Object;
        29: checkcast     #24                 // class java/lang/Comparable
        32: invokevirtual #26                 // Method getName:(Lnet/minecraft/world/level/block/state/properties/Property;Ljava/lang/Comparable;)Ljava/lang/String;
        35: invokedynamic #31,  0             // InvokeDynamic #0:makeConcatWithConstants:(Ljava/lang/String;Ljava/lang/String;)Ljava/lang/String;
        40: areturn
      LineNumberTable:
        line 26: 0
        line 27: 4
        line 29: 7
        line 30: 17
      LocalVariableTable:
        Start  Length  Slot  Name   Signature
           17      24     2 property   Lnet/minecraft/world/level/block/state/properties/Property;
            0      41     0  this   Lnet/minecraft/world/level/block/state/StateHolder$1;
            0      41     1 p_61155_   Ljava/util/Map$Entry;
      LocalVariableTypeTable:
        Start  Length  Slot  Name   Signature
           17      24     2 property   Lnet/minecraft/world/level/block/state/properties/Property<*>;
            0      41     1 p_61155_   Ljava/util/Map$Entry<Lnet/minecraft/world/level/block/state/properties/Property<*>;Ljava/lang/Comparable<*>;>;
      StackMapTable: number_of_entries = 1
        frame_type = 7 /* same */
    Signature: #58                          // (Ljava/util/Map$Entry<Lnet/minecraft/world/level/block/state/properties/Property<*>;Ljava/lang/Comparable<*>;>;)Ljava/lang/String;
    RuntimeVisibleParameterAnnotations:
      parameter 0:
        0: #60()
          javax.annotation.Nullable

  private <T extends java.lang.Comparable<T>> java.lang.String getName(net.minecraft.world.level.block.state.properties.Property<T>, java.lang.Comparable<?>);
    descriptor: (Lnet/minecraft/world/level/block/state/properties/Property;Ljava/lang/Comparable;)Ljava/lang/String;
    flags: (0x0002) ACC_PRIVATE
    Code:
      stack=2, locals=3, args_size=3
         0: aload_1
         1: aload_2
         2: invokevirtual #35                 // Method net/minecraft/world/level/block/state/properties/Property.getName:(Ljava/lang/Comparable;)Ljava/lang/String;
         5: areturn
      LineNumberTable:
        line 35: 0
      LocalVariableTable:
        Start  Length  Slot  Name   Signature
            0       6     0  this   Lnet/minecraft/world/level/block/state/StateHolder$1;
            0       6     1 p_61152_   Lnet/minecraft/world/level/block/state/properties/Property;
            0       6     2 p_61153_   Ljava/lang/Comparable;
      LocalVariableTypeTable:
        Start  Length  Slot  Name   Signature
            0       6     1 p_61152_   Lnet/minecraft/world/level/block/state/properties/Property<TT;>;
            0       6     2 p_61153_   Ljava/lang/Comparable<*>;
    Signature: #66                          // <T::Ljava/lang/Comparable<TT;>;>(Lnet/minecraft/world/level/block/state/properties/Property<TT;>;Ljava/lang/Comparable<*>;)Ljava/lang/String;

  public java.lang.Object apply(java.lang.Object);
    descriptor: (Ljava/lang/Object;)Ljava/lang/Object;
    flags: (0x1041) ACC_PUBLIC, ACC_BRIDGE, ACC_SYNTHETIC
    Code:
      stack=2, locals=2, args_size=2
         0: aload_0
         1: aload_1
         2: checkcast     #10                 // class java/util/Map$Entry
         5: invokevirtual #38                 // Method apply:(Ljava/util/Map$Entry;)Ljava/lang/String;
         8: areturn
      LineNumberTable:
        line 24: 0
      LocalVariableTable:
        Start  Length  Slot  Name   Signature
            0       9     0  this   Lnet/minecraft/world/level/block/state/StateHolder$1;
    RuntimeVisibleParameterAnnotations:
      parameter 0:
        0: #60()
          javax.annotation.Nullable
}
Signature: #68                          // Ljava/lang/Object;Ljava/util/function/Function<Ljava/util/Map$Entry<Lnet/minecraft/world/level/block/state/properties/Property<*>;Ljava/lang/Comparable<*>;>;Ljava/lang/String;>;
SourceFile: "StateHolder.java"
EnclosingMethod: #72.#0                 // net.minecraft.world.level.block.state.StateHolder
NestHost: class net/minecraft/world/level/block/state/StateHolder
BootstrapMethods:
  0: #76 REF_invokeStatic java/lang/invoke/StringConcatFactory.makeConcatWithConstants:(Ljava/lang/invoke/MethodHandles$Lookup;Ljava/lang/String;Ljava/lang/invoke/MethodType;Ljava/lang/String;[Ljava/lang/Object;)Ljava/lang/invoke/CallSite;
    Method arguments:
      #82 \u0001=\u0001
InnerClasses:
  public static #87= #10 of #85;          // Entry=class java/util/Map$Entry of class java/util/Map
  #27;                                    // class net/minecraft/world/level/block/state/StateHolder$1
  public static final #92= #88 of #90;    // Lookup=class java/lang/invoke/MethodHandles$Lookup of class java/lang/invoke/MethodHandles
