Classfile /F:/My_Minecraft_Expansion_3/_forge_mod_dev/test_mod/_temp_decomp/cav.class
  Last modified Feb 28, 2022; size 26593 bytes
  SHA-256 checksum 9f7d7d1d01266760d1f734ef70eff427763816c50a6b0df1e8a54212f6b13108
  Compiled from "SourceFile"
public abstract class cav implements caw,java.lang.AutoCloseable
  minor version: 0
  major version: 61
  flags: (0x0421) ACC_PUBLIC, ACC_SUPER, ACC_ABSTRACT
  this_class: #2                          // cav
  super_class: #4                         // java/lang/Object
  interfaces: 2, fields: 34, methods: 120, attributes: 4
Constant pool:
     #1 = Utf8               cav
     #2 = Class              #1           // cav
     #3 = Utf8               java/lang/Object
     #4 = Class              #3           // java/lang/Object
     #5 = Utf8               caw
     #6 = Class              #5           // caw
     #7 = Utf8               java/lang/AutoCloseable
     #8 = Class              #7           // java/lang/AutoCloseable
     #9 = Utf8               SourceFile
    #10 = Utf8               cav$1
    #11 = Class              #10          // cav$1
    #12 = Utf8               cbt$a
    #13 = Class              #12          // cbt$a
    #14 = Utf8               cbt
    #15 = Class              #14          // cbt
    #16 = Utf8               a
    #17 = Utf8               adi$c
    #18 = Class              #17          // adi$c
    #19 = Utf8               adi
    #20 = Class              #19          // adi
    #21 = Utf8               c
    #22 = Utf8               ctw$a
    #23 = Class              #22          // ctw$a
    #24 = Utf8               ctw
    #25 = Class              #24          // ctw
    #26 = Utf8               can$a
    #27 = Class              #26          // can$a
    #28 = Utf8               can
    #29 = Class              #28          // can
    #30 = Utf8               cra$b
    #31 = Class              #30          // cra$b
    #32 = Utf8               cra
    #33 = Class              #32          // cra
    #34 = Utf8               b
    #35 = Utf8               cbr$d
    #36 = Class              #35          // cbr$d
    #37 = Utf8               cbr
    #38 = Class              #37          // cbr
    #39 = Utf8               d
    #40 = Utf8               go$c
    #41 = Class              #40          // go$c
    #42 = Utf8               go
    #43 = Class              #42          // go
    #44 = Utf8               java/lang/invoke/MethodHandles$Lookup
    #45 = Class              #44          // java/lang/invoke/MethodHandles$Lookup
    #46 = Utf8               java/lang/invoke/MethodHandles
    #47 = Class              #46          // java/lang/invoke/MethodHandles
    #48 = Utf8               Lookup
    #49 = Utf8               Lcom/mojang/serialization/Codec;
    #50 = Utf8               Lcom/mojang/serialization/Codec<Lys<Lcav;>;>;
    #51 = Utf8               e
    #52 = Utf8               Lys;
    #53 = Utf8               Lys<Lcav;>;
    #54 = Utf8               f
    #55 = Utf8               g
    #56 = Utf8               h
    #57 = Utf8               I
    #58 = Integer            30000000
    #59 = Utf8               i
    #60 = Integer            512
    #61 = Utf8               j
    #62 = Integer            32
    #63 = Utf8               [Lgo;
    #64 = Utf8               k
    #65 = Integer            15
    #66 = Utf8               l
    #67 = Integer            24000
    #68 = Utf8               m
    #69 = Integer            20000000
    #70 = Utf8               n
    #71 = Integer            -20000000
    #72 = Utf8               o
    #73 = Utf8               Ljava/util/List;
    #74 = Utf8               Ljava/util/List<Lcny;>;
    #75 = Utf8               Z
    #76 = Utf8               y
    #77 = Utf8               Ljava/lang/Thread;
    #78 = Utf8               z
    #79 = Utf8               A
    #80 = Utf8               p
    #81 = Utf8               q
    #82 = Integer            1013904223
    #83 = Utf8               r
    #84 = Utf8               F
    #85 = Utf8               s
    #86 = Utf8               t
    #87 = Utf8               u
    #88 = Utf8               v
    #89 = Utf8               Ljava/util/Random;
    #90 = Utf8               B
    #91 = Utf8               Lcry;
    #92 = Utf8               C
    #93 = Utf8               Lgs;
    #94 = Utf8               Lgs<Lcry;>;
    #95 = Utf8               w
    #96 = Utf8               Ldkw;
    #97 = Utf8               D
    #98 = Utf8               Ljava/util/function/Supplier;
    #99 = Utf8               Ljava/util/function/Supplier<Lasy;>;
   #100 = Utf8               x
   #101 = Utf8               E
   #102 = Utf8               Lcql;
   #103 = Utf8               Lcbt;
   #104 = Utf8               G
   #105 = Utf8               H
   #106 = Utf8               J
   #107 = Utf8               <init>
   #108 = Utf8               (Ldkw;Lys;Lgs;Ljava/util/function/Supplier;ZZJ)V
   #109 = Utf8               (Ldkw;Lys<Lcav;>;Lgs<Lcry;>;Ljava/util/function/Supplier<Lasy;>;ZZJ)V
   #110 = Utf8               ()V
   #111 = NameAndType        #107:#110    // "<init>":()V
   #112 = Methodref          #4.#111      // java/lang/Object."<init>":()V
   #113 = Utf8               com/google/common/collect/Lists
   #114 = Class              #113         // com/google/common/collect/Lists
   #115 = Utf8               newArrayList
   #116 = Utf8               ()Ljava/util/ArrayList;
   #117 = NameAndType        #115:#116    // newArrayList:()Ljava/util/ArrayList;
   #118 = Methodref          #114.#117    // com/google/common/collect/Lists.newArrayList:()Ljava/util/ArrayList;
   #119 = NameAndType        #72:#73      // o:Ljava/util/List;
   #120 = Fieldref           #2.#119      // cav.o:Ljava/util/List;
   #121 = NameAndType        #34:#73      // b:Ljava/util/List;
   #122 = Fieldref           #2.#121      // cav.b:Ljava/util/List;
   #123 = Utf8               java/util/Random
   #124 = Class              #123         // java/util/Random
   #125 = Methodref          #124.#111    // java/util/Random."<init>":()V
   #126 = Utf8               nextInt
   #127 = Utf8               ()I
   #128 = NameAndType        #126:#127    // nextInt:()I
   #129 = Methodref          #124.#128    // java/util/Random.nextInt:()I
   #130 = NameAndType        #80:#57      // p:I
   #131 = Fieldref           #2.#130      // cav.p:I
   #132 = NameAndType        #81:#57      // q:I
   #133 = Fieldref           #2.#132      // cav.q:I
   #134 = NameAndType        #88:#89      // v:Ljava/util/Random;
   #135 = Fieldref           #2.#134      // cav.v:Ljava/util/Random;
   #136 = NameAndType        #97:#98      // D:Ljava/util/function/Supplier;
   #137 = Fieldref           #2.#136      // cav.D:Ljava/util/function/Supplier;
   #138 = NameAndType        #95:#96      // w:Ldkw;
   #139 = Fieldref           #2.#138      // cav.w:Ldkw;
   #140 = NameAndType        #92:#93      // C:Lgs;
   #141 = Fieldref           #2.#140      // cav.C:Lgs;
   #142 = Utf8               gs
   #143 = Class              #142         // gs
   #144 = Utf8               ()Ljava/lang/Object;
   #145 = NameAndType        #16:#144     // a:()Ljava/lang/Object;
   #146 = InterfaceMethodref #143.#145    // gs.a:()Ljava/lang/Object;
   #147 = Utf8               cry
   #148 = Class              #147         // cry
   #149 = NameAndType        #90:#91      // B:Lcry;
   #150 = Fieldref           #2.#149      // cav.B:Lcry;
   #151 = NameAndType        #104:#52     // G:Lys;
   #152 = Fieldref           #2.#151      // cav.G:Lys;
   #153 = NameAndType        #100:#75     // x:Z
   #154 = Fieldref           #2.#153      // cav.x:Z
   #155 = Utf8               ()D
   #156 = NameAndType        #51:#155     // e:()D
   #157 = Methodref          #148.#156    // cry.e:()D
   #158 = Utf8               (Lcav;)V
   #159 = NameAndType        #107:#158    // "<init>":(Lcav;)V
   #160 = Methodref          #11.#159     // cav$1."<init>":(Lcav;)V
   #161 = NameAndType        #101:#102    // E:Lcql;
   #162 = Fieldref           #2.#161      // cav.E:Lcql;
   #163 = Utf8               cql
   #164 = Class              #163         // cql
   #165 = Methodref          #164.#111    // cql."<init>":()V
   #166 = Utf8               java/lang/Thread
   #167 = Class              #166         // java/lang/Thread
   #168 = Utf8               currentThread
   #169 = Utf8               ()Ljava/lang/Thread;
   #170 = NameAndType        #168:#169    // currentThread:()Ljava/lang/Thread;
   #171 = Methodref          #167.#170    // java/lang/Thread.currentThread:()Ljava/lang/Thread;
   #172 = NameAndType        #76:#77      // y:Ljava/lang/Thread;
   #173 = Fieldref           #2.#172      // cav.y:Ljava/lang/Thread;
   #174 = Utf8               (Lcbt$a;J)V
   #175 = NameAndType        #107:#174    // "<init>":(Lcbt$a;J)V
   #176 = Methodref          #15.#175     // cbt."<init>":(Lcbt$a;J)V
   #177 = NameAndType        #84:#103     // F:Lcbt;
   #178 = Fieldref           #2.#177      // cav.F:Lcbt;
   #179 = NameAndType        #78:#75      // z:Z
   #180 = Fieldref           #2.#179      // cav.z:Z
   #181 = Utf8               this
   #182 = Utf8               Lcav;
   #183 = Utf8               $$0
   #184 = Utf8               $$1
   #185 = Utf8               $$2
   #186 = Utf8               $$3
   #187 = Utf8               $$4
   #188 = Utf8               $$5
   #189 = Utf8               $$6
   #190 = Utf8               k_
   #191 = Utf8               ()Z
   #192 = Utf8               ()Lnet/minecraft/server/MinecraftServer;
   #193 = Utf8               Ljavax/annotation/Nullable;
   #194 = Utf8               (Lgj;)Z
   #195 = NameAndType        #87:#194     // u:(Lgj;)Z
   #196 = Methodref          #2.#195      // cav.u:(Lgj;)Z
   #197 = NameAndType        #97:#194     // D:(Lgj;)Z
   #198 = Methodref          #2.#197      // cav.D:(Lgj;)Z
   #199 = Utf8               Lgj;
   #200 = Utf8               gj
   #201 = Class              #200         // gj
   #202 = NameAndType        #88:#127     // v:()I
   #203 = Methodref          #201.#202    // gj.v:()I
   #204 = Utf8               (I)Z
   #205 = NameAndType        #34:#204     // b:(I)Z
   #206 = Methodref          #2.#205      // cav.b:(I)Z
   #207 = NameAndType        #87:#127     // u:()I
   #208 = Methodref          #201.#207    // gj.u:()I
   #209 = Integer            -30000000
   #210 = NameAndType        #95:#127     // w:()I
   #211 = Methodref          #201.#210    // gj.w:()I
   #212 = Utf8               (Lgj;)Lcra;
   #213 = Utf8               hf
   #214 = Class              #213         // hf
   #215 = Utf8               (I)I
   #216 = NameAndType        #16:#215     // a:(I)I
   #217 = Methodref          #214.#216    // hf.a:(I)I
   #218 = Utf8               (II)Lcra;
   #219 = NameAndType        #39:#218     // d:(II)Lcra;
   #220 = Methodref          #2.#219      // cav.d:(II)Lcra;
   #221 = Utf8               cqt
   #222 = Class              #221         // cqt
   #223 = Utf8               Lcqt;
   #224 = NameAndType        #72:#223     // o:Lcqt;
   #225 = Fieldref           #222.#224    // cqt.o:Lcqt;
   #226 = Utf8               (IILcqt;)Lcqq;
   #227 = NameAndType        #16:#226     // a:(IILcqt;)Lcqq;
   #228 = Methodref          #2.#227      // cav.a:(IILcqt;)Lcqq;
   #229 = Utf8               (IILcqt;Z)Lcqq;
   #230 = Utf8               K
   #231 = Utf8               ()Lcqs;
   #232 = NameAndType        #230:#231    // K:()Lcqs;
   #233 = Methodref          #2.#232      // cav.K:()Lcqs;
   #234 = Utf8               cqs
   #235 = Class              #234         // cqs
   #236 = NameAndType        #16:#229     // a:(IILcqt;Z)Lcqq;
   #237 = Methodref          #235.#236    // cqs.a:(IILcqt;Z)Lcqq;
   #238 = Utf8               java/lang/IllegalStateException
   #239 = Class              #238         // java/lang/IllegalStateException
   #240 = Utf8               Should always be able to create a chunk!
   #241 = String             #240         // Should always be able to create a chunk!
   #242 = Utf8               (Ljava/lang/String;)V
   #243 = NameAndType        #107:#242    // "<init>":(Ljava/lang/String;)V
   #244 = Methodref          #239.#243    // java/lang/IllegalStateException."<init>":(Ljava/lang/String;)V
   #245 = Utf8               cqq
   #246 = Class              #245         // cqq
   #247 = Utf8               Lcqq;
   #248 = Utf8               (Lgj;Lcov;I)Z
   #249 = Utf8               (Lgj;Lcov;II)Z
   #250 = NameAndType        #16:#249     // a:(Lgj;Lcov;II)Z
   #251 = Methodref          #2.#250      // cav.a:(Lgj;Lcov;II)Z
   #252 = Utf8               Lcov;
   #253 = Utf8               ad
   #254 = NameAndType        #253:#191    // ad:()Z
   #255 = Methodref          #2.#254      // cav.ad:()Z
   #256 = NameAndType        #66:#212     // l:(Lgj;)Lcra;
   #257 = Methodref          #2.#256      // cav.l:(Lgj;)Lcra;
   #258 = Utf8               cov
   #259 = Class              #258         // cov
   #260 = Utf8               ()Lcdq;
   #261 = NameAndType        #34:#260     // b:()Lcdq;
   #262 = Methodref          #259.#261    // cov.b:()Lcdq;
   #263 = Utf8               cdq
   #264 = Class              #263         // cdq
   #265 = Utf8               (Lgj;Lcov;Z)Lcov;
   #266 = NameAndType        #16:#265     // a:(Lgj;Lcov;Z)Lcov;
   #267 = Methodref          #33.#266     // cra.a:(Lgj;Lcov;Z)Lcov;
   #268 = Utf8               a_
   #269 = Utf8               (Lgj;)Lcov;
   #270 = NameAndType        #268:#269    // a_:(Lgj;)Lcov;
   #271 = Methodref          #2.#270      // cav.a_:(Lgj;)Lcov;
   #272 = Utf8               (Lcab;Lgj;)I
   #273 = NameAndType        #34:#272     // b:(Lcab;Lgj;)I
   #274 = Methodref          #259.#273    // cov.b:(Lcab;Lgj;)I
   #275 = NameAndType        #54:#127     // f:()I
   #276 = Methodref          #259.#275    // cov.f:()I
   #277 = NameAndType        #51:#191     // e:()Z
   #278 = Methodref          #259.#277    // cov.e:()Z
   #279 = Utf8               ab
   #280 = Utf8               ()Lasy;
   #281 = NameAndType        #279:#280    // ab:()Lasy;
   #282 = Methodref          #2.#281      // cav.ab:()Lasy;
   #283 = Utf8               queueCheckLight
   #284 = String             #283         // queueCheckLight
   #285 = Utf8               asy
   #286 = Class              #285         // asy
   #287 = NameAndType        #16:#242     // a:(Ljava/lang/String;)V
   #288 = InterfaceMethodref #286.#287    // asy.a:(Ljava/lang/String;)V
   #289 = Utf8               ()Ldio;
   #290 = NameAndType        #70:#289     // n:()Ldio;
   #291 = Methodref          #235.#290    // cqs.n:()Ldio;
   #292 = Utf8               dio
   #293 = Class              #292         // dio
   #294 = Utf8               (Lgj;)V
   #295 = NameAndType        #16:#294     // a:(Lgj;)V
   #296 = Methodref          #293.#295    // dio.a:(Lgj;)V
   #297 = NameAndType        #21:#110     // c:()V
   #298 = InterfaceMethodref #286.#297    // asy.c:()V
   #299 = Utf8               (Lgj;Lcov;Lcov;)V
   #300 = NameAndType        #34:#299     // b:(Lgj;Lcov;Lcov;)V
   #301 = Methodref          #2.#300      // cav.b:(Lgj;Lcov;Lcov;)V
   #302 = Utf8               ()Ladi$c;
   #303 = NameAndType        #90:#302     // B:()Ladi$c;
   #304 = Methodref          #33.#303     // cra.B:()Ladi$c;
   #305 = Utf8               Ladi$c;
   #306 = NameAndType        #21:#305     // c:Ladi$c;
   #307 = Fieldref           #18.#306     // adi$c.c:Ladi$c;
   #308 = Utf8               (Ladi$c;)Z
   #309 = NameAndType        #16:#308     // a:(Ladi$c;)Z
   #310 = Methodref          #18.#309     // adi$c.a:(Ladi$c;)Z
   #311 = Utf8               (Lgj;Lcov;Lcov;I)V
   #312 = NameAndType        #16:#311     // a:(Lgj;Lcov;Lcov;I)V
   #313 = Methodref          #2.#312      // cav.a:(Lgj;Lcov;Lcov;I)V
   #314 = Utf8               (Lgj;Lcdq;)V
   #315 = NameAndType        #16:#314     // a:(Lgj;Lcdq;)V
   #316 = Methodref          #2.#315      // cav.a:(Lgj;Lcdq;)V
   #317 = NameAndType        #61:#191     // j:()Z
   #318 = Methodref          #259.#317    // cov.j:()Z
   #319 = NameAndType        #21:#314     // c:(Lgj;Lcdq;)V
   #320 = Methodref          #2.#319      // cav.c:(Lgj;Lcdq;)V
   #321 = Utf8               (Lcaw;Lgj;II)V
   #322 = NameAndType        #34:#321     // b:(Lcaw;Lgj;II)V
   #323 = Methodref          #259.#322    // cov.b:(Lcaw;Lgj;II)V
   #324 = NameAndType        #16:#321     // a:(Lcaw;Lgj;II)V
   #325 = Methodref          #259.#324    // cov.a:(Lcaw;Lgj;II)V
   #326 = NameAndType        #16:#299     // a:(Lgj;Lcov;Lcov;)V
   #327 = Methodref          #2.#326      // cav.a:(Lgj;Lcov;Lcov;)V
   #328 = Utf8               Lcra;
   #329 = Utf8               Lcdq;
   #330 = Utf8               $$7
   #331 = Utf8               $$8
   #332 = Utf8               (Lgj;Z)Z
   #333 = Utf8               b_
   #334 = Utf8               (Lgj;)Ldix;
   #335 = NameAndType        #333:#334    // b_:(Lgj;)Ldix;
   #336 = Methodref          #2.#335      // cav.b_:(Lgj;)Ldix;
   #337 = Utf8               dix
   #338 = Class              #337         // dix
   #339 = Utf8               ()Lcov;
   #340 = NameAndType        #55:#339     // g:()Lcov;
   #341 = Methodref          #338.#340    // dix.g:()Lcov;
   #342 = NameAndType        #16:#248     // a:(Lgj;Lcov;I)Z
   #343 = Methodref          #2.#342      // cav.a:(Lgj;Lcov;I)Z
   #344 = Utf8               Ldix;
   #345 = Utf8               (Lgj;ZLaxk;I)Z
   #346 = NameAndType        #55:#191     // g:()Z
   #347 = Methodref          #259.#346    // cov.g:()Z
   #348 = Utf8               cde
   #349 = Class              #348         // cde
   #350 = Utf8               (Lcov;)I
   #351 = NameAndType        #59:#350     // i:(Lcov;)I
   #352 = Methodref          #264.#351    // cdq.i:(Lcov;)I
   #353 = Utf8               (ILgj;I)V
   #354 = NameAndType        #21:#353     // c:(ILgj;I)V
   #355 = Methodref          #2.#354      // cav.c:(ILgj;I)V
   #356 = NameAndType        #70:#191     // n:()Z
   #357 = Methodref          #259.#356    // cov.n:()Z
   #358 = Utf8               c_
   #359 = Utf8               (Lgj;)Lcmr;
   #360 = NameAndType        #358:#359    // c_:(Lgj;)Lcmr;
   #361 = Methodref          #2.#360      // cav.c_:(Lgj;)Lcmr;
   #362 = Utf8               axk
   #363 = Class              #362         // axk
   #364 = Utf8               cmr
   #365 = Class              #364         // cmr
   #366 = Utf8               buw
   #367 = Class              #366         // buw
   #368 = Utf8               Lbuw;
   #369 = NameAndType        #34:#368     // b:Lbuw;
   #370 = Fieldref           #367.#369    // buw.b:Lbuw;
   #371 = Utf8               (Lcov;Lcav;Lgj;Lcmr;Laxk;Lbuw;)V
   #372 = NameAndType        #16:#371     // a:(Lcov;Lcav;Lgj;Lcmr;Laxk;Lbuw;)V
   #373 = Methodref          #264.#372    // cdq.a:(Lcov;Lcav;Lgj;Lcmr;Laxk;Lbuw;)V
   #374 = Utf8               csy
   #375 = Class              #374         // csy
   #376 = Utf8               Lcsy;
   #377 = NameAndType        #39:#376     // d:Lcsy;
   #378 = Fieldref           #375.#377    // csy.d:Lcsy;
   #379 = Utf8               (Laxk;Lcsy;Lgj;)V
   #380 = NameAndType        #16:#379     // a:(Laxk;Lcsy;Lgj;)V
   #381 = Methodref          #2.#380      // cav.a:(Laxk;Lcsy;Lgj;)V
   #382 = Utf8               Laxk;
   #383 = Utf8               Lcmr;
   #384 = Utf8               (Lgj;Lcov;)V
   #385 = Utf8               (Lgj;Lcov;)Z
   #386 = Utf8               ()Lgj;
   #387 = NameAndType        #54:#386     // f:()Lgj;
   #388 = Methodref          #201.#387    // gj.f:()Lgj;
   #389 = Utf8               (Lgj;Lcdq;Lgj;)V
   #390 = NameAndType        #16:#389     // a:(Lgj;Lcdq;Lgj;)V
   #391 = Methodref          #2.#390      // cav.a:(Lgj;Lcdq;Lgj;)V
   #392 = NameAndType        #55:#386     // g:()Lgj;
   #393 = Methodref          #201.#392    // gj.g:()Lgj;
   #394 = NameAndType        #21:#386     // c:()Lgj;
   #395 = Methodref          #201.#394    // gj.c:()Lgj;
   #396 = NameAndType        #34:#386     // b:()Lgj;
   #397 = Methodref          #201.#396    // gj.b:()Lgj;
   #398 = NameAndType        #39:#386     // d:()Lgj;
   #399 = Methodref          #201.#398    // gj.d:()Lgj;
   #400 = NameAndType        #51:#386     // e:()Lgj;
   #401 = Methodref          #201.#400    // gj.e:()Lgj;
   #402 = Utf8               (Lgj;Lcdq;Lgo;)V
   #403 = Utf8               Lgo;
   #404 = NameAndType        #51:#403     // e:Lgo;
   #405 = Fieldref           #43.#404     // go.e:Lgo;
   #406 = NameAndType        #54:#403     // f:Lgo;
   #407 = Fieldref           #43.#406     // go.f:Lgo;
   #408 = NameAndType        #16:#403     // a:Lgo;
   #409 = Fieldref           #43.#408     // go.a:Lgo;
   #410 = NameAndType        #34:#403     // b:Lgo;
   #411 = Fieldref           #43.#410     // go.b:Lgo;
   #412 = NameAndType        #21:#403     // c:Lgo;
   #413 = Fieldref           #43.#412     // go.c:Lgo;
   #414 = NameAndType        #39:#403     // d:Lgo;
   #415 = Fieldref           #43.#414     // go.d:Lgo;
   #416 = Utf8               java/lang/Throwable
   #417 = Class              #416         // java/lang/Throwable
   #418 = Utf8               (Lcav;Lgj;Lcdq;Lgj;Z)V
   #419 = NameAndType        #16:#418     // a:(Lcav;Lgj;Lcdq;Lgj;Z)V
   #420 = Methodref          #259.#419    // cov.a:(Lcav;Lgj;Lcdq;Lgj;Z)V
   #421 = Utf8               Exception while updating neighbours
   #422 = String             #421         // Exception while updating neighbours
   #423 = Class              #81          // q
   #424 = Utf8               (Ljava/lang/Throwable;Ljava/lang/String;)Lq;
   #425 = NameAndType        #16:#424     // a:(Ljava/lang/Throwable;Ljava/lang/String;)Lq;
   #426 = Methodref          #423.#425    // q.a:(Ljava/lang/Throwable;Ljava/lang/String;)Lq;
   #427 = Utf8               Block being updated
   #428 = String             #427         // Block being updated
   #429 = Utf8               (Ljava/lang/String;)Lr;
   #430 = NameAndType        #16:#429     // a:(Ljava/lang/String;)Lr;
   #431 = Methodref          #423.#430    // q.a:(Ljava/lang/String;)Lr;
   #432 = Utf8               Source block type
   #433 = String             #432         // Source block type
   #434 = MethodType         #144         //  ()Ljava/lang/Object;
   #435 = Utf8               (Lcdq;)Ljava/lang/String;
   #436 = NameAndType        #16:#435     // a:(Lcdq;)Ljava/lang/String;
   #437 = Methodref          #2.#436      // cav.a:(Lcdq;)Ljava/lang/String;
   #438 = MethodHandle       6:#437       // REF_invokeStatic cav.a:(Lcdq;)Ljava/lang/String;
   #439 = Utf8               ()Ljava/lang/String;
   #440 = MethodType         #439         //  ()Ljava/lang/String;
   #441 = Utf8               java/lang/invoke/LambdaMetafactory
   #442 = Class              #441         // java/lang/invoke/LambdaMetafactory
   #443 = Utf8               metafactory
   #444 = Utf8               (Ljava/lang/invoke/MethodHandles$Lookup;Ljava/lang/String;Ljava/lang/invoke/MethodType;Ljava/lang/invoke/MethodType;Ljava/lang/invoke/MethodHandle;Ljava/lang/invoke/MethodType;)Ljava/lang/invoke/CallSite;
   #445 = NameAndType        #443:#444    // metafactory:(Ljava/lang/invoke/MethodHandles$Lookup;Ljava/lang/String;Ljava/lang/invoke/MethodType;Ljava/lang/invoke/MethodType;Ljava/lang/invoke/MethodHandle;Ljava/lang/invoke/MethodType;)Ljava/lang/invoke/CallSite;
   #446 = Methodref          #442.#445    // java/lang/invoke/LambdaMetafactory.metafactory:(Ljava/lang/invoke/MethodHandles$Lookup;Ljava/lang/String;Ljava/lang/invoke/MethodType;Ljava/lang/invoke/MethodType;Ljava/lang/invoke/MethodHandle;Ljava/lang/invoke/MethodType;)Ljava/lang/invoke/CallSite;
   #447 = MethodHandle       6:#446       // REF_invokeStatic java/lang/invoke/LambdaMetafactory.metafactory:(Ljava/lang/invoke/MethodHandles$Lookup;Ljava/lang/String;Ljava/lang/invoke/MethodType;Ljava/lang/invoke/MethodType;Ljava/lang/invoke/MethodHandle;Ljava/lang/invoke/MethodType;)Ljava/lang/invoke/CallSite;
   #448 = Utf8               call
   #449 = Utf8               (Lcdq;)Ls;
   #450 = NameAndType        #448:#449    // call:(Lcdq;)Ls;
   #451 = InvokeDynamic      #0:#450      // #0:call:(Lcdq;)Ls;
   #452 = Class              #83          // r
   #453 = Utf8               (Ljava/lang/String;Ls;)Lr;
   #454 = NameAndType        #16:#453     // a:(Ljava/lang/String;Ls;)Lr;
   #455 = Methodref          #452.#454    // r.a:(Ljava/lang/String;Ls;)Lr;
   #456 = Utf8               (Lr;Lcax;Lgj;Lcov;)V
   #457 = NameAndType        #16:#456     // a:(Lr;Lcax;Lgj;Lcov;)V
   #458 = Methodref          #452.#457    // r.a:(Lr;Lcax;Lgj;Lcov;)V
   #459 = Class              #78          // z
   #460 = Utf8               (Lq;)V
   #461 = NameAndType        #107:#460    // "<init>":(Lq;)V
   #462 = Methodref          #459.#461    // z."<init>":(Lq;)V
   #463 = Utf8               Ljava/lang/Throwable;
   #464 = Utf8               Lq;
   #465 = Utf8               Lr;
   #466 = Utf8               (Lctw$a;II)I
   #467 = Utf8               m_
   #468 = NameAndType        #467:#127    // m_:()I
   #469 = Methodref          #2.#468      // cav.m_:()I
   #470 = Utf8               (II)Z
   #471 = NameAndType        #34:#470     // b:(II)Z
   #472 = Methodref          #2.#471      // cav.b:(II)Z
   #473 = NameAndType        #16:#466     // a:(Lctw$a;II)I
   #474 = Methodref          #33.#473     // cra.a:(Lctw$a;II)I
   #475 = Utf8               u_
   #476 = NameAndType        #475:#127    // u_:()I
   #477 = Methodref          #2.#476      // cav.u_:()I
   #478 = Utf8               Lctw$a;
   #479 = Utf8               l_
   #480 = Utf8               cdr
   #481 = Class              #480         // cdr
   #482 = Utf8               lo
   #483 = NameAndType        #482:#329    // lo:Lcdq;
   #484 = Fieldref           #481.#483    // cdr.lo:Lcdq;
   #485 = NameAndType        #70:#339     // n:()Lcov;
   #486 = Methodref          #264.#485    // cdq.n:()Lcov;
   #487 = Methodref          #33.#270     // cra.a_:(Lgj;)Lcov;
   #488 = Utf8               diy
   #489 = Class              #488         // diy
   #490 = Utf8               Ldiw;
   #491 = NameAndType        #16:#490     // a:Ldiw;
   #492 = Fieldref           #489.#491    // diy.a:Ldiw;
   #493 = Utf8               diw
   #494 = Class              #493         // diw
   #495 = Utf8               ()Ldix;
   #496 = NameAndType        #56:#495     // h:()Ldix;
   #497 = Methodref          #494.#496    // diw.h:()Ldix;
   #498 = Methodref          #33.#335     // cra.b_:(Lgj;)Ldix;
   #499 = Utf8               O
   #500 = Utf8               q_
   #501 = Utf8               ()Lcry;
   #502 = NameAndType        #500:#501    // q_:()Lcry;
   #503 = Methodref          #2.#502      // cav.q_:()Lcry;
   #504 = Methodref          #148.#356    // cry.n:()Z
   #505 = NameAndType        #79:#57      // A:I
   #506 = Fieldref           #2.#505      // cav.A:I
   #507 = Utf8               P
   #508 = NameAndType        #499:#191    // O:()Z
   #509 = Methodref          #2.#508      // cav.O:()Z
   #510 = Utf8               (Lboj;Lgj;Lahj;Lahl;FF)V
   #511 = Double             0.5d
   #513 = Utf8               (Lboj;DDDLahj;Lahl;FF)V
   #514 = NameAndType        #16:#513     // a:(Lboj;DDDLahj;Lahl;FF)V
   #515 = Methodref          #2.#514      // cav.a:(Lboj;DDDLahj;Lahl;FF)V
   #516 = Utf8               Lboj;
   #517 = Utf8               Lahj;
   #518 = Utf8               Lahl;
   #519 = Utf8               (Lboj;Laxk;Lahj;Lahl;FF)V
   #520 = Utf8               (DDDLahj;Lahl;FFZ)V
   #521 = Utf8               (Lia;DDDDDD)V
   #522 = Utf8               Lia;
   #523 = Utf8               (Lia;ZDDDDDD)V
   #524 = Utf8               (F)F
   #525 = NameAndType        #54:#524     // f:(F)F
   #526 = Methodref          #2.#525      // cav.f:(F)F
   #527 = Float              6.2831855f
   #528 = Utf8               (Lcny;)V
   #529 = NameAndType        #21:#75      // c:Z
   #530 = Fieldref           #2.#529      // cav.c:Z
   #531 = Utf8               cny
   #532 = Class              #531         // cny
   #533 = Utf8               java/util/List
   #534 = Class              #533         // java/util/List
   #535 = Utf8               add
   #536 = Utf8               (Ljava/lang/Object;)Z
   #537 = NameAndType        #535:#536    // add:(Ljava/lang/Object;)Z
   #538 = InterfaceMethodref #534.#537    // java/util/List.add:(Ljava/lang/Object;)Z
   #539 = Utf8               Lcny;
   #540 = Utf8               Q
   #541 = Utf8               blockEntities
   #542 = String             #541         // blockEntities
   #543 = Utf8               isEmpty
   #544 = NameAndType        #543:#191    // isEmpty:()Z
   #545 = InterfaceMethodref #534.#544    // java/util/List.isEmpty:()Z
   #546 = Utf8               addAll
   #547 = Utf8               (Ljava/util/Collection;)Z
   #548 = NameAndType        #546:#547    // addAll:(Ljava/util/Collection;)Z
   #549 = InterfaceMethodref #534.#548    // java/util/List.addAll:(Ljava/util/Collection;)Z
   #550 = Utf8               clear
   #551 = NameAndType        #550:#110    // clear:()V
   #552 = InterfaceMethodref #534.#551    // java/util/List.clear:()V
   #553 = Utf8               iterator
   #554 = Utf8               ()Ljava/util/Iterator;
   #555 = NameAndType        #553:#554    // iterator:()Ljava/util/Iterator;
   #556 = InterfaceMethodref #534.#555    // java/util/List.iterator:()Ljava/util/Iterator;
   #557 = Utf8               java/util/Iterator
   #558 = Class              #557         // java/util/Iterator
   #559 = Utf8               hasNext
   #560 = NameAndType        #559:#191    // hasNext:()Z
   #561 = InterfaceMethodref #558.#560    // java/util/Iterator.hasNext:()Z
   #562 = Utf8               next
   #563 = NameAndType        #562:#144    // next:()Ljava/lang/Object;
   #564 = InterfaceMethodref #558.#563    // java/util/Iterator.next:()Ljava/lang/Object;
   #565 = NameAndType        #34:#191     // b:()Z
   #566 = InterfaceMethodref #532.#565    // cny.b:()Z
   #567 = Utf8               remove
   #568 = NameAndType        #567:#110    // remove:()V
   #569 = InterfaceMethodref #558.#568    // java/util/Iterator.remove:()V
   #570 = InterfaceMethodref #532.#394    // cny.c:()Lgj;
   #571 = Utf8               cac
   #572 = Class              #571         // cac
   #573 = Utf8               (Lgj;)J
   #574 = NameAndType        #16:#573     // a:(Lgj;)J
   #575 = Methodref          #572.#574    // cac.a:(Lgj;)J
   #576 = Utf8               (J)Z
   #577 = NameAndType        #16:#576     // a:(J)Z
   #578 = Methodref          #2.#577      // cav.a:(J)Z
   #579 = NameAndType        #16:#110     // a:()V
   #580 = InterfaceMethodref #532.#579    // cny.a:()V
   #581 = Utf8               Lasy;
   #582 = Utf8               Ljava/util/Iterator<Lcny;>;
   #583 = Utf8               Ljava/util/Iterator;
   #584 = Utf8               (Ljava/util/function/Consumer;Laxk;)V
   #585 = Utf8               <T:Laxk;>(Ljava/util/function/Consumer<TT;>;TT;)V
   #586 = Utf8               java/util/function/Consumer
   #587 = Class              #586         // java/util/function/Consumer
   #588 = Utf8               accept
   #589 = Utf8               (Ljava/lang/Object;)V
   #590 = NameAndType        #588:#589    // accept:(Ljava/lang/Object;)V
   #591 = InterfaceMethodref #587.#590    // java/util/function/Consumer.accept:(Ljava/lang/Object;)V
   #592 = Utf8               Ticking entity
   #593 = String             #592         // Ticking entity
   #594 = Utf8               Entity being ticked
   #595 = String             #594         // Entity being ticked
   #596 = Utf8               (Lr;)V
   #597 = NameAndType        #16:#596     // a:(Lr;)V
   #598 = Methodref          #363.#597    // axk.a:(Lr;)V
   #599 = Utf8               Ljava/util/function/Consumer<TT;>;
   #600 = Utf8               Ljava/util/function/Consumer;
   #601 = Utf8               TT;
   #602 = Utf8               (Laxk;)Z
   #603 = Utf8               (Laxk;DDDFLcan$a;)Lcan;
   #604 = Utf8               (Laxk;Lawu;Lcao;DDDFZLcan$a;)Lcan;
   #605 = NameAndType        #16:#604     // a:(Laxk;Lawu;Lcao;DDDFZLcan$a;)Lcan;
   #606 = Methodref          #2.#605      // cav.a:(Laxk;Lawu;Lcao;DDDFZLcan$a;)Lcan;
   #607 = Utf8               Lcan$a;
   #608 = Utf8               (Laxk;DDDFZLcan$a;)Lcan;
   #609 = Utf8               (Lcav;Laxk;Lawu;Lcao;DDDFZLcan$a;)V
   #610 = NameAndType        #107:#609    // "<init>":(Lcav;Laxk;Lawu;Lcao;DDDFZLcan$a;)V
   #611 = Methodref          #29.#610     // can."<init>":(Lcav;Laxk;Lawu;Lcao;DDDFZLcan$a;)V
   #612 = Methodref          #29.#579     // can.a:()V
   #613 = Utf8               (Z)V
   #614 = NameAndType        #16:#613     // a:(Z)V
   #615 = Methodref          #29.#614     // can.a:(Z)V
   #616 = Utf8               Lawu;
   #617 = Utf8               Lcao;
   #618 = Utf8               $$9
   #619 = Utf8               Lcan;
   #620 = Utf8               Lcra$b;
   #621 = NameAndType        #16:#620     // a:Lcra$b;
   #622 = Fieldref           #31.#621     // cra$b.a:Lcra$b;
   #623 = Utf8               (Lgj;Lcra$b;)Lcmr;
   #624 = NameAndType        #16:#623     // a:(Lgj;Lcra$b;)Lcmr;
   #625 = Methodref          #33.#624     // cra.a:(Lgj;Lcra$b;)Lcmr;
   #626 = Utf8               (Lcmr;)V
   #627 = NameAndType        #80:#386     // p:()Lgj;
   #628 = Methodref          #365.#627    // cmr.p:()Lgj;
   #629 = NameAndType        #34:#626     // b:(Lcmr;)V
   #630 = Methodref          #33.#629     // cra.b:(Lcmr;)V
   #631 = NameAndType        #39:#294     // d:(Lgj;)V
   #632 = Methodref          #33.#631     // cra.d:(Lgj;)V
   #633 = Methodref          #235.#471    // cqs.b:(II)Z
   #634 = Utf8               (Lgj;Laxk;Lgo;)Z
   #635 = Methodref          #2.#236      // cav.a:(IILcqt;Z)Lcqq;
   #636 = Methodref          #246.#270    // cqq.a_:(Lgj;)Lcov;
   #637 = Utf8               (Lcab;Lgj;Laxk;Lgo;)Z
   #638 = NameAndType        #16:#637     // a:(Lcab;Lgj;Laxk;Lgo;)Z
   #639 = Methodref          #259.#638    // cov.a:(Lcab;Lgj;Laxk;Lgo;)Z
   #640 = Utf8               (Lgj;Laxk;)Z
   #641 = NameAndType        #16:#634     // a:(Lgj;Laxk;Lgo;)Z
   #642 = Methodref          #2.#641      // cav.a:(Lgj;Laxk;Lgo;)Z
   #643 = Utf8               R
   #644 = NameAndType        #39:#524     // d:(F)F
   #645 = Methodref          #2.#644      // cav.d:(F)F
   #646 = Float              5.0f
   #647 = Double             16.0d
   #649 = NameAndType        #34:#524     // b:(F)F
   #650 = Methodref          #2.#649      // cav.b:(F)F
   #651 = Double             2.0d
   #653 = Utf8               ajl
   #654 = Class              #653         // ajl
   #655 = Methodref          #654.#649    // ajl.b:(F)F
   #656 = Double             -0.25d
   #658 = Double             0.25d
   #660 = Utf8               (DDD)D
   #661 = NameAndType        #16:#660     // a:(DDD)D
   #662 = Methodref          #654.#661    // ajl.a:(DDD)D
   #663 = Double             11.0d
   #665 = Utf8               (ZZ)V
   #666 = NameAndType        #16:#665     // a:(ZZ)V
   #667 = Methodref          #235.#666    // cqs.a:(ZZ)V
   #668 = Utf8               S
   #669 = Utf8               dkw
   #670 = Class              #669         // dkw
   #671 = NameAndType        #64:#191     // k:()Z
   #672 = InterfaceMethodref #670.#671    // dkw.k:()Z
   #673 = NameAndType        #85:#84      // s:F
   #674 = Fieldref           #2.#673      // cav.s:F
   #675 = NameAndType        #59:#191     // i:()Z
   #676 = InterfaceMethodref #670.#675    // dkw.i:()Z
   #677 = NameAndType        #87:#84      // u:F
   #678 = Fieldref           #2.#677      // cav.u:F
   #679 = Utf8               close
   #680 = Utf8               java/io/IOException
   #681 = Class              #680         // java/io/IOException
   #682 = NameAndType        #679:#110    // close:()V
   #683 = Methodref          #235.#682    // cqs.close:()V
   #684 = Utf8               (II)Lcab;
   #685 = Utf8               (Laxk;Ldpj;Ljava/util/function/Predicate;)Ljava/util/List;
   #686 = Utf8               (Laxk;Ldpj;Ljava/util/function/Predicate<-Laxk;>;)Ljava/util/List<Laxk;>;
   #687 = Utf8               getEntities
   #688 = String             #687         // getEntities
   #689 = NameAndType        #39:#242     // d:(Ljava/lang/String;)V
   #690 = InterfaceMethodref #286.#689    // asy.d:(Ljava/lang/String;)V
   #691 = Utf8               ()Lcsp;
   #692 = NameAndType        #105:#691    // H:()Lcsp;
   #693 = Methodref          #2.#692      // cav.H:()Lcsp;
   #694 = MethodType         #589         //  (Ljava/lang/Object;)V
   #695 = Utf8               (Laxk;Ljava/util/function/Predicate;Ljava/util/List;Laxk;)V
   #696 = NameAndType        #16:#695     // a:(Laxk;Ljava/util/function/Predicate;Ljava/util/List;Laxk;)V
   #697 = Methodref          #2.#696      // cav.a:(Laxk;Ljava/util/function/Predicate;Ljava/util/List;Laxk;)V
   #698 = MethodHandle       6:#697       // REF_invokeStatic cav.a:(Laxk;Ljava/util/function/Predicate;Ljava/util/List;Laxk;)V
   #699 = Utf8               (Laxk;)V
   #700 = MethodType         #699         //  (Laxk;)V
   #701 = Utf8               (Laxk;Ljava/util/function/Predicate;Ljava/util/List;)Ljava/util/function/Consumer;
   #702 = NameAndType        #588:#701    // accept:(Laxk;Ljava/util/function/Predicate;Ljava/util/List;)Ljava/util/function/Consumer;
   #703 = InvokeDynamic      #1:#702      // #1:accept:(Laxk;Ljava/util/function/Predicate;Ljava/util/List;)Ljava/util/function/Consumer;
   #704 = Utf8               csp
   #705 = Class              #704         // csp
   #706 = Utf8               (Ldpj;Ljava/util/function/Consumer;)V
   #707 = NameAndType        #16:#706     // a:(Ldpj;Ljava/util/function/Consumer;)V
   #708 = InterfaceMethodref #705.#707    // csp.a:(Ldpj;Ljava/util/function/Consumer;)V
   #709 = Utf8               Ldpj;
   #710 = Utf8               Ljava/util/function/Predicate<-Laxk;>;
   #711 = Utf8               Ljava/util/function/Predicate;
   #712 = Utf8               Ljava/util/List<Laxk;>;
   #713 = Utf8               (Lcsn;Ldpj;Ljava/util/function/Predicate;)Ljava/util/List;
   #714 = Utf8               <T:Laxk;>(Lcsn<Laxk;TT;>;Ldpj;Ljava/util/function/Predicate<-TT;>;)Ljava/util/List<TT;>;
   #715 = Utf8               (Ljava/util/function/Predicate;Ljava/util/List;Lcsn;Laxk;)V
   #716 = NameAndType        #16:#715     // a:(Ljava/util/function/Predicate;Ljava/util/List;Lcsn;Laxk;)V
   #717 = Methodref          #2.#716      // cav.a:(Ljava/util/function/Predicate;Ljava/util/List;Lcsn;Laxk;)V
   #718 = MethodHandle       6:#717       // REF_invokeStatic cav.a:(Ljava/util/function/Predicate;Ljava/util/List;Lcsn;Laxk;)V
   #719 = Utf8               (Ljava/util/function/Predicate;Ljava/util/List;Lcsn;)Ljava/util/function/Consumer;
   #720 = NameAndType        #588:#719    // accept:(Ljava/util/function/Predicate;Ljava/util/List;Lcsn;)Ljava/util/function/Consumer;
   #721 = InvokeDynamic      #2:#720      // #2:accept:(Ljava/util/function/Predicate;Ljava/util/List;Lcsn;)Ljava/util/function/Consumer;
   #722 = Utf8               (Lcsn;Ldpj;Ljava/util/function/Consumer;)V
   #723 = NameAndType        #16:#722     // a:(Lcsn;Ldpj;Ljava/util/function/Consumer;)V
   #724 = InterfaceMethodref #705.#723    // csp.a:(Lcsn;Ldpj;Ljava/util/function/Consumer;)V
   #725 = Utf8               Lcsn<Laxk;TT;>;
   #726 = Utf8               Lcsn;
   #727 = Utf8               Ljava/util/function/Predicate<-TT;>;
   #728 = Utf8               Ljava/util/List<TT;>;
   #729 = Utf8               (I)Laxk;
   #730 = NameAndType        #92:#194     // C:(Lgj;)Z
   #731 = Methodref          #2.#730      // cav.C:(Lgj;)Z
   #732 = Methodref          #33.#614     // cra.a:(Z)V
   #733 = Utf8               (Lgj;)I
   #734 = Utf8               (Lgj;Lgo;)I
   #735 = NameAndType        #21:#734     // c:(Lgj;Lgo;)I
   #736 = Methodref          #2.#735      // cav.c:(Lgj;Lgo;)I
   #737 = Utf8               java/lang/Math
   #738 = Class              #737         // java/lang/Math
   #739 = Utf8               max
   #740 = Utf8               (II)I
   #741 = NameAndType        #739:#740    // max:(II)I
   #742 = Methodref          #738.#741    // java/lang/Math.max:(II)I
   #743 = Utf8               (Lgj;Lgo;)Z
   #744 = NameAndType        #34:#734     // b:(Lgj;Lgo;)I
   #745 = Methodref          #2.#744      // cav.b:(Lgj;Lgo;)I
   #746 = Utf8               (Lcab;Lgj;Lgo;)I
   #747 = NameAndType        #34:#746     // b:(Lcab;Lgj;Lgo;)I
   #748 = Methodref          #259.#747    // cov.b:(Lcab;Lgj;Lgo;)I
   #749 = Utf8               (Lcab;Lgj;)Z
   #750 = NameAndType        #55:#749     // g:(Lcab;Lgj;)Z
   #751 = Methodref          #259.#750    // cov.g:(Lcab;Lgj;)Z
   #752 = NameAndType        #80:#733     // p:(Lgj;)I
   #753 = Methodref          #2.#752      // cav.p:(Lgj;)I
   #754 = NameAndType        #16:#63      // a:[Lgo;
   #755 = Fieldref           #2.#754      // cav.a:[Lgo;
   #756 = Class              #63          // "[Lgo;"
   #757 = Utf8               (Lgo;)Lgj;
   #758 = NameAndType        #16:#757     // a:(Lgo;)Lgj;
   #759 = Methodref          #201.#758    // gj.a:(Lgo;)Lgj;
   #760 = Utf8               T
   #761 = Utf8               U
   #762 = Utf8               ()J
   #763 = NameAndType        #51:#762     // e:()J
   #764 = InterfaceMethodref #670.#763    // dkw.e:()J
   #765 = Utf8               V
   #766 = NameAndType        #54:#762     // f:()J
   #767 = InterfaceMethodref #670.#766    // dkw.f:()J
   #768 = Utf8               (Lboj;Lgj;)Z
   #769 = Utf8               (Laxk;B)V
   #770 = Utf8               (Lgj;Lcdq;II)V
   #771 = Utf8               (Lcav;Lgj;II)Z
   #772 = NameAndType        #16:#771     // a:(Lcav;Lgj;II)Z
   #773 = Methodref          #259.#772    // cov.a:(Lcav;Lgj;II)Z
   #774 = Utf8               n_
   #775 = Utf8               ()Ldkm;
   #776 = Utf8               W
   #777 = Utf8               ()Lcar;
   #778 = NameAndType        #81:#777     // q:()Lcar;
   #779 = InterfaceMethodref #670.#778    // dkw.q:()Lcar;
   #780 = NameAndType        #86:#84      // t:F
   #781 = Fieldref           #2.#780      // cav.t:F
   #782 = Utf8               (FFF)F
   #783 = NameAndType        #59:#782     // i:(FFF)F
   #784 = Methodref          #654.#783    // ajl.i:(FFF)F
   #785 = Utf8               (F)V
   #786 = NameAndType        #16:#782     // a:(FFF)F
   #787 = Methodref          #654.#786    // ajl.a:(FFF)F
   #788 = NameAndType        #83:#84      // r:F
   #789 = Fieldref           #2.#788      // cav.r:F
   #790 = Utf8               X
   #791 = NameAndType        #16:#191     // a:()Z
   #792 = Methodref          #148.#791    // cry.a:()Z
   #793 = Methodref          #148.#565    // cry.b:()Z
   #794 = Double             0.9d
   #796 = Utf8               Y
   #797 = Double             0.2d
   #799 = NameAndType        #796:#191    // Y:()Z
   #800 = Methodref          #2.#799      // cav.Y:()Z
   #801 = NameAndType        #55:#194     // g:(Lgj;)Z
   #802 = Methodref          #2.#801      // cav.g:(Lgj;)Z
   #803 = NameAndType        #51:#478     // e:Lctw$a;
   #804 = Fieldref           #23.#803     // ctw$a.e:Lctw$a;
   #805 = Utf8               (Lctw$a;Lgj;)Lgj;
   #806 = NameAndType        #16:#805     // a:(Lctw$a;Lgj;)Lgj;
   #807 = Methodref          #2.#806      // cav.a:(Lctw$a;Lgj;)Lgj;
   #808 = Utf8               (Lgj;)Lgs;
   #809 = NameAndType        #88:#808     // v:(Lgj;)Lgs;
   #810 = Methodref          #2.#809      // cav.v:(Lgj;)Lgs;
   #811 = Utf8               ()Lcbr$d;
   #812 = NameAndType        #21:#811     // c:()Lcbr$d;
   #813 = Methodref          #38.#812     // cbr.c:()Lcbr$d;
   #814 = Utf8               Lcbr$d;
   #815 = NameAndType        #34:#814     // b:Lcbr$d;
   #816 = Fieldref           #36.#815     // cbr$d.b:Lcbr$d;
   #817 = NameAndType        #34:#194     // b:(Lgj;)Z
   #818 = Methodref          #38.#817     // cbr.b:(Lgj;)Z
   #819 = Utf8               Lcbr;
   #820 = NameAndType        #39:#191     // d:()Z
   #821 = Methodref          #38.#820     // cbr.d:()Z
   #822 = Utf8               (Ljava/lang/String;)Ldkf;
   #823 = Utf8               (Ljava/lang/String;Ldkf;)V
   #824 = Utf8               (Lq;)Lr;
   #825 = Utf8               Affected level
   #826 = String             #825         // Affected level
   #827 = Utf8               (Ljava/lang/String;I)Lr;
   #828 = NameAndType        #16:#827     // a:(Ljava/lang/String;I)Lr;
   #829 = Methodref          #423.#828    // q.a:(Ljava/lang/String;I)Lr;
   #830 = Utf8               All players
   #831 = String             #830         // All players
   #832 = NameAndType        #72:#439     // o:()Ljava/lang/String;
   #833 = Methodref          #2.#832      // cav.o:()Ljava/lang/String;
   #834 = MethodHandle       5:#833       // REF_invokeVirtual cav.o:()Ljava/lang/String;
   #835 = Utf8               (Lcav;)Ls;
   #836 = NameAndType        #448:#835    // call:(Lcav;)Ls;
   #837 = InvokeDynamic      #3:#836      // #3:call:(Lcav;)Ls;
   #838 = Utf8               Chunk stats
   #839 = String             #838         // Chunk stats
   #840 = Utf8               java/util/Objects
   #841 = Class              #840         // java/util/Objects
   #842 = Utf8               requireNonNull
   #843 = Utf8               (Ljava/lang/Object;)Ljava/lang/Object;
   #844 = NameAndType        #842:#843    // requireNonNull:(Ljava/lang/Object;)Ljava/lang/Object;
   #845 = Methodref          #841.#844    // java/util/Objects.requireNonNull:(Ljava/lang/Object;)Ljava/lang/Object;
   #846 = NameAndType        #51:#439     // e:()Ljava/lang/String;
   #847 = Methodref          #235.#846    // cqs.e:()Ljava/lang/String;
   #848 = MethodHandle       5:#847       // REF_invokeVirtual cqs.e:()Ljava/lang/String;
   #849 = Utf8               (Lcqs;)Ls;
   #850 = NameAndType        #448:#849    // call:(Lcqs;)Ls;
   #851 = InvokeDynamic      #4:#850      // #4:call:(Lcqs;)Ls;
   #852 = Utf8               Level dimension
   #853 = String             #852         // Level dimension
   #854 = NameAndType        #16:#439     // a:()Ljava/lang/String;
   #855 = Methodref          #2.#854      // cav.a:()Ljava/lang/String;
   #856 = MethodHandle       5:#855       // REF_invokeVirtual cav.a:()Ljava/lang/String;
   #857 = InvokeDynamic      #5:#836      // #5:call:(Lcav;)Ls;
   #858 = Utf8               (Lr;Lcax;)V
   #859 = NameAndType        #16:#858     // a:(Lr;Lcax;)V
   #860 = InterfaceMethodref #670.#859    // dkw.a:(Lr;Lcax;)V
   #861 = Utf8               Level Data Unobtainable
   #862 = String             #861         // Level Data Unobtainable
   #863 = Utf8               (Ljava/lang/String;Ljava/lang/Throwable;)V
   #864 = NameAndType        #16:#863     // a:(Ljava/lang/String;Ljava/lang/Throwable;)V
   #865 = Methodref          #452.#864    // r.a:(Ljava/lang/String;Ljava/lang/Throwable;)V
   #866 = Utf8               (DDDDDDLok;)V
   #867 = Utf8               Lok;
   #868 = Utf8               ()Ldqm;
   #869 = Utf8               Lgo$c;
   #870 = NameAndType        #16:#869     // a:Lgo$c;
   #871 = Fieldref           #41.#870     // go$c.a:Lgo$c;
   #872 = Methodref          #41.#555     // go$c.iterator:()Ljava/util/Iterator;
   #873 = Utf8               fH
   #874 = NameAndType        #873:#329    // fH:Lcdq;
   #875 = Fieldref           #481.#874    // cdr.fH:Lcdq;
   #876 = Utf8               (Lcdq;)Z
   #877 = NameAndType        #16:#876     // a:(Lcdq;)Z
   #878 = Methodref          #259.#877    // cov.a:(Lcdq;)Z
   #879 = Utf8               d_
   #880 = Utf8               (Lgj;)Lawf;
   #881 = Utf8               ak
   #882 = Utf8               ()F
   #883 = NameAndType        #881:#882    // ak:()F
   #884 = Methodref          #2.#883      // cav.ak:()F
   #885 = NameAndType        #87:#762     // u:()J
   #886 = Methodref          #33.#885     // cra.u:()J
   #887 = Utf8               awf
   #888 = Class              #887         // awf
   #889 = Utf8               af
   #890 = Utf8               ()Lawe;
   #891 = NameAndType        #889:#890    // af:()Lawe;
   #892 = Methodref          #2.#891      // cav.af:()Lawe;
   #893 = NameAndType        #765:#762    // V:()J
   #894 = Methodref          #2.#893      // cav.V:()J
   #895 = Utf8               (Lawe;JJF)V
   #896 = NameAndType        #107:#895    // "<init>":(Lawe;JJF)V
   #897 = Methodref          #888.#896    // awf."<init>":(Lawe;JJF)V
   #898 = Utf8               o_
   #899 = Utf8               (I)V
   #900 = Utf8               p_
   #901 = Utf8               ()Lcql;
   #902 = Utf8               (Lrc;)V
   #903 = Utf8               (Lrc<*>;)V
   #904 = Utf8               java/lang/UnsupportedOperationException
   #905 = Class              #904         // java/lang/UnsupportedOperationException
   #906 = Utf8               Can\'t send packets to server unless you\'re on the client.
   #907 = String             #906         // Can\'t send packets to server unless you\'re on the client.
   #908 = Methodref          #905.#243    // java/lang/UnsupportedOperationException."<init>":(Ljava/lang/String;)V
   #909 = Utf8               Lrc<*>;
   #910 = Utf8               Lrc;
   #911 = Utf8               ()Lgs;
   #912 = Utf8               ()Lgs<Lcry;>;
   #913 = Utf8               aa
   #914 = Utf8               ()Lys;
   #915 = Utf8               ()Lys<Lcav;>;
   #916 = Utf8               r_
   #917 = Utf8               ()Ljava/util/Random;
   #918 = Utf8               (Lgj;Ljava/util/function/Predicate;)Z
   #919 = Utf8               (Lgj;Ljava/util/function/Predicate<Lcov;>;)Z
   #920 = Utf8               java/util/function/Predicate
   #921 = Class              #920         // java/util/function/Predicate
   #922 = Utf8               test
   #923 = NameAndType        #922:#536    // test:(Ljava/lang/Object;)Z
   #924 = InterfaceMethodref #921.#923    // java/util/function/Predicate.test:(Ljava/lang/Object;)Z
   #925 = Utf8               Ljava/util/function/Predicate<Lcov;>;
   #926 = Utf8               (Lgj;Ljava/util/function/Predicate<Ldix;>;)Z
   #927 = Utf8               Ljava/util/function/Predicate<Ldix;>;
   #928 = Utf8               ()Lbxp;
   #929 = Utf8               (IIII)Lgj;
   #930 = Utf8               (III)V
   #931 = NameAndType        #107:#930    // "<init>":(III)V
   #932 = Methodref          #201.#931    // gj."<init>":(III)V
   #933 = Utf8               java/util/function/Supplier
   #934 = Class              #933         // java/util/function/Supplier
   #935 = Utf8               get
   #936 = NameAndType        #935:#144    // get:()Ljava/lang/Object;
   #937 = InterfaceMethodref #934.#936    // java/util/function/Supplier.get:()Ljava/lang/Object;
   #938 = Utf8               ac
   #939 = Utf8               ()Ljava/util/function/Supplier;
   #940 = Utf8               ()Ljava/util/function/Supplier<Lasy;>;
   #941 = Utf8               s_
   #942 = Utf8               ()Lcbt;
   #943 = Utf8               ()Lcsp<Laxk;>;
   #944 = Utf8               (Laxk;Lcsy;Lgj;I)V
   #945 = NameAndType        #16:#218     // a:(II)Lcra;
   #946 = Methodref          #235.#945    // cqs.a:(II)Lcra;
   #947 = Utf8               (I)Lcsz;
   #948 = NameAndType        #16:#947     // a:(I)Lcsz;
   #949 = Methodref          #246.#948    // cqq.a:(I)Lcsz;
   #950 = Utf8               csz
   #951 = Class              #950         // csz
   #952 = Utf8               (Lcsy;Laxk;Lgj;)V
   #953 = NameAndType        #16:#952     // a:(Lcsy;Laxk;Lgj;)V
   #954 = InterfaceMethodref #951.#953    // csz.a:(Lcsy;Laxk;Lgj;)V
   #955 = Utf8               $$10
   #956 = Utf8               $$11
   #957 = Utf8               $$12
   #958 = Utf8               $$13
   #959 = Utf8               t_
   #960 = NameAndType        #105:#106    // H:J
   #961 = Fieldref           #2.#960      // cav.H:J
   #962 = Utf8               (II)Lcqq;
   #963 = Utf8               java/lang/Exception
   #964 = Class              #963         // java/lang/Exception
   #965 = NameAndType        #913:#914    // aa:()Lys;
   #966 = Methodref          #2.#965      // cav.aa:()Lys;
   #967 = Utf8               ys
   #968 = Class              #967         // ys
   #969 = Utf8               ()Lyt;
   #970 = NameAndType        #16:#969     // a:()Lyt;
   #971 = Methodref          #968.#970    // ys.a:()Lyt;
   #972 = Utf8               yt
   #973 = Class              #972         // yt
   #974 = Utf8               toString
   #975 = NameAndType        #974:#439    // toString:()Ljava/lang/String;
   #976 = Methodref          #973.#975    // yt.toString:()Ljava/lang/String;
   #977 = Utf8               ()Ljava/util/List;
   #978 = NameAndType        #76:#977     // y:()Ljava/util/List;
   #979 = Methodref          #2.#978      // cav.y:()Ljava/util/List;
   #980 = Utf8               size
   #981 = NameAndType        #980:#127    // size:()I
   #982 = InterfaceMethodref #534.#981    // java/util/List.size:()I
   #983 = Utf8               \u0001 total; \u0001
   #984 = String             #983         // \u0001 total; \u0001
   #985 = Utf8               java/lang/invoke/StringConcatFactory
   #986 = Class              #985         // java/lang/invoke/StringConcatFactory
   #987 = Utf8               makeConcatWithConstants
   #988 = Utf8               (Ljava/lang/invoke/MethodHandles$Lookup;Ljava/lang/String;Ljava/lang/invoke/MethodType;Ljava/lang/String;[Ljava/lang/Object;)Ljava/lang/invoke/CallSite;
   #989 = NameAndType        #987:#988    // makeConcatWithConstants:(Ljava/lang/invoke/MethodHandles$Lookup;Ljava/lang/String;Ljava/lang/invoke/MethodType;Ljava/lang/String;[Ljava/lang/Object;)Ljava/lang/invoke/CallSite;
   #990 = Methodref          #986.#989    // java/lang/invoke/StringConcatFactory.makeConcatWithConstants:(Ljava/lang/invoke/MethodHandles$Lookup;Ljava/lang/String;Ljava/lang/invoke/MethodType;Ljava/lang/String;[Ljava/lang/Object;)Ljava/lang/invoke/CallSite;
   #991 = MethodHandle       6:#990       // REF_invokeStatic java/lang/invoke/StringConcatFactory.makeConcatWithConstants:(Ljava/lang/invoke/MethodHandles$Lookup;Ljava/lang/String;Ljava/lang/invoke/MethodType;Ljava/lang/String;[Ljava/lang/Object;)Ljava/lang/invoke/CallSite;
   #992 = Utf8               (ILjava/util/List;)Ljava/lang/String;
   #993 = NameAndType        #987:#992    // makeConcatWithConstants:(ILjava/util/List;)Ljava/lang/String;
   #994 = InvokeDynamic      #6:#993      // #6:makeConcatWithConstants:(ILjava/util/List;)Ljava/lang/String;
   #995 = Utf8               bkd
   #996 = Class              #995         // bkd
   #997 = Utf8               ()[Lbkb;
   #998 = NameAndType        #86:#997     // t:()[Lbkb;
   #999 = Methodref          #996.#998    // bkd.t:()[Lbkb;
  #1000 = Utf8               csn
  #1001 = Class              #1000        // csn
  #1002 = Utf8               [Lbkb;
  #1003 = Class              #1002        // "[Lbkb;"
  #1004 = NameAndType        #16:#843     // a:(Ljava/lang/Object;)Ljava/lang/Object;
  #1005 = InterfaceMethodref #1001.#1004  // csn.a:(Ljava/lang/Object;)Ljava/lang/Object;
  #1006 = Utf8               Lbkd;
  #1007 = Utf8               Lbkb;
  #1008 = Utf8               ID #%s (%s // %s)
  #1009 = String             #1008        // ID #%s (%s // %s)
  #1010 = Utf8               hb
  #1011 = Class              #1010        // hb
  #1012 = Utf8               Lgn;
  #1013 = NameAndType        #761:#1012   // U:Lgn;
  #1014 = Fieldref           #1011.#1013  // hb.U:Lgn;
  #1015 = Utf8               gn
  #1016 = Class              #1015        // gn
  #1017 = Utf8               (Ljava/lang/Object;)Lyt;
  #1018 = NameAndType        #34:#1017    // b:(Ljava/lang/Object;)Lyt;
  #1019 = Methodref          #1016.#1018  // gn.b:(Ljava/lang/Object;)Lyt;
  #1020 = NameAndType        #56:#439     // h:()Ljava/lang/String;
  #1021 = Methodref          #264.#1020   // cdq.h:()Ljava/lang/String;
  #1022 = Utf8               getClass
  #1023 = Utf8               ()Ljava/lang/Class;
  #1024 = NameAndType        #1022:#1023  // getClass:()Ljava/lang/Class;
  #1025 = Methodref          #4.#1024     // java/lang/Object.getClass:()Ljava/lang/Class;
  #1026 = Utf8               java/lang/Class
  #1027 = Class              #1026        // java/lang/Class
  #1028 = Utf8               getCanonicalName
  #1029 = NameAndType        #1028:#439   // getCanonicalName:()Ljava/lang/String;
  #1030 = Methodref          #1027.#1029  // java/lang/Class.getCanonicalName:()Ljava/lang/String;
  #1031 = Utf8               java/lang/String
  #1032 = Class              #1031        // java/lang/String
  #1033 = Utf8               format
  #1034 = Utf8               (Ljava/lang/String;[Ljava/lang/Object;)Ljava/lang/String;
  #1035 = NameAndType        #1033:#1034  // format:(Ljava/lang/String;[Ljava/lang/Object;)Ljava/lang/String;
  #1036 = Methodref          #1032.#1035  // java/lang/String.format:(Ljava/lang/String;[Ljava/lang/Object;)Ljava/lang/String;
  #1037 = Utf8               ID #\u0001
  #1038 = String             #1037        // ID #\u0001
  #1039 = Utf8               (Lyt;)Ljava/lang/String;
  #1040 = NameAndType        #987:#1039   // makeConcatWithConstants:(Lyt;)Ljava/lang/String;
  #1041 = InvokeDynamic      #7:#1040     // #7:makeConcatWithConstants:(Lyt;)Ljava/lang/String;
  #1042 = Utf8               <clinit>
  #1043 = NameAndType        #16:#49      // a:Lcom/mojang/serialization/Codec;
  #1044 = Fieldref           #973.#1043   // yt.a:Lcom/mojang/serialization/Codec;
  #1045 = NameAndType        #499:#52     // O:Lys;
  #1046 = Fieldref           #1011.#1045  // hb.O:Lys;
  #1047 = Utf8               (Lys;)Ljava/util/function/Function;
  #1048 = NameAndType        #39:#1047    // d:(Lys;)Ljava/util/function/Function;
  #1049 = Methodref          #968.#1048   // ys.d:(Lys;)Ljava/util/function/Function;
  #1050 = MethodType         #843         //  (Ljava/lang/Object;)Ljava/lang/Object;
  #1051 = MethodHandle       5:#971       // REF_invokeVirtual ys.a:()Lyt;
  #1052 = Utf8               (Lys;)Lyt;
  #1053 = MethodType         #1052        //  (Lys;)Lyt;
  #1054 = Utf8               apply
  #1055 = Utf8               ()Ljava/util/function/Function;
  #1056 = NameAndType        #1054:#1055  // apply:()Ljava/util/function/Function;
  #1057 = InvokeDynamic      #8:#1056     // #8:apply:()Ljava/util/function/Function;
  #1058 = Utf8               com/mojang/serialization/Codec
  #1059 = Class              #1058        // com/mojang/serialization/Codec
  #1060 = Utf8               xmap
  #1061 = Utf8               (Ljava/util/function/Function;Ljava/util/function/Function;)Lcom/mojang/serialization/Codec;
  #1062 = NameAndType        #1060:#1061  // xmap:(Ljava/util/function/Function;Ljava/util/function/Function;)Lcom/mojang/serialization/Codec;
  #1063 = InterfaceMethodref #1059.#1062  // com/mojang/serialization/Codec.xmap:(Ljava/util/function/Function;Ljava/util/function/Function;)Lcom/mojang/serialization/Codec;
  #1064 = NameAndType        #39:#49      // d:Lcom/mojang/serialization/Codec;
  #1065 = Fieldref           #2.#1064     // cav.d:Lcom/mojang/serialization/Codec;
  #1066 = Utf8               overworld
  #1067 = String             #1066        // overworld
  #1068 = Methodref          #973.#243    // yt."<init>":(Ljava/lang/String;)V
  #1069 = Utf8               (Lys;Lyt;)Lys;
  #1070 = NameAndType        #16:#1069    // a:(Lys;Lyt;)Lys;
  #1071 = Methodref          #968.#1070   // ys.a:(Lys;Lyt;)Lys;
  #1072 = NameAndType        #51:#52      // e:Lys;
  #1073 = Fieldref           #2.#1072     // cav.e:Lys;
  #1074 = Utf8               the_nether
  #1075 = String             #1074        // the_nether
  #1076 = NameAndType        #54:#52      // f:Lys;
  #1077 = Fieldref           #2.#1076     // cav.f:Lys;
  #1078 = Utf8               the_end
  #1079 = String             #1078        // the_end
  #1080 = NameAndType        #55:#52      // g:Lys;
  #1081 = Fieldref           #2.#1080     // cav.g:Lys;
  #1082 = Utf8               values
  #1083 = Utf8               ()[Lgo;
  #1084 = NameAndType        #1082:#1083  // values:()[Lgo;
  #1085 = Methodref          #43.#1084    // go.values:()[Lgo;
  #1086 = Utf8               Signature
  #1087 = Utf8               ConstantValue
  #1088 = Utf8               Code
  #1089 = Utf8               StackMapTable
  #1090 = Utf8               LineNumberTable
  #1091 = Utf8               LocalVariableTable
  #1092 = Utf8               LocalVariableTypeTable
  #1093 = Utf8               RuntimeVisibleAnnotations
  #1094 = Utf8               RuntimeVisibleParameterAnnotations
  #1095 = Utf8               Exceptions
  #1096 = Utf8               InnerClasses
  #1097 = Utf8               BootstrapMethods
  #1098 = Utf8               NestMembers
{
  public static final com.mojang.serialization.Codec<ys<cav>> d;
    descriptor: Lcom/mojang/serialization/Codec;
    flags: (0x0019) ACC_PUBLIC, ACC_STATIC, ACC_FINAL
    Signature: #50                          // Lcom/mojang/serialization/Codec<Lys<Lcav;>;>;

  public static final ys<cav> e;
    descriptor: Lys;
    flags: (0x0019) ACC_PUBLIC, ACC_STATIC, ACC_FINAL
    Signature: #53                          // Lys<Lcav;>;

  public static final ys<cav> f;
    descriptor: Lys;
    flags: (0x0019) ACC_PUBLIC, ACC_STATIC, ACC_FINAL
    Signature: #53                          // Lys<Lcav;>;

  public static final ys<cav> g;
    descriptor: Lys;
    flags: (0x0019) ACC_PUBLIC, ACC_STATIC, ACC_FINAL
    Signature: #53                          // Lys<Lcav;>;

  public static final int h = 30000000;
    descriptor: I
    flags: (0x0019) ACC_PUBLIC, ACC_STATIC, ACC_FINAL
    ConstantValue: int 30000000

  public static final int i = 512;
    descriptor: I
    flags: (0x0019) ACC_PUBLIC, ACC_STATIC, ACC_FINAL
    ConstantValue: int 512

  public static final int j = 32;
    descriptor: I
    flags: (0x0019) ACC_PUBLIC, ACC_STATIC, ACC_FINAL
    ConstantValue: int 32

  private static final go[] a;
    descriptor: [Lgo;
    flags: (0x001a) ACC_PRIVATE, ACC_STATIC, ACC_FINAL

  public static final int k = 15;
    descriptor: I
    flags: (0x0019) ACC_PUBLIC, ACC_STATIC, ACC_FINAL
    ConstantValue: int 15

  public static final int l = 24000;
    descriptor: I
    flags: (0x0019) ACC_PUBLIC, ACC_STATIC, ACC_FINAL
    ConstantValue: int 24000

  public static final int m = 20000000;
    descriptor: I
    flags: (0x0019) ACC_PUBLIC, ACC_STATIC, ACC_FINAL
    ConstantValue: int 20000000

  public static final int n = -20000000;
    descriptor: I
    flags: (0x0019) ACC_PUBLIC, ACC_STATIC, ACC_FINAL
    ConstantValue: int -20000000

  protected final java.util.List<cny> o;
    descriptor: Ljava/util/List;
    flags: (0x0014) ACC_PROTECTED, ACC_FINAL
    Signature: #74                          // Ljava/util/List<Lcny;>;

  private final java.util.List<cny> b;
    descriptor: Ljava/util/List;
    flags: (0x0012) ACC_PRIVATE, ACC_FINAL
    Signature: #74                          // Ljava/util/List<Lcny;>;

  private boolean c;
    descriptor: Z
    flags: (0x0002) ACC_PRIVATE

  private final java.lang.Thread y;
    descriptor: Ljava/lang/Thread;
    flags: (0x0012) ACC_PRIVATE, ACC_FINAL

  private final boolean z;
    descriptor: Z
    flags: (0x0012) ACC_PRIVATE, ACC_FINAL

  private int A;
    descriptor: I
    flags: (0x0002) ACC_PRIVATE

  protected int p;
    descriptor: I
    flags: (0x0004) ACC_PROTECTED

  protected final int q = 1013904223;
    descriptor: I
    flags: (0x0014) ACC_PROTECTED, ACC_FINAL
    ConstantValue: int 1013904223

  protected float r;
    descriptor: F
    flags: (0x0004) ACC_PROTECTED

  protected float s;
    descriptor: F
    flags: (0x0004) ACC_PROTECTED

  protected float t;
    descriptor: F
    flags: (0x0004) ACC_PROTECTED

  protected float u;
    descriptor: F
    flags: (0x0004) ACC_PROTECTED

  public final java.util.Random v;
    descriptor: Ljava/util/Random;
    flags: (0x0011) ACC_PUBLIC, ACC_FINAL

  final cry B;
    descriptor: Lcry;
    flags: (0x0010) ACC_FINAL

  private final gs<cry> C;
    descriptor: Lgs;
    flags: (0x0012) ACC_PRIVATE, ACC_FINAL
    Signature: #94                          // Lgs<Lcry;>;

  protected final dkw w;
    descriptor: Ldkw;
    flags: (0x0014) ACC_PROTECTED, ACC_FINAL

  private final java.util.function.Supplier<asy> D;
    descriptor: Ljava/util/function/Supplier;
    flags: (0x0012) ACC_PRIVATE, ACC_FINAL
    Signature: #99                          // Ljava/util/function/Supplier<Lasy;>;

  public final boolean x;
    descriptor: Z
    flags: (0x0011) ACC_PUBLIC, ACC_FINAL

  private final cql E;
    descriptor: Lcql;
    flags: (0x0012) ACC_PRIVATE, ACC_FINAL

  private final cbt F;
    descriptor: Lcbt;
    flags: (0x0012) ACC_PRIVATE, ACC_FINAL

  private final ys<cav> G;
    descriptor: Lys;
    flags: (0x0012) ACC_PRIVATE, ACC_FINAL
    Signature: #53                          // Lys<Lcav;>;

  private long H;
    descriptor: J
    flags: (0x0002) ACC_PRIVATE

  protected cav(dkw, ys<cav>, gs<cry>, java.util.function.Supplier<asy>, boolean, boolean, long);
    descriptor: (Ldkw;Lys;Lgs;Ljava/util/function/Supplier;ZZJ)V
    flags: (0x0004) ACC_PROTECTED
    Code:
      stack=6, locals=9, args_size=8
         0: aload_0
         1: invokespecial #112                // Method java/lang/Object."<init>":()V
         4: aload_0
         5: invokestatic  #118                // Method com/google/common/collect/Lists.newArrayList:()Ljava/util/ArrayList;
         8: putfield      #120                // Field o:Ljava/util/List;
        11: aload_0
        12: invokestatic  #118                // Method com/google/common/collect/Lists.newArrayList:()Ljava/util/ArrayList;
        15: putfield      #122                // Field b:Ljava/util/List;
        18: aload_0
        19: new           #124                // class java/util/Random
        22: dup
        23: invokespecial #125                // Method java/util/Random."<init>":()V
        26: invokevirtual #129                // Method java/util/Random.nextInt:()I
        29: putfield      #131                // Field p:I
        32: aload_0
        33: ldc           #82                 // int 1013904223
        35: putfield      #133                // Field q:I
        38: aload_0
        39: new           #124                // class java/util/Random
        42: dup
        43: invokespecial #125                // Method java/util/Random."<init>":()V
        46: putfield      #135                // Field v:Ljava/util/Random;
        49: aload_0
        50: aload         4
        52: putfield      #137                // Field D:Ljava/util/function/Supplier;
        55: aload_0
        56: aload_1
        57: putfield      #139                // Field w:Ldkw;
        60: aload_0
        61: aload_3
        62: putfield      #141                // Field C:Lgs;
        65: aload_0
        66: aload_3
        67: invokeinterface #146,  1          // InterfaceMethod gs.a:()Ljava/lang/Object;
        72: checkcast     #148                // class cry
        75: putfield      #150                // Field B:Lcry;
        78: aload_0
        79: aload_2
        80: putfield      #152                // Field G:Lys;
        83: aload_0
        84: iload         5
        86: putfield      #154                // Field x:Z
        89: aload_0
        90: getfield      #150                // Field B:Lcry;
        93: invokevirtual #157                // Method cry.e:()D
        96: dconst_1
        97: dcmpl
        98: ifeq          116
       101: aload_0
       102: new           #11                 // class cav$1
       105: dup
       106: aload_0
       107: invokespecial #160                // Method cav$1."<init>":(Lcav;)V
       110: putfield      #162                // Field E:Lcql;
       113: goto          127
       116: aload_0
       117: new           #164                // class cql
       120: dup
       121: invokespecial #165                // Method cql."<init>":()V
       124: putfield      #162                // Field E:Lcql;
       127: aload_0
       128: invokestatic  #171                // Method java/lang/Thread.currentThread:()Ljava/lang/Thread;
       131: putfield      #173                // Field y:Ljava/lang/Thread;
       134: aload_0
       135: new           #15                 // class cbt
       138: dup
       139: aload_0
       140: lload         7
       142: invokespecial #176                // Method cbt."<init>":(Lcbt$a;J)V
       145: putfield      #178                // Field F:Lcbt;
       148: aload_0
       149: iload         6
       151: putfield      #180                // Field z:Z
       154: return
      StackMapTable: number_of_entries = 2
        frame_type = 255 /* full_frame */
          offset_delta = 116
          locals = [ class cav, top, top, top, top, top, int, long ]
          stack = []
        frame_type = 10 /* same */
      LineNumberTable:
        line 121: 0
        line 90: 4
        line 91: 11
        line 99: 18
        line 100: 32
        line 106: 38
        line 122: 49
        line 123: 55
        line 124: 60
        line 125: 65
        line 126: 78
        line 127: 83
        line 128: 89
        line 129: 101
        line 141: 116
        line 143: 127
        line 144: 134
        line 145: 148
        line 146: 154
      LocalVariableTable:
        Start  Length  Slot  Name   Signature
            0     155     0  this   Lcav;
            0     155     1   $$0   Ldkw;
            0     155     2   $$1   Lys;
            0     155     3   $$2   Lgs;
            0     155     4   $$3   Ljava/util/function/Supplier;
            0     155     5   $$4   Z
            0     155     6   $$5   Z
            0     155     7   $$6   J
      LocalVariableTypeTable:
        Start  Length  Slot  Name   Signature
            0     155     2   $$1   Lys<Lcav;>;
            0     155     3   $$2   Lgs<Lcry;>;
            0     155     4   $$3   Ljava/util/function/Supplier<Lasy;>;
    Signature: #109                         // (Ldkw;Lys<Lcav;>;Lgs<Lcry;>;Ljava/util/function/Supplier<Lasy;>;ZZJ)V

  public boolean k_();
    descriptor: ()Z
    flags: (0x0001) ACC_PUBLIC
    Code:
      stack=1, locals=1, args_size=1
         0: aload_0
         1: getfield      #154                // Field x:Z
         4: ireturn
      LineNumberTable:
        line 150: 0
      LocalVariableTable:
        Start  Length  Slot  Name   Signature
            0       5     0  this   Lcav;

  public net.minecraft.server.MinecraftServer n();
    descriptor: ()Lnet/minecraft/server/MinecraftServer;
    flags: (0x0001) ACC_PUBLIC
    Code:
      stack=1, locals=1, args_size=1
         0: aconst_null
         1: areturn
      LineNumberTable:
        line 156: 0
      LocalVariableTable:
        Start  Length  Slot  Name   Signature
            0       2     0  this   Lcav;
    RuntimeVisibleAnnotations:
      0: #193()
        javax.annotation.Nullable

  public boolean j(gj);
    descriptor: (Lgj;)Z
    flags: (0x0001) ACC_PUBLIC
    Code:
      stack=2, locals=2, args_size=2
         0: aload_0
         1: aload_1
         2: invokevirtual #196                // Method u:(Lgj;)Z
         5: ifne          19
         8: aload_1
         9: invokestatic  #198                // Method D:(Lgj;)Z
        12: ifeq          19
        15: iconst_1
        16: goto          20
        19: iconst_0
        20: ireturn
      StackMapTable: number_of_entries = 2
        frame_type = 249 /* chop */
          offset_delta = 19
        frame_type = 64 /* same_locals_1_stack_item */
          stack = [ int ]
      LineNumberTable:
        line 160: 0
      LocalVariableTable:
        Start  Length  Slot  Name   Signature
            0      21     0  this   Lcav;
            0      21     1   $$0   Lgj;

  public static boolean k(gj);
    descriptor: (Lgj;)Z
    flags: (0x0009) ACC_PUBLIC, ACC_STATIC
    Code:
      stack=1, locals=1, args_size=1
         0: aload_0
         1: invokevirtual #203                // Method gj.v:()I
         4: invokestatic  #206                // Method b:(I)Z
         7: ifne          21
        10: aload_0
        11: invokestatic  #198                // Method D:(Lgj;)Z
        14: ifeq          21
        17: iconst_1
        18: goto          22
        21: iconst_0
        22: ireturn
      StackMapTable: number_of_entries = 2
        frame_type = 250 /* chop */
          offset_delta = 21
        frame_type = 64 /* same_locals_1_stack_item */
          stack = [ int ]
      LineNumberTable:
        line 164: 0
      LocalVariableTable:
        Start  Length  Slot  Name   Signature
            0      23     0   $$0   Lgj;

  private static boolean D(gj);
    descriptor: (Lgj;)Z
    flags: (0x000a) ACC_PRIVATE, ACC_STATIC
    Code:
      stack=2, locals=1, args_size=1
         0: aload_0
         1: invokevirtual #208                // Method gj.u:()I
         4: ldc           #209                // int -30000000
         6: if_icmplt     40
         9: aload_0
        10: invokevirtual #211                // Method gj.w:()I
        13: ldc           #209                // int -30000000
        15: if_icmplt     40
        18: aload_0
        19: invokevirtual #208                // Method gj.u:()I
        22: ldc           #58                 // int 30000000
        24: if_icmpge     40
        27: aload_0
        28: invokevirtual #211                // Method gj.w:()I
        31: ldc           #58                 // int 30000000
        33: if_icmpge     40
        36: iconst_1
        37: goto          41
        40: iconst_0
        41: ireturn
      StackMapTable: number_of_entries = 2
        frame_type = 250 /* chop */
          offset_delta = 40
        frame_type = 64 /* same_locals_1_stack_item */
          stack = [ int ]
      LineNumberTable:
        line 168: 0
      LocalVariableTable:
        Start  Length  Slot  Name   Signature
            0      42     0   $$0   Lgj;

  private static boolean b(int);
    descriptor: (I)Z
    flags: (0x000a) ACC_PRIVATE, ACC_STATIC
    Code:
      stack=2, locals=1, args_size=1
         0: iload_0
         1: ldc           #71                 // int -20000000
         3: if_icmplt     12
         6: iload_0
         7: ldc           #69                 // int 20000000
         9: if_icmplt     16
        12: iconst_1
        13: goto          17
        16: iconst_0
        17: ireturn
      StackMapTable: number_of_entries = 3
        frame_type = 250 /* chop */
          offset_delta = 12
        frame_type = 3 /* same */
        frame_type = 64 /* same_locals_1_stack_item */
          stack = [ int ]
      LineNumberTable:
        line 172: 0
      LocalVariableTable:
        Start  Length  Slot  Name   Signature
            0      18     0   $$0   I

  public cra l(gj);
    descriptor: (Lgj;)Lcra;
    flags: (0x0001) ACC_PUBLIC
    Code:
      stack=3, locals=2, args_size=2
         0: aload_0
         1: aload_1
         2: invokevirtual #208                // Method gj.u:()I
         5: invokestatic  #217                // Method hf.a:(I)I
         8: aload_1
         9: invokevirtual #211                // Method gj.w:()I
        12: invokestatic  #217                // Method hf.a:(I)I
        15: invokevirtual #220                // Method d:(II)Lcra;
        18: areturn
      LineNumberTable:
        line 176: 0
      LocalVariableTable:
        Start  Length  Slot  Name   Signature
            0      19     0  this   Lcav;
            0      19     1   $$0   Lgj;

  public cra d(int, int);
    descriptor: (II)Lcra;
    flags: (0x0001) ACC_PUBLIC
    Code:
      stack=4, locals=3, args_size=3
         0: aload_0
         1: iload_1
         2: iload_2
         3: getstatic     #225                // Field cqt.o:Lcqt;
         6: invokevirtual #228                // Method a:(IILcqt;)Lcqq;
         9: checkcast     #33                 // class cra
        12: areturn
      LineNumberTable:
        line 181: 0
      LocalVariableTable:
        Start  Length  Slot  Name   Signature
            0      13     0  this   Lcav;
            0      13     1   $$0   I
            0      13     2   $$1   I

  public cqq a(int, int, cqt, boolean);
    descriptor: (IILcqt;Z)Lcqq;
    flags: (0x0001) ACC_PUBLIC
    Code:
      stack=5, locals=6, args_size=5
         0: aload_0
         1: invokevirtual #233                // Method K:()Lcqs;
         4: iload_1
         5: iload_2
         6: aload_3
         7: iload         4
         9: invokevirtual #237                // Method cqs.a:(IILcqt;Z)Lcqq;
        12: astore        5
        14: aload         5
        16: ifnonnull     34
        19: iload         4
        21: ifeq          34
        24: new           #239                // class java/lang/IllegalStateException
        27: dup
        28: ldc           #241                // String Should always be able to create a chunk!
        30: invokespecial #244                // Method java/lang/IllegalStateException."<init>":(Ljava/lang/String;)V
        33: athrow
        34: aload         5
        36: areturn
      StackMapTable: number_of_entries = 1
        frame_type = 255 /* full_frame */
          offset_delta = 34
          locals = [ top, top, top, top, top, class cqq ]
          stack = []
      LineNumberTable:
        line 187: 0
        line 188: 14
        line 189: 24
        line 191: 34
      LocalVariableTable:
        Start  Length  Slot  Name   Signature
            0      37     0  this   Lcav;
            0      37     1   $$0   I
            0      37     2   $$1   I
            0      37     3   $$2   Lcqt;
            0      37     4   $$3   Z
           14      23     5   $$4   Lcqq;
    RuntimeVisibleAnnotations:
      0: #193()
        javax.annotation.Nullable

  public boolean a(gj, cov, int);
    descriptor: (Lgj;Lcov;I)Z
    flags: (0x0001) ACC_PUBLIC
    Code:
      stack=5, locals=4, args_size=4
         0: aload_0
         1: aload_1
         2: aload_2
         3: iload_3
         4: sipush        512
         7: invokevirtual #251                // Method a:(Lgj;Lcov;II)Z
        10: ireturn
      LineNumberTable:
        line 196: 0
      LocalVariableTable:
        Start  Length  Slot  Name   Signature
            0      11     0  this   Lcav;
            0      11     1   $$0   Lgj;
            0      11     2   $$1   Lcov;
            0      11     3   $$2   I

  public boolean a(gj, cov, int, int);
    descriptor: (Lgj;Lcov;II)Z
    flags: (0x0001) ACC_PUBLIC
    Code:
      stack=6, locals=10, args_size=5
         0: aload_0
         1: aload_1
         2: invokevirtual #196                // Method u:(Lgj;)Z
         5: ifeq          10
         8: iconst_0
         9: ireturn
        10: aload_0
        11: getfield      #154                // Field x:Z
        14: ifne          26
        17: aload_0
        18: invokevirtual #255                // Method ad:()Z
        21: ifeq          26
        24: iconst_0
        25: ireturn
        26: aload_0
        27: aload_1
        28: invokevirtual #257                // Method l:(Lgj;)Lcra;
        31: astore        5
        33: aload_2
        34: invokevirtual #262                // Method cov.b:()Lcdq;
        37: astore        6
        39: aload         5
        41: aload_1
        42: aload_2
        43: iload_3
        44: bipush        64
        46: iand
        47: ifeq          54
        50: iconst_1
        51: goto          55
        54: iconst_0
        55: invokevirtual #267                // Method cra.a:(Lgj;Lcov;Z)Lcov;
        58: astore        7
        60: aload         7
        62: ifnull        347
        65: aload_0
        66: aload_1
        67: invokevirtual #271                // Method a_:(Lgj;)Lcov;
        70: astore        8
        72: iload_3
        73: sipush        128
        76: iand
        77: ifne          165
        80: aload         8
        82: aload         7
        84: if_acmpeq     165
        87: aload         8
        89: aload_0
        90: aload_1
        91: invokevirtual #274                // Method cov.b:(Lcab;Lgj;)I
        94: aload         7
        96: aload_0
        97: aload_1
        98: invokevirtual #274                // Method cov.b:(Lcab;Lgj;)I
       101: if_icmpne     133
       104: aload         8
       106: invokevirtual #276                // Method cov.f:()I
       109: aload         7
       111: invokevirtual #276                // Method cov.f:()I
       114: if_icmpne     133
       117: aload         8
       119: invokevirtual #278                // Method cov.e:()Z
       122: ifne          133
       125: aload         7
       127: invokevirtual #278                // Method cov.e:()Z
       130: ifeq          165
       133: aload_0
       134: invokevirtual #282                // Method ab:()Lasy;
       137: ldc_w         #284                // String queueCheckLight
       140: invokeinterface #288,  2          // InterfaceMethod asy.a:(Ljava/lang/String;)V
       145: aload_0
       146: invokevirtual #233                // Method K:()Lcqs;
       149: invokevirtual #291                // Method cqs.n:()Ldio;
       152: aload_1
       153: invokevirtual #296                // Method dio.a:(Lgj;)V
       156: aload_0
       157: invokevirtual #282                // Method ab:()Lasy;
       160: invokeinterface #298,  1          // InterfaceMethod asy.c:()V
       165: aload         8
       167: aload_2
       168: if_acmpne     345
       171: aload         7
       173: aload         8
       175: if_acmpeq     187
       178: aload_0
       179: aload_1
       180: aload         7
       182: aload         8
       184: invokevirtual #301                // Method b:(Lgj;Lcov;Lcov;)V
       187: iload_3
       188: iconst_2
       189: iand
       190: ifeq          244
       193: aload_0
       194: getfield      #154                // Field x:Z
       197: ifeq          206
       200: iload_3
       201: iconst_4
       202: iand
       203: ifne          244
       206: aload_0
       207: getfield      #154                // Field x:Z
       210: ifne          235
       213: aload         5
       215: invokevirtual #304                // Method cra.B:()Ladi$c;
       218: ifnull        244
       221: aload         5
       223: invokevirtual #304                // Method cra.B:()Ladi$c;
       226: getstatic     #307                // Field adi$c.c:Ladi$c;
       229: invokevirtual #310                // Method adi$c.a:(Ladi$c;)Z
       232: ifeq          244
       235: aload_0
       236: aload_1
       237: aload         7
       239: aload_2
       240: iload_3
       241: invokevirtual #313                // Method a:(Lgj;Lcov;Lcov;I)V
       244: iload_3
       245: iconst_1
       246: iand
       247: ifeq          281
       250: aload_0
       251: aload_1
       252: aload         7
       254: invokevirtual #262                // Method cov.b:()Lcdq;
       257: invokevirtual #316                // Method a:(Lgj;Lcdq;)V
       260: aload_0
       261: getfield      #154                // Field x:Z
       264: ifne          281
       267: aload_2
       268: invokevirtual #318                // Method cov.j:()Z
       271: ifeq          281
       274: aload_0
       275: aload_1
       276: aload         6
       278: invokevirtual #320                // Method c:(Lgj;Lcdq;)V
       281: iload_3
       282: bipush        16
       284: iand
       285: ifne          336
       288: iload         4
       290: ifle          336
       293: iload_3
       294: bipush        -34
       296: iand
       297: istore        9
       299: aload         7
       301: aload_0
       302: aload_1
       303: iload         9
       305: iload         4
       307: iconst_1
       308: isub
       309: invokevirtual #323                // Method cov.b:(Lcaw;Lgj;II)V
       312: aload_2
       313: aload_0
       314: aload_1
       315: iload         9
       317: iload         4
       319: iconst_1
       320: isub
       321: invokevirtual #325                // Method cov.a:(Lcaw;Lgj;II)V
       324: aload_2
       325: aload_0
       326: aload_1
       327: iload         9
       329: iload         4
       331: iconst_1
       332: isub
       333: invokevirtual #323                // Method cov.b:(Lcaw;Lgj;II)V
       336: aload_0
       337: aload_1
       338: aload         7
       340: aload         8
       342: invokevirtual #327                // Method a:(Lgj;Lcov;Lcov;)V
       345: iconst_1
       346: ireturn
       347: iconst_0
       348: ireturn
      StackMapTable: number_of_entries = 14
        frame_type = 10 /* same */
        frame_type = 15 /* same */
        frame_type = 255 /* full_frame */
          offset_delta = 27
          locals = [ class cav, class gj, class cov, int, int, class cra, class cdq ]
          stack = [ class cra, class gj, class cov ]
        frame_type = 255 /* full_frame */
          offset_delta = 0
          locals = [ class cav, class gj, class cov, int, int, class cra, class cdq ]
          stack = [ class cra, class gj, class cov, int ]
        frame_type = 253 /* append */
          offset_delta = 77
          locals = [ class cov, class cov ]
        frame_type = 31 /* same */
        frame_type = 21 /* same */
        frame_type = 18 /* same */
        frame_type = 255 /* full_frame */
          offset_delta = 28
          locals = [ class cav, class gj, class cov, int, int, top, class cdq, class cov, class cov ]
          stack = []
        frame_type = 8 /* same */
        frame_type = 255 /* full_frame */
          offset_delta = 36
          locals = [ class cav, class gj, class cov, int, int, top, top, class cov, class cov ]
          stack = []
        frame_type = 255 /* full_frame */
          offset_delta = 54
          locals = [ class cav, class gj, top, top, top, top, top, class cov, class cov ]
          stack = []
        frame_type = 255 /* full_frame */
          offset_delta = 8
          locals = []
          stack = []
        frame_type = 1 /* same */
      LineNumberTable:
        line 201: 0
        line 202: 8
        line 205: 10
        line 206: 24
        line 209: 26
        line 210: 33
        line 211: 39
        line 214: 60
        line 216: 65
        line 218: 72
        line 219: 133
        line 220: 145
        line 221: 156
        line 225: 165
        line 226: 171
        line 227: 178
        line 230: 187
        line 231: 235
        line 234: 244
        line 235: 250
        line 236: 260
        line 237: 274
        line 242: 281
        line 243: 293
        line 244: 299
        line 245: 312
        line 246: 324
        line 249: 336
        line 252: 345
        line 255: 347
      LocalVariableTable:
        Start  Length  Slot  Name   Signature
            0     349     0  this   Lcav;
            0     349     1   $$0   Lgj;
            0     349     2   $$1   Lcov;
            0     349     3   $$2   I
            0     349     4   $$3   I
           33     316     5   $$4   Lcra;
           39     310     6   $$5   Lcdq;
           60     289     7   $$6   Lcov;
           72     275     8   $$7   Lcov;
          299      37     9   $$8   I

  public void a(gj, cov, cov);
    descriptor: (Lgj;Lcov;Lcov;)V
    flags: (0x0001) ACC_PUBLIC
    Code:
      stack=0, locals=4, args_size=4
         0: return
      LineNumberTable:
        line 259: 0
      LocalVariableTable:
        Start  Length  Slot  Name   Signature
            0       1     0  this   Lcav;
            0       1     1   $$0   Lgj;
            0       1     2   $$1   Lcov;
            0       1     3   $$2   Lcov;

  public boolean a(gj, boolean);
    descriptor: (Lgj;Z)Z
    flags: (0x0001) ACC_PUBLIC
    Code:
      stack=5, locals=4, args_size=3
         0: aload_0
         1: aload_1
         2: invokevirtual #336                // Method b_:(Lgj;)Ldix;
         5: astore_3
         6: aload_0
         7: aload_1
         8: aload_3
         9: invokevirtual #341                // Method dix.g:()Lcov;
        12: iconst_3
        13: iload_2
        14: ifeq          22
        17: bipush        64
        19: goto          23
        22: iconst_0
        23: ior
        24: invokevirtual #343                // Method a:(Lgj;Lcov;I)Z
        27: ireturn
      StackMapTable: number_of_entries = 2
        frame_type = 255 /* full_frame */
          offset_delta = 22
          locals = []
          stack = [ class cav, class gj, class cov, int ]
        frame_type = 255 /* full_frame */
          offset_delta = 0
          locals = []
          stack = [ class cav, class gj, class cov, int, int ]
      LineNumberTable:
        line 270: 0
        line 271: 6
      LocalVariableTable:
        Start  Length  Slot  Name   Signature
            0      28     0  this   Lcav;
            0      28     1   $$0   Lgj;
            0      28     2   $$1   Z
            6      22     3   $$2   Ldix;

  public boolean a(gj, boolean, axk, int);
    descriptor: (Lgj;ZLaxk;I)Z
    flags: (0x0001) ACC_PUBLIC
    Code:
      stack=6, locals=8, args_size=5
         0: aload_0
         1: aload_1
         2: invokevirtual #271                // Method a_:(Lgj;)Lcov;
         5: astore        5
         7: aload         5
         9: invokevirtual #347                // Method cov.g:()Z
        12: ifeq          17
        15: iconst_0
        16: ireturn
        17: aload_0
        18: aload_1
        19: invokevirtual #336                // Method b_:(Lgj;)Ldix;
        22: astore        6
        24: aload         5
        26: invokevirtual #262                // Method cov.b:()Lcdq;
        29: instanceof    #349                // class cde
        32: ifne          48
        35: aload_0
        36: sipush        2001
        39: aload_1
        40: aload         5
        42: invokestatic  #352                // Method cdq.i:(Lcov;)I
        45: invokevirtual #355                // Method c:(ILgj;I)V
        48: iload_2
        49: ifeq          84
        52: aload         5
        54: invokevirtual #357                // Method cov.n:()Z
        57: ifeq          68
        60: aload_0
        61: aload_1
        62: invokevirtual #361                // Method c_:(Lgj;)Lcmr;
        65: goto          69
        68: aconst_null
        69: astore        7
        71: aload         5
        73: aload_0
        74: aload_1
        75: aload         7
        77: aload_3
        78: getstatic     #370                // Field buw.b:Lbuw;
        81: invokestatic  #373                // Method cdq.a:(Lcov;Lcav;Lgj;Lcmr;Laxk;Lbuw;)V
        84: aload_0
        85: aload_1
        86: aload         6
        88: invokevirtual #341                // Method dix.g:()Lcov;
        91: iconst_3
        92: iload         4
        94: invokevirtual #251                // Method a:(Lgj;Lcov;II)Z
        97: istore        7
        99: iload         7
       101: ifeq          113
       104: aload_0
       105: aload_3
       106: getstatic     #378                // Field csy.d:Lcsy;
       109: aload_1
       110: invokevirtual #381                // Method a:(Laxk;Lcsy;Lgj;)V
       113: iload         7
       115: ireturn
      StackMapTable: number_of_entries = 6
        frame_type = 252 /* append */
          offset_delta = 17
          locals = [ class cov ]
        frame_type = 252 /* append */
          offset_delta = 30
          locals = [ class dix ]
        frame_type = 255 /* full_frame */
          offset_delta = 19
          locals = [ class cav, class gj, top, class axk, int, class cov, class dix ]
          stack = []
        frame_type = 64 /* same_locals_1_stack_item */
          stack = [ class cmr ]
        frame_type = 255 /* full_frame */
          offset_delta = 14
          locals = [ class cav, class gj, top, class axk, int, top, class dix ]
          stack = []
        frame_type = 255 /* full_frame */
          offset_delta = 28
          locals = [ top, top, top, top, top, top, top, int ]
          stack = []
      LineNumberTable:
        line 284: 0
        line 285: 7
        line 286: 15
        line 289: 17
        line 290: 24
        line 291: 35
        line 293: 48
        line 294: 52
        line 295: 71
        line 298: 84
        line 300: 99
        line 301: 104
        line 304: 113
      LocalVariableTable:
        Start  Length  Slot  Name   Signature
            0     116     0  this   Lcav;
            0     116     1   $$0   Lgj;
            0     116     2   $$1   Z
            0     116     3   $$2   Laxk;
            0     116     4   $$3   I
            7     109     5   $$4   Lcov;
           24      92     6   $$5   Ldix;
           71      13     7   $$6   Lcmr;
           99      17     7   $$7   Z
    RuntimeVisibleParameterAnnotations:
      parameter 0:
      parameter 1:
      parameter 2:
        0: #193()
          javax.annotation.Nullable
      parameter 3:

  public void a(gj, cov);
    descriptor: (Lgj;Lcov;)V
    flags: (0x0001) ACC_PUBLIC
    Code:
      stack=0, locals=3, args_size=3
         0: return
      LineNumberTable:
        line 308: 0
      LocalVariableTable:
        Start  Length  Slot  Name   Signature
            0       1     0  this   Lcav;
            0       1     1   $$0   Lgj;
            0       1     2   $$1   Lcov;

  public boolean b(gj, cov);
    descriptor: (Lgj;Lcov;)Z
    flags: (0x0001) ACC_PUBLIC
    Code:
      stack=4, locals=3, args_size=3
         0: aload_0
         1: aload_1
         2: aload_2
         3: iconst_3
         4: invokevirtual #343                // Method a:(Lgj;Lcov;I)Z
         7: ireturn
      LineNumberTable:
        line 311: 0
      LocalVariableTable:
        Start  Length  Slot  Name   Signature
            0       8     0  this   Lcav;
            0       8     1   $$0   Lgj;
            0       8     2   $$1   Lcov;

  public abstract void a(gj, cov, cov, int);
    descriptor: (Lgj;Lcov;Lcov;I)V
    flags: (0x0401) ACC_PUBLIC, ACC_ABSTRACT

  public void b(gj, cov, cov);
    descriptor: (Lgj;Lcov;Lcov;)V
    flags: (0x0001) ACC_PUBLIC
    Code:
      stack=0, locals=4, args_size=4
         0: return
      LineNumberTable:
        line 317: 0
      LocalVariableTable:
        Start  Length  Slot  Name   Signature
            0       1     0  this   Lcav;
            0       1     1   $$0   Lgj;
            0       1     2   $$1   Lcov;
            0       1     3   $$2   Lcov;

  public void b(gj, cdq);
    descriptor: (Lgj;Lcdq;)V
    flags: (0x0001) ACC_PUBLIC
    Code:
      stack=4, locals=3, args_size=3
         0: aload_0
         1: aload_1
         2: invokevirtual #388                // Method gj.f:()Lgj;
         5: aload_2
         6: aload_1
         7: invokevirtual #391                // Method a:(Lgj;Lcdq;Lgj;)V
        10: aload_0
        11: aload_1
        12: invokevirtual #393                // Method gj.g:()Lgj;
        15: aload_2
        16: aload_1
        17: invokevirtual #391                // Method a:(Lgj;Lcdq;Lgj;)V
        20: aload_0
        21: aload_1
        22: invokevirtual #395                // Method gj.c:()Lgj;
        25: aload_2
        26: aload_1
        27: invokevirtual #391                // Method a:(Lgj;Lcdq;Lgj;)V
        30: aload_0
        31: aload_1
        32: invokevirtual #397                // Method gj.b:()Lgj;
        35: aload_2
        36: aload_1
        37: invokevirtual #391                // Method a:(Lgj;Lcdq;Lgj;)V
        40: aload_0
        41: aload_1
        42: invokevirtual #399                // Method gj.d:()Lgj;
        45: aload_2
        46: aload_1
        47: invokevirtual #391                // Method a:(Lgj;Lcdq;Lgj;)V
        50: aload_0
        51: aload_1
        52: invokevirtual #401                // Method gj.e:()Lgj;
        55: aload_2
        56: aload_1
        57: invokevirtual #391                // Method a:(Lgj;Lcdq;Lgj;)V
        60: return
      LineNumberTable:
        line 320: 0
        line 321: 10
        line 322: 20
        line 323: 30
        line 324: 40
        line 325: 50
        line 326: 60
      LocalVariableTable:
        Start  Length  Slot  Name   Signature
            0      61     0  this   Lcav;
            0      61     1   $$0   Lgj;
            0      61     2   $$1   Lcdq;

  public void a(gj, cdq, go);
    descriptor: (Lgj;Lcdq;Lgo;)V
    flags: (0x0001) ACC_PUBLIC
    Code:
      stack=4, locals=4, args_size=4
         0: aload_3
         1: getstatic     #405                // Field go.e:Lgo;
         4: if_acmpeq     17
         7: aload_0
         8: aload_1
         9: invokevirtual #388                // Method gj.f:()Lgj;
        12: aload_2
        13: aload_1
        14: invokevirtual #391                // Method a:(Lgj;Lcdq;Lgj;)V
        17: aload_3
        18: getstatic     #407                // Field go.f:Lgo;
        21: if_acmpeq     34
        24: aload_0
        25: aload_1
        26: invokevirtual #393                // Method gj.g:()Lgj;
        29: aload_2
        30: aload_1
        31: invokevirtual #391                // Method a:(Lgj;Lcdq;Lgj;)V
        34: aload_3
        35: getstatic     #409                // Field go.a:Lgo;
        38: if_acmpeq     51
        41: aload_0
        42: aload_1
        43: invokevirtual #395                // Method gj.c:()Lgj;
        46: aload_2
        47: aload_1
        48: invokevirtual #391                // Method a:(Lgj;Lcdq;Lgj;)V
        51: aload_3
        52: getstatic     #411                // Field go.b:Lgo;
        55: if_acmpeq     68
        58: aload_0
        59: aload_1
        60: invokevirtual #397                // Method gj.b:()Lgj;
        63: aload_2
        64: aload_1
        65: invokevirtual #391                // Method a:(Lgj;Lcdq;Lgj;)V
        68: aload_3
        69: getstatic     #413                // Field go.c:Lgo;
        72: if_acmpeq     85
        75: aload_0
        76: aload_1
        77: invokevirtual #399                // Method gj.d:()Lgj;
        80: aload_2
        81: aload_1
        82: invokevirtual #391                // Method a:(Lgj;Lcdq;Lgj;)V
        85: aload_3
        86: getstatic     #415                // Field go.d:Lgo;
        89: if_acmpeq     102
        92: aload_0
        93: aload_1
        94: invokevirtual #401                // Method gj.e:()Lgj;
        97: aload_2
        98: aload_1
        99: invokevirtual #391                // Method a:(Lgj;Lcdq;Lgj;)V
       102: return
      StackMapTable: number_of_entries = 6
        frame_type = 17 /* same */
        frame_type = 16 /* same */
        frame_type = 16 /* same */
        frame_type = 16 /* same */
        frame_type = 16 /* same */
        frame_type = 255 /* full_frame */
          offset_delta = 16
          locals = []
          stack = []
      LineNumberTable:
        line 329: 0
        line 330: 7
        line 332: 17
        line 333: 24
        line 335: 34
        line 336: 41
        line 338: 51
        line 339: 58
        line 341: 68
        line 342: 75
        line 344: 85
        line 345: 92
        line 347: 102
      LocalVariableTable:
        Start  Length  Slot  Name   Signature
            0     103     0  this   Lcav;
            0     103     1   $$0   Lgj;
            0     103     2   $$1   Lcdq;
            0     103     3   $$2   Lgo;

  public void a(gj, cdq, gj);
    descriptor: (Lgj;Lcdq;Lgj;)V
    flags: (0x0001) ACC_PUBLIC
    Code:
      stack=6, locals=8, args_size=4
         0: aload_0
         1: getfield      #154                // Field x:Z
         4: ifeq          8
         7: return
         8: aload_0
         9: aload_1
        10: invokevirtual #271                // Method a_:(Lgj;)Lcov;
        13: astore        4
        15: aload         4
        17: aload_0
        18: aload_1
        19: aload_2
        20: aload_3
        21: iconst_0
        22: invokevirtual #420                // Method cov.a:(Lcav;Lgj;Lcdq;Lgj;Z)V
        25: goto          84
        28: astore        5
        30: aload         5
        32: ldc_w         #422                // String Exception while updating neighbours
        35: invokestatic  #426                // Method q.a:(Ljava/lang/Throwable;Ljava/lang/String;)Lq;
        38: astore        6
        40: aload         6
        42: ldc_w         #428                // String Block being updated
        45: invokevirtual #431                // Method q.a:(Ljava/lang/String;)Lr;
        48: astore        7
        50: aload         7
        52: ldc_w         #433                // String Source block type
        55: aload_2
        56: invokedynamic #451,  0            // InvokeDynamic #0:call:(Lcdq;)Ls;
        61: invokevirtual #455                // Method r.a:(Ljava/lang/String;Ls;)Lr;
        64: pop
        65: aload         7
        67: aload_0
        68: aload_1
        69: aload         4
        71: invokestatic  #458                // Method r.a:(Lr;Lcax;Lgj;Lcov;)V
        74: new           #459                // class z
        77: dup
        78: aload         6
        80: invokespecial #462                // Method z."<init>":(Lq;)V
        83: athrow
        84: return
      Exception table:
         from    to  target type
            15    25    28   Class java/lang/Throwable
      StackMapTable: number_of_entries = 3
        frame_type = 8 /* same */
        frame_type = 255 /* full_frame */
          offset_delta = 19
          locals = [ class cav, class gj, class cdq, top, class cov ]
          stack = [ class java/lang/Throwable ]
        frame_type = 255 /* full_frame */
          offset_delta = 55
          locals = []
          stack = []
      LineNumberTable:
        line 350: 0
        line 351: 7
        line 353: 8
        line 356: 15
        line 372: 25
        line 357: 28
        line 358: 30
        line 359: 40
        line 361: 50
        line 369: 65
        line 371: 74
        line 373: 84
      LocalVariableTable:
        Start  Length  Slot  Name   Signature
            0      85     0  this   Lcav;
            0      85     1   $$0   Lgj;
            0      85     2   $$1   Lcdq;
            0      85     3   $$2   Lgj;
           15      70     4   $$3   Lcov;
           30      54     5   $$4   Ljava/lang/Throwable;
           40      44     6   $$5   Lq;
           50      34     7   $$6   Lr;

  public int a(ctw$a, int, int);
    descriptor: (Lctw$a;II)I
    flags: (0x0001) ACC_PUBLIC
    Code:
      stack=5, locals=5, args_size=4
         0: iload_2
         1: ldc           #209                // int -30000000
         3: if_icmplt     24
         6: iload_3
         7: ldc           #209                // int -30000000
         9: if_icmplt     24
        12: iload_2
        13: ldc           #58                 // int 30000000
        15: if_icmpge     24
        18: iload_3
        19: ldc           #58                 // int 30000000
        21: if_icmplt     35
        24: aload_0
        25: invokevirtual #469                // Method m_:()I
        28: iconst_1
        29: iadd
        30: istore        4
        32: goto          87
        35: aload_0
        36: iload_2
        37: invokestatic  #217                // Method hf.a:(I)I
        40: iload_3
        41: invokestatic  #217                // Method hf.a:(I)I
        44: invokevirtual #472                // Method b:(II)Z
        47: ifeq          81
        50: aload_0
        51: iload_2
        52: invokestatic  #217                // Method hf.a:(I)I
        55: iload_3
        56: invokestatic  #217                // Method hf.a:(I)I
        59: invokevirtual #220                // Method d:(II)Lcra;
        62: aload_1
        63: iload_2
        64: bipush        15
        66: iand
        67: iload_3
        68: bipush        15
        70: iand
        71: invokevirtual #474                // Method cra.a:(Lctw$a;II)I
        74: iconst_1
        75: iadd
        76: istore        4
        78: goto          87
        81: aload_0
        82: invokevirtual #477                // Method u_:()I
        85: istore        4
        87: iload         4
        89: ireturn
      StackMapTable: number_of_entries = 4
        frame_type = 248 /* chop */
          offset_delta = 24
        frame_type = 254 /* append */
          offset_delta = 10
          locals = [ class ctw$a, int, int ]
        frame_type = 248 /* chop */
          offset_delta = 45
        frame_type = 255 /* full_frame */
          offset_delta = 5
          locals = [ top, top, top, top, int ]
          stack = []
      LineNumberTable:
        line 378: 0
        line 379: 24
        line 380: 35
        line 381: 50
        line 383: 81
        line 385: 87
      LocalVariableTable:
        Start  Length  Slot  Name   Signature
            0      90     0  this   Lcav;
            0      90     1   $$0   Lctw$a;
            0      90     2   $$1   I
            0      90     3   $$2   I
           32       3     4   $$3   I
           78       3     4   $$4   I
           87       3     4   $$5   I

  public dio l_();
    descriptor: ()Ldio;
    flags: (0x0001) ACC_PUBLIC
    Code:
      stack=1, locals=1, args_size=1
         0: aload_0
         1: invokevirtual #233                // Method K:()Lcqs;
         4: invokevirtual #291                // Method cqs.n:()Ldio;
         7: areturn
      LineNumberTable:
        line 390: 0
      LocalVariableTable:
        Start  Length  Slot  Name   Signature
            0       8     0  this   Lcav;

  public cov a_(gj);
    descriptor: (Lgj;)Lcov;
    flags: (0x0001) ACC_PUBLIC
    Code:
      stack=3, locals=3, args_size=2
         0: aload_0
         1: aload_1
         2: invokevirtual #196                // Method u:(Lgj;)Z
         5: ifeq          15
         8: getstatic     #484                // Field cdr.lo:Lcdq;
        11: invokevirtual #486                // Method cdq.n:()Lcov;
        14: areturn
        15: aload_0
        16: aload_1
        17: invokevirtual #208                // Method gj.u:()I
        20: invokestatic  #217                // Method hf.a:(I)I
        23: aload_1
        24: invokevirtual #211                // Method gj.w:()I
        27: invokestatic  #217                // Method hf.a:(I)I
        30: invokevirtual #220                // Method d:(II)Lcra;
        33: astore_2
        34: aload_2
        35: aload_1
        36: invokevirtual #487                // Method cra.a_:(Lgj;)Lcov;
        39: areturn
      StackMapTable: number_of_entries = 1
        frame_type = 15 /* same */
      LineNumberTable:
        line 395: 0
        line 396: 8
        line 398: 15
        line 399: 34
      LocalVariableTable:
        Start  Length  Slot  Name   Signature
            0      40     0  this   Lcav;
            0      40     1   $$0   Lgj;
           34       6     2   $$1   Lcra;

  public dix b_(gj);
    descriptor: (Lgj;)Ldix;
    flags: (0x0001) ACC_PUBLIC
    Code:
      stack=2, locals=3, args_size=2
         0: aload_0
         1: aload_1
         2: invokevirtual #196                // Method u:(Lgj;)Z
         5: ifeq          15
         8: getstatic     #492                // Field diy.a:Ldiw;
        11: invokevirtual #497                // Method diw.h:()Ldix;
        14: areturn
        15: aload_0
        16: aload_1
        17: invokevirtual #257                // Method l:(Lgj;)Lcra;
        20: astore_2
        21: aload_2
        22: aload_1
        23: invokevirtual #498                // Method cra.b_:(Lgj;)Ldix;
        26: areturn
      StackMapTable: number_of_entries = 1
        frame_type = 15 /* same */
      LineNumberTable:
        line 404: 0
        line 405: 8
        line 407: 15
        line 408: 21
      LocalVariableTable:
        Start  Length  Slot  Name   Signature
            0      27     0  this   Lcav;
            0      27     1   $$0   Lgj;
           21       6     2   $$1   Lcra;

  public boolean O();
    descriptor: ()Z
    flags: (0x0001) ACC_PUBLIC
    Code:
      stack=2, locals=1, args_size=1
         0: aload_0
         1: invokevirtual #503                // Method q_:()Lcry;
         4: invokevirtual #504                // Method cry.n:()Z
         7: ifne          22
        10: aload_0
        11: getfield      #506                // Field A:I
        14: iconst_4
        15: if_icmpge     22
        18: iconst_1
        19: goto          23
        22: iconst_0
        23: ireturn
      StackMapTable: number_of_entries = 2
        frame_type = 250 /* chop */
          offset_delta = 22
        frame_type = 64 /* same_locals_1_stack_item */
          stack = [ int ]
      LineNumberTable:
        line 412: 0
      LocalVariableTable:
        Start  Length  Slot  Name   Signature
            0      24     0  this   Lcav;

  public boolean P();
    descriptor: ()Z
    flags: (0x0001) ACC_PUBLIC
    Code:
      stack=1, locals=1, args_size=1
         0: aload_0
         1: invokevirtual #503                // Method q_:()Lcry;
         4: invokevirtual #504                // Method cry.n:()Z
         7: ifne          21
        10: aload_0
        11: invokevirtual #509                // Method O:()Z
        14: ifne          21
        17: iconst_1
        18: goto          22
        21: iconst_0
        22: ireturn
      StackMapTable: number_of_entries = 2
        frame_type = 250 /* chop */
          offset_delta = 21
        frame_type = 64 /* same_locals_1_stack_item */
          stack = [ int ]
      LineNumberTable:
        line 416: 0
      LocalVariableTable:
        Start  Length  Slot  Name   Signature
            0      23     0  this   Lcav;

  public void a(boj, gj, ahj, ahl, float, float);
    descriptor: (Lboj;Lgj;Lahj;Lahl;FF)V
    flags: (0x0001) ACC_PUBLIC
    Code:
      stack=12, locals=7, args_size=7
         0: aload_0
         1: aload_1
         2: aload_2
         3: invokevirtual #208                // Method gj.u:()I
         6: i2d
         7: ldc2_w        #511                // double 0.5d
        10: dadd
        11: aload_2
        12: invokevirtual #203                // Method gj.v:()I
        15: i2d
        16: ldc2_w        #511                // double 0.5d
        19: dadd
        20: aload_2
        21: invokevirtual #211                // Method gj.w:()I
        24: i2d
        25: ldc2_w        #511                // double 0.5d
        28: dadd
        29: aload_3
        30: aload         4
        32: fload         5
        34: fload         6
        36: invokevirtual #515                // Method a:(Lboj;DDDLahj;Lahl;FF)V
        39: return
      LineNumberTable:
        line 422: 0
        line 423: 39
      LocalVariableTable:
        Start  Length  Slot  Name   Signature
            0      40     0  this   Lcav;
            0      40     1   $$0   Lboj;
            0      40     2   $$1   Lgj;
            0      40     3   $$2   Lahj;
            0      40     4   $$3   Lahl;
            0      40     5   $$4   F
            0      40     6   $$5   F
    RuntimeVisibleParameterAnnotations:
      parameter 0:
        0: #193()
          javax.annotation.Nullable
      parameter 1:
      parameter 2:
      parameter 3:
      parameter 4:
      parameter 5:

  public abstract void a(boj, double, double, double, ahj, ahl, float, float);
    descriptor: (Lboj;DDDLahj;Lahl;FF)V
    flags: (0x0401) ACC_PUBLIC, ACC_ABSTRACT
    RuntimeVisibleParameterAnnotations:
      parameter 0:
        0: #193()
          javax.annotation.Nullable
      parameter 1:
      parameter 2:
      parameter 3:
      parameter 4:
      parameter 5:
      parameter 6:
      parameter 7:

  public abstract void a(boj, axk, ahj, ahl, float, float);
    descriptor: (Lboj;Laxk;Lahj;Lahl;FF)V
    flags: (0x0401) ACC_PUBLIC, ACC_ABSTRACT
    RuntimeVisibleParameterAnnotations:
      parameter 0:
        0: #193()
          javax.annotation.Nullable
      parameter 1:
      parameter 2:
      parameter 3:
      parameter 4:
      parameter 5:

  public void a(double, double, double, ahj, ahl, float, float, boolean);
    descriptor: (DDDLahj;Lahl;FFZ)V
    flags: (0x0001) ACC_PUBLIC
    Code:
      stack=0, locals=12, args_size=9
         0: return
      LineNumberTable:
        line 432: 0
      LocalVariableTable:
        Start  Length  Slot  Name   Signature
            0       1     0  this   Lcav;
            0       1     1   $$0   D
            0       1     3   $$1   D
            0       1     5   $$2   D
            0       1     7   $$3   Lahj;
            0       1     8   $$4   Lahl;
            0       1     9   $$5   F
            0       1    10   $$6   F
            0       1    11   $$7   Z

  public void a(ia, double, double, double, double, double, double);
    descriptor: (Lia;DDDDDD)V
    flags: (0x0001) ACC_PUBLIC
    Code:
      stack=0, locals=14, args_size=8
         0: return
      LineNumberTable:
        line 436: 0
      LocalVariableTable:
        Start  Length  Slot  Name   Signature
            0       1     0  this   Lcav;
            0       1     1   $$0   Lia;
            0       1     2   $$1   D
            0       1     4   $$2   D
            0       1     6   $$3   D
            0       1     8   $$4   D
            0       1    10   $$5   D
            0       1    12   $$6   D

  public void a(ia, boolean, double, double, double, double, double, double);
    descriptor: (Lia;ZDDDDDD)V
    flags: (0x0001) ACC_PUBLIC
    Code:
      stack=0, locals=15, args_size=9
         0: return
      LineNumberTable:
        line 439: 0
      LocalVariableTable:
        Start  Length  Slot  Name   Signature
            0       1     0  this   Lcav;
            0       1     1   $$0   Lia;
            0       1     2   $$1   Z
            0       1     3   $$2   D
            0       1     5   $$3   D
            0       1     7   $$4   D
            0       1     9   $$5   D
            0       1    11   $$6   D
            0       1    13   $$7   D

  public void b(ia, double, double, double, double, double, double);
    descriptor: (Lia;DDDDDD)V
    flags: (0x0001) ACC_PUBLIC
    Code:
      stack=0, locals=14, args_size=8
         0: return
      LineNumberTable:
        line 444: 0
      LocalVariableTable:
        Start  Length  Slot  Name   Signature
            0       1     0  this   Lcav;
            0       1     1   $$0   Lia;
            0       1     2   $$1   D
            0       1     4   $$2   D
            0       1     6   $$3   D
            0       1     8   $$4   D
            0       1    10   $$5   D
            0       1    12   $$6   D

  public void b(ia, boolean, double, double, double, double, double, double);
    descriptor: (Lia;ZDDDDDD)V
    flags: (0x0001) ACC_PUBLIC
    Code:
      stack=0, locals=15, args_size=9
         0: return
      LineNumberTable:
        line 447: 0
      LocalVariableTable:
        Start  Length  Slot  Name   Signature
            0       1     0  this   Lcav;
            0       1     1   $$0   Lia;
            0       1     2   $$1   Z
            0       1     3   $$2   D
            0       1     5   $$3   D
            0       1     7   $$4   D
            0       1     9   $$5   D
            0       1    11   $$6   D
            0       1    13   $$7   D

  public float a(float);
    descriptor: (F)F
    flags: (0x0001) ACC_PUBLIC
    Code:
      stack=2, locals=3, args_size=2
         0: aload_0
         1: fload_1
         2: invokevirtual #526                // Method f:(F)F
         5: fstore_2
         6: fload_2
         7: ldc_w         #527                // float 6.2831855f
        10: fmul
        11: freturn
      LineNumberTable:
        line 450: 0
        line 451: 6
      LocalVariableTable:
        Start  Length  Slot  Name   Signature
            0      12     0  this   Lcav;
            0      12     1   $$0   F
            6       6     2   $$1   F

  public void a(cny);
    descriptor: (Lcny;)V
    flags: (0x0001) ACC_PUBLIC
    Code:
      stack=2, locals=2, args_size=2
         0: aload_0
         1: getfield      #530                // Field c:Z
         4: ifeq          14
         7: aload_0
         8: getfield      #122                // Field b:Ljava/util/List;
        11: goto          18
        14: aload_0
        15: getfield      #120                // Field o:Ljava/util/List;
        18: aload_1
        19: invokeinterface #538,  2          // InterfaceMethod java/util/List.add:(Ljava/lang/Object;)Z
        24: pop
        25: return
      StackMapTable: number_of_entries = 2
        frame_type = 14 /* same */
        frame_type = 255 /* full_frame */
          offset_delta = 3
          locals = [ top, class cny ]
          stack = [ class java/util/List ]
      LineNumberTable:
        line 455: 0
        line 456: 25
      LocalVariableTable:
        Start  Length  Slot  Name   Signature
            0      26     0  this   Lcav;
            0      26     1   $$0   Lcny;

  protected void Q();
    descriptor: ()V
    flags: (0x0004) ACC_PROTECTED
    Code:
      stack=3, locals=4, args_size=1
         0: aload_0
         1: invokevirtual #282                // Method ab:()Lasy;
         4: astore_1
         5: aload_1
         6: ldc_w         #542                // String blockEntities
         9: invokeinterface #288,  2          // InterfaceMethod asy.a:(Ljava/lang/String;)V
        14: aload_0
        15: iconst_1
        16: putfield      #530                // Field c:Z
        19: aload_0
        20: getfield      #122                // Field b:Ljava/util/List;
        23: invokeinterface #545,  1          // InterfaceMethod java/util/List.isEmpty:()Z
        28: ifne          54
        31: aload_0
        32: getfield      #120                // Field o:Ljava/util/List;
        35: aload_0
        36: getfield      #122                // Field b:Ljava/util/List;
        39: invokeinterface #549,  2          // InterfaceMethod java/util/List.addAll:(Ljava/util/Collection;)Z
        44: pop
        45: aload_0
        46: getfield      #122                // Field b:Ljava/util/List;
        49: invokeinterface #552,  1          // InterfaceMethod java/util/List.clear:()V
        54: aload_0
        55: getfield      #120                // Field o:Ljava/util/List;
        58: invokeinterface #556,  1          // InterfaceMethod java/util/List.iterator:()Ljava/util/Iterator;
        63: astore_2
        64: aload_2
        65: invokeinterface #561,  1          // InterfaceMethod java/util/Iterator.hasNext:()Z
        70: ifeq          126
        73: aload_2
        74: invokeinterface #564,  1          // InterfaceMethod java/util/Iterator.next:()Ljava/lang/Object;
        79: checkcast     #532                // class cny
        82: astore_3
        83: aload_3
        84: invokeinterface #566,  1          // InterfaceMethod cny.b:()Z
        89: ifeq          101
        92: aload_2
        93: invokeinterface #569,  1          // InterfaceMethod java/util/Iterator.remove:()V
        98: goto          123
       101: aload_0
       102: aload_3
       103: invokeinterface #570,  1          // InterfaceMethod cny.c:()Lgj;
       108: invokestatic  #575                // Method cac.a:(Lgj;)J
       111: invokevirtual #578                // Method a:(J)Z
       114: ifeq          123
       117: aload_3
       118: invokeinterface #580,  1          // InterfaceMethod cny.a:()V
       123: goto          64
       126: aload_0
       127: iconst_0
       128: putfield      #530                // Field c:Z
       131: aload_1
       132: invokeinterface #298,  1          // InterfaceMethod asy.c:()V
       137: return
      StackMapTable: number_of_entries = 5
        frame_type = 252 /* append */
          offset_delta = 54
          locals = [ class asy ]
        frame_type = 252 /* append */
          offset_delta = 9
          locals = [ class java/util/Iterator ]
        frame_type = 252 /* append */
          offset_delta = 36
          locals = [ class cny ]
        frame_type = 250 /* chop */
          offset_delta = 21
        frame_type = 250 /* chop */
          offset_delta = 2
      LineNumberTable:
        line 459: 0
        line 460: 5
        line 461: 14
        line 463: 19
        line 464: 31
        line 465: 45
        line 468: 54
        line 469: 64
        line 470: 73
        line 471: 83
        line 472: 92
        line 474: 101
        line 475: 117
        line 478: 123
        line 479: 126
        line 480: 131
        line 481: 137
      LocalVariableTable:
        Start  Length  Slot  Name   Signature
            0     138     0  this   Lcav;
            5     133     1   $$0   Lasy;
           64      74     2   $$1   Ljava/util/Iterator;
           83      40     3   $$2   Lcny;
      LocalVariableTypeTable:
        Start  Length  Slot  Name   Signature
           64      74     2   $$1   Ljava/util/Iterator<Lcny;>;

  public <T extends axk> void a(java.util.function.Consumer<T>, T);
    descriptor: (Ljava/util/function/Consumer;Laxk;)V
    flags: (0x0001) ACC_PUBLIC
    Code:
      stack=3, locals=6, args_size=3
         0: aload_1
         1: aload_2
         2: invokeinterface #591,  2          // InterfaceMethod java/util/function/Consumer.accept:(Ljava/lang/Object;)V
         7: goto          46
        10: astore_3
        11: aload_3
        12: ldc_w         #593                // String Ticking entity
        15: invokestatic  #426                // Method q.a:(Ljava/lang/Throwable;Ljava/lang/String;)Lq;
        18: astore        4
        20: aload         4
        22: ldc_w         #595                // String Entity being ticked
        25: invokevirtual #431                // Method q.a:(Ljava/lang/String;)Lr;
        28: astore        5
        30: aload_2
        31: aload         5
        33: invokevirtual #598                // Method axk.a:(Lr;)V
        36: new           #459                // class z
        39: dup
        40: aload         4
        42: invokespecial #462                // Method z."<init>":(Lq;)V
        45: athrow
        46: return
      Exception table:
         from    to  target type
             0     7    10   Class java/lang/Throwable
      StackMapTable: number_of_entries = 2
        frame_type = 255 /* full_frame */
          offset_delta = 10
          locals = [ top, top, class axk ]
          stack = [ class java/lang/Throwable ]
        frame_type = 248 /* chop */
          offset_delta = 35
      LineNumberTable:
        line 485: 0
        line 493: 7
        line 486: 10
        line 487: 11
        line 488: 20
        line 490: 30
        line 492: 36
        line 494: 46
      LocalVariableTable:
        Start  Length  Slot  Name   Signature
            0      47     0  this   Lcav;
            0      47     1   $$0   Ljava/util/function/Consumer;
            0      47     2   $$1   Laxk;
           11      35     3   $$2   Ljava/lang/Throwable;
           20      26     4   $$3   Lq;
           30      16     5   $$4   Lr;
      LocalVariableTypeTable:
        Start  Length  Slot  Name   Signature
            0      47     1   $$0   Ljava/util/function/Consumer<TT;>;
            0      47     2   $$1   TT;
    Signature: #585                         // <T:Laxk;>(Ljava/util/function/Consumer<TT;>;TT;)V

  public boolean h(axk);
    descriptor: (Laxk;)Z
    flags: (0x0001) ACC_PUBLIC
    Code:
      stack=1, locals=2, args_size=2
         0: iconst_1
         1: ireturn
      LineNumberTable:
        line 497: 0
      LocalVariableTable:
        Start  Length  Slot  Name   Signature
            0       2     0  this   Lcav;
            0       2     1   $$0   Laxk;

  public boolean a(long);
    descriptor: (J)Z
    flags: (0x0001) ACC_PUBLIC
    Code:
      stack=1, locals=3, args_size=2
         0: iconst_1
         1: ireturn
      LineNumberTable:
        line 501: 0
      LocalVariableTable:
        Start  Length  Slot  Name   Signature
            0       2     0  this   Lcav;
            0       2     1   $$0   J

  public can a(axk, double, double, double, float, can$a);
    descriptor: (Laxk;DDDFLcan$a;)Lcan;
    flags: (0x0001) ACC_PUBLIC
    Code:
      stack=13, locals=10, args_size=7
         0: aload_0
         1: aload_1
         2: aconst_null
         3: aconst_null
         4: dload_2
         5: dload         4
         7: dload         6
         9: fload         8
        11: iconst_0
        12: aload         9
        14: invokevirtual #606                // Method a:(Laxk;Lawu;Lcao;DDDFZLcan$a;)Lcan;
        17: areturn
      LineNumberTable:
        line 505: 0
      LocalVariableTable:
        Start  Length  Slot  Name   Signature
            0      18     0  this   Lcav;
            0      18     1   $$0   Laxk;
            0      18     2   $$1   D
            0      18     4   $$2   D
            0      18     6   $$3   D
            0      18     8   $$4   F
            0      18     9   $$5   Lcan$a;
    RuntimeVisibleParameterAnnotations:
      parameter 0:
        0: #193()
          javax.annotation.Nullable
      parameter 1:
      parameter 2:
      parameter 3:
      parameter 4:
      parameter 5:

  public can a(axk, double, double, double, float, boolean, can$a);
    descriptor: (Laxk;DDDFZLcan$a;)Lcan;
    flags: (0x0001) ACC_PUBLIC
    Code:
      stack=13, locals=11, args_size=8
         0: aload_0
         1: aload_1
         2: aconst_null
         3: aconst_null
         4: dload_2
         5: dload         4
         7: dload         6
         9: fload         8
        11: iload         9
        13: aload         10
        15: invokevirtual #606                // Method a:(Laxk;Lawu;Lcao;DDDFZLcan$a;)Lcan;
        18: areturn
      LineNumberTable:
        line 509: 0
      LocalVariableTable:
        Start  Length  Slot  Name   Signature
            0      19     0  this   Lcav;
            0      19     1   $$0   Laxk;
            0      19     2   $$1   D
            0      19     4   $$2   D
            0      19     6   $$3   D
            0      19     8   $$4   F
            0      19     9   $$5   Z
            0      19    10   $$6   Lcan$a;
    RuntimeVisibleParameterAnnotations:
      parameter 0:
        0: #193()
          javax.annotation.Nullable
      parameter 1:
      parameter 2:
      parameter 3:
      parameter 4:
      parameter 5:
      parameter 6:

  public can a(axk, awu, cao, double, double, double, float, boolean, can$a);
    descriptor: (Laxk;Lawu;Lcao;DDDFZLcan$a;)Lcan;
    flags: (0x0001) ACC_PUBLIC
    Code:
      stack=15, locals=14, args_size=10
         0: new           #29                 // class can
         3: dup
         4: aload_0
         5: aload_1
         6: aload_2
         7: aload_3
         8: dload         4
        10: dload         6
        12: dload         8
        14: fload         10
        16: iload         11
        18: aload         12
        20: invokespecial #611                // Method can."<init>":(Lcav;Laxk;Lawu;Lcao;DDDFZLcan$a;)V
        23: astore        13
        25: aload         13
        27: invokevirtual #612                // Method can.a:()V
        30: aload         13
        32: iconst_1
        33: invokevirtual #615                // Method can.a:(Z)V
        36: aload         13
        38: areturn
      LineNumberTable:
        line 513: 0
        line 514: 25
        line 515: 30
        line 516: 36
      LocalVariableTable:
        Start  Length  Slot  Name   Signature
            0      39     0  this   Lcav;
            0      39     1   $$0   Laxk;
            0      39     2   $$1   Lawu;
            0      39     3   $$2   Lcao;
            0      39     4   $$3   D
            0      39     6   $$4   D
            0      39     8   $$5   D
            0      39    10   $$6   F
            0      39    11   $$7   Z
            0      39    12   $$8   Lcan$a;
           25      14    13   $$9   Lcan;
    RuntimeVisibleParameterAnnotations:
      parameter 0:
        0: #193()
          javax.annotation.Nullable
      parameter 1:
        0: #193()
          javax.annotation.Nullable
      parameter 2:
        0: #193()
          javax.annotation.Nullable
      parameter 3:
      parameter 4:
      parameter 5:
      parameter 6:
      parameter 7:
      parameter 8:

  public abstract java.lang.String I();
    descriptor: ()Ljava/lang/String;
    flags: (0x0401) ACC_PUBLIC, ACC_ABSTRACT

  public cmr c_(gj);
    descriptor: (Lgj;)Lcmr;
    flags: (0x0001) ACC_PUBLIC
    Code:
      stack=3, locals=2, args_size=2
         0: aload_0
         1: aload_1
         2: invokevirtual #196                // Method u:(Lgj;)Z
         5: ifeq          10
         8: aconst_null
         9: areturn
        10: aload_0
        11: getfield      #154                // Field x:Z
        14: ifne          29
        17: invokestatic  #171                // Method java/lang/Thread.currentThread:()Ljava/lang/Thread;
        20: aload_0
        21: getfield      #173                // Field y:Ljava/lang/Thread;
        24: if_acmpeq     29
        27: aconst_null
        28: areturn
        29: aload_0
        30: aload_1
        31: invokevirtual #257                // Method l:(Lgj;)Lcra;
        34: aload_1
        35: getstatic     #622                // Field cra$b.a:Lcra$b;
        38: invokevirtual #625                // Method cra.a:(Lgj;Lcra$b;)Lcmr;
        41: areturn
      StackMapTable: number_of_entries = 2
        frame_type = 10 /* same */
        frame_type = 18 /* same */
      LineNumberTable:
        line 524: 0
        line 525: 8
        line 529: 10
        line 530: 27
        line 533: 29
      LocalVariableTable:
        Start  Length  Slot  Name   Signature
            0      42     0  this   Lcav;
            0      42     1   $$0   Lgj;
    RuntimeVisibleAnnotations:
      0: #193()
        javax.annotation.Nullable

  public void a(cmr);
    descriptor: (Lcmr;)V
    flags: (0x0001) ACC_PUBLIC
    Code:
      stack=2, locals=3, args_size=2
         0: aload_1
         1: invokevirtual #628                // Method cmr.p:()Lgj;
         4: astore_2
         5: aload_0
         6: aload_2
         7: invokevirtual #196                // Method u:(Lgj;)Z
        10: ifeq          14
        13: return
        14: aload_0
        15: aload_2
        16: invokevirtual #257                // Method l:(Lgj;)Lcra;
        19: aload_1
        20: invokevirtual #630                // Method cra.b:(Lcmr;)V
        23: return
      StackMapTable: number_of_entries = 1
        frame_type = 252 /* append */
          offset_delta = 14
          locals = [ class gj ]
      LineNumberTable:
        line 537: 0
        line 538: 5
        line 539: 13
        line 542: 14
        line 543: 23
      LocalVariableTable:
        Start  Length  Slot  Name   Signature
            0      24     0  this   Lcav;
            0      24     1   $$0   Lcmr;
            5      19     2   $$1   Lgj;

  public void m(gj);
    descriptor: (Lgj;)V
    flags: (0x0001) ACC_PUBLIC
    Code:
      stack=2, locals=2, args_size=2
         0: aload_0
         1: aload_1
         2: invokevirtual #196                // Method u:(Lgj;)Z
         5: ifeq          9
         8: return
         9: aload_0
        10: aload_1
        11: invokevirtual #257                // Method l:(Lgj;)Lcra;
        14: aload_1
        15: invokevirtual #632                // Method cra.d:(Lgj;)V
        18: return
      StackMapTable: number_of_entries = 1
        frame_type = 9 /* same */
      LineNumberTable:
        line 546: 0
        line 547: 8
        line 550: 9
        line 551: 18
      LocalVariableTable:
        Start  Length  Slot  Name   Signature
            0      19     0  this   Lcav;
            0      19     1   $$0   Lgj;

  public boolean n(gj);
    descriptor: (Lgj;)Z
    flags: (0x0001) ACC_PUBLIC
    Code:
      stack=3, locals=2, args_size=2
         0: aload_0
         1: aload_1
         2: invokevirtual #196                // Method u:(Lgj;)Z
         5: ifeq          10
         8: iconst_0
         9: ireturn
        10: aload_0
        11: invokevirtual #233                // Method K:()Lcqs;
        14: aload_1
        15: invokevirtual #208                // Method gj.u:()I
        18: invokestatic  #217                // Method hf.a:(I)I
        21: aload_1
        22: invokevirtual #211                // Method gj.w:()I
        25: invokestatic  #217                // Method hf.a:(I)I
        28: invokevirtual #633                // Method cqs.b:(II)Z
        31: ireturn
      StackMapTable: number_of_entries = 1
        frame_type = 10 /* same */
      LineNumberTable:
        line 554: 0
        line 555: 8
        line 557: 10
      LocalVariableTable:
        Start  Length  Slot  Name   Signature
            0      32     0  this   Lcav;
            0      32     1   $$0   Lgj;

  public boolean a(gj, axk, go);
    descriptor: (Lgj;Laxk;Lgo;)Z
    flags: (0x0001) ACC_PUBLIC
    Code:
      stack=5, locals=5, args_size=4
         0: aload_0
         1: aload_1
         2: invokevirtual #196                // Method u:(Lgj;)Z
         5: ifeq          10
         8: iconst_0
         9: ireturn
        10: aload_0
        11: aload_1
        12: invokevirtual #208                // Method gj.u:()I
        15: invokestatic  #217                // Method hf.a:(I)I
        18: aload_1
        19: invokevirtual #211                // Method gj.w:()I
        22: invokestatic  #217                // Method hf.a:(I)I
        25: getstatic     #225                // Field cqt.o:Lcqt;
        28: iconst_0
        29: invokevirtual #635                // Method a:(IILcqt;Z)Lcqq;
        32: astore        4
        34: aload         4
        36: ifnonnull     41
        39: iconst_0
        40: ireturn
        41: aload         4
        43: aload_1
        44: invokevirtual #636                // Method cqq.a_:(Lgj;)Lcov;
        47: aload_0
        48: aload_1
        49: aload_2
        50: aload_3
        51: invokevirtual #639                // Method cov.a:(Lcab;Lgj;Laxk;Lgo;)Z
        54: ireturn
      StackMapTable: number_of_entries = 2
        frame_type = 10 /* same */
        frame_type = 252 /* append */
          offset_delta = 30
          locals = [ class cqq ]
      LineNumberTable:
        line 566: 0
        line 567: 8
        line 570: 10
        line 571: 34
        line 572: 39
        line 575: 41
      LocalVariableTable:
        Start  Length  Slot  Name   Signature
            0      55     0  this   Lcav;
            0      55     1   $$0   Lgj;
            0      55     2   $$1   Laxk;
            0      55     3   $$2   Lgo;
           34      21     4   $$3   Lcqq;

  public boolean a(gj, axk);
    descriptor: (Lgj;Laxk;)Z
    flags: (0x0001) ACC_PUBLIC
    Code:
      stack=4, locals=3, args_size=3
         0: aload_0
         1: aload_1
         2: aload_2
         3: getstatic     #411                // Field go.b:Lgo;
         6: invokevirtual #642                // Method a:(Lgj;Laxk;Lgo;)Z
         9: ireturn
      LineNumberTable:
        line 579: 0
      LocalVariableTable:
        Start  Length  Slot  Name   Signature
            0      10     0  this   Lcav;
            0      10     1   $$0   Lgj;
            0      10     2   $$1   Laxk;

  public void R();
    descriptor: ()V
    flags: (0x0001) ACC_PUBLIC
    Code:
      stack=10, locals=7, args_size=1
         0: dconst_1
         1: aload_0
         2: fconst_1
         3: invokevirtual #645                // Method d:(F)F
         6: ldc_w         #646                // float 5.0f
         9: fmul
        10: f2d
        11: ldc2_w        #647                // double 16.0d
        14: ddiv
        15: dsub
        16: dstore_1
        17: dconst_1
        18: aload_0
        19: fconst_1
        20: invokevirtual #650                // Method b:(F)F
        23: ldc_w         #646                // float 5.0f
        26: fmul
        27: f2d
        28: ldc2_w        #647                // double 16.0d
        31: ddiv
        32: dsub
        33: dstore_3
        34: ldc2_w        #511                // double 0.5d
        37: ldc2_w        #651                // double 2.0d
        40: aload_0
        41: fconst_1
        42: invokevirtual #526                // Method f:(F)F
        45: ldc_w         #527                // float 6.2831855f
        48: fmul
        49: invokestatic  #655                // Method ajl.b:(F)F
        52: f2d
        53: ldc2_w        #656                // double -0.25d
        56: ldc2_w        #658                // double 0.25d
        59: invokestatic  #662                // Method ajl.a:(DDD)D
        62: dmul
        63: dadd
        64: dstore        5
        66: aload_0
        67: dconst_1
        68: dload         5
        70: dload_1
        71: dmul
        72: dload_3
        73: dmul
        74: dsub
        75: ldc2_w        #663                // double 11.0d
        78: dmul
        79: d2i
        80: putfield      #506                // Field A:I
        83: return
      LineNumberTable:
        line 583: 0
        line 584: 17
        line 586: 34
        line 588: 66
        line 589: 83
      LocalVariableTable:
        Start  Length  Slot  Name   Signature
            0      84     0  this   Lcav;
           17      67     1   $$0   D
           34      50     3   $$1   D
           66      18     5   $$2   D

  public void b(boolean, boolean);
    descriptor: (ZZ)V
    flags: (0x0001) ACC_PUBLIC
    Code:
      stack=3, locals=3, args_size=3
         0: aload_0
         1: invokevirtual #233                // Method K:()Lcqs;
         4: iload_1
         5: iload_2
         6: invokevirtual #667                // Method cqs.a:(ZZ)V
         9: return
      LineNumberTable:
        line 592: 0
        line 593: 9
      LocalVariableTable:
        Start  Length  Slot  Name   Signature
            0      10     0  this   Lcav;
            0      10     1   $$0   Z
            0      10     2   $$1   Z

  protected void S();
    descriptor: ()V
    flags: (0x0004) ACC_PROTECTED
    Code:
      stack=2, locals=1, args_size=1
         0: aload_0
         1: getfield      #139                // Field w:Ldkw;
         4: invokeinterface #672,  1          // InterfaceMethod dkw.k:()Z
         9: ifeq          34
        12: aload_0
        13: fconst_1
        14: putfield      #674                // Field s:F
        17: aload_0
        18: getfield      #139                // Field w:Ldkw;
        21: invokeinterface #676,  1          // InterfaceMethod dkw.i:()Z
        26: ifeq          34
        29: aload_0
        30: fconst_1
        31: putfield      #678                // Field u:F
        34: return
      StackMapTable: number_of_entries = 1
        frame_type = 250 /* chop */
          offset_delta = 34
      LineNumberTable:
        line 596: 0
        line 597: 12
        line 598: 17
        line 599: 29
        line 602: 34
      LocalVariableTable:
        Start  Length  Slot  Name   Signature
            0      35     0  this   Lcav;

  public void close() throws java.io.IOException;
    descriptor: ()V
    flags: (0x0001) ACC_PUBLIC
    Code:
      stack=1, locals=1, args_size=1
         0: aload_0
         1: invokevirtual #233                // Method K:()Lcqs;
         4: invokevirtual #683                // Method cqs.close:()V
         7: return
      LineNumberTable:
        line 606: 0
        line 607: 7
      LocalVariableTable:
        Start  Length  Slot  Name   Signature
            0       8     0  this   Lcav;
    Exceptions:
      throws java.io.IOException

  public cab c(int, int);
    descriptor: (II)Lcab;
    flags: (0x0001) ACC_PUBLIC
    Code:
      stack=5, locals=3, args_size=3
         0: aload_0
         1: iload_1
         2: iload_2
         3: getstatic     #225                // Field cqt.o:Lcqt;
         6: iconst_0
         7: invokevirtual #635                // Method a:(IILcqt;Z)Lcqq;
        10: areturn
      LineNumberTable:
        line 612: 0
      LocalVariableTable:
        Start  Length  Slot  Name   Signature
            0      11     0  this   Lcav;
            0      11     1   $$0   I
            0      11     2   $$1   I
    RuntimeVisibleAnnotations:
      0: #193()
        javax.annotation.Nullable

  public java.util.List<axk> a(axk, dpj, java.util.function.Predicate<? super axk>);
    descriptor: (Laxk;Ldpj;Ljava/util/function/Predicate;)Ljava/util/List;
    flags: (0x0001) ACC_PUBLIC
    Code:
      stack=5, locals=5, args_size=4
         0: aload_0
         1: invokevirtual #282                // Method ab:()Lasy;
         4: ldc_w         #688                // String getEntities
         7: invokeinterface #690,  2          // InterfaceMethod asy.d:(Ljava/lang/String;)V
        12: invokestatic  #118                // Method com/google/common/collect/Lists.newArrayList:()Ljava/util/ArrayList;
        15: astore        4
        17: aload_0
        18: invokevirtual #693                // Method H:()Lcsp;
        21: aload_2
        22: aload_1
        23: aload_3
        24: aload         4
        26: invokedynamic #703,  0            // InvokeDynamic #1:accept:(Laxk;Ljava/util/function/Predicate;Ljava/util/List;)Ljava/util/function/Consumer;
        31: invokeinterface #708,  3          // InterfaceMethod csp.a:(Ldpj;Ljava/util/function/Consumer;)V
        36: aload         4
        38: areturn
      LineNumberTable:
        line 617: 0
        line 619: 12
        line 620: 17
        line 633: 36
      LocalVariableTable:
        Start  Length  Slot  Name   Signature
            0      39     0  this   Lcav;
            0      39     1   $$0   Laxk;
            0      39     2   $$1   Ldpj;
            0      39     3   $$2   Ljava/util/function/Predicate;
           17      22     4   $$3   Ljava/util/List;
      LocalVariableTypeTable:
        Start  Length  Slot  Name   Signature
            0      39     3   $$2   Ljava/util/function/Predicate<-Laxk;>;
           17      22     4   $$3   Ljava/util/List<Laxk;>;
    Signature: #686                         // (Laxk;Ldpj;Ljava/util/function/Predicate<-Laxk;>;)Ljava/util/List<Laxk;>;
    RuntimeVisibleParameterAnnotations:
      parameter 0:
        0: #193()
          javax.annotation.Nullable
      parameter 1:
      parameter 2:

  public <T extends axk> java.util.List<T> a(csn<axk, T>, dpj, java.util.function.Predicate<? super T>);
    descriptor: (Lcsn;Ldpj;Ljava/util/function/Predicate;)Ljava/util/List;
    flags: (0x0001) ACC_PUBLIC
    Code:
      stack=6, locals=5, args_size=4
         0: aload_0
         1: invokevirtual #282                // Method ab:()Lasy;
         4: ldc_w         #688                // String getEntities
         7: invokeinterface #690,  2          // InterfaceMethod asy.d:(Ljava/lang/String;)V
        12: invokestatic  #118                // Method com/google/common/collect/Lists.newArrayList:()Ljava/util/ArrayList;
        15: astore        4
        17: aload_0
        18: invokevirtual #693                // Method H:()Lcsp;
        21: aload_1
        22: aload_2
        23: aload_3
        24: aload         4
        26: aload_1
        27: invokedynamic #721,  0            // InvokeDynamic #2:accept:(Ljava/util/function/Predicate;Ljava/util/List;Lcsn;)Ljava/util/function/Consumer;
        32: invokeinterface #724,  4          // InterfaceMethod csp.a:(Lcsn;Ldpj;Ljava/util/function/Consumer;)V
        37: aload         4
        39: areturn
      LineNumberTable:
        line 638: 0
        line 640: 12
        line 641: 17
        line 655: 37
      LocalVariableTable:
        Start  Length  Slot  Name   Signature
            0      40     0  this   Lcav;
            0      40     1   $$0   Lcsn;
            0      40     2   $$1   Ldpj;
            0      40     3   $$2   Ljava/util/function/Predicate;
           17      23     4   $$3   Ljava/util/List;
      LocalVariableTypeTable:
        Start  Length  Slot  Name   Signature
            0      40     1   $$0   Lcsn<Laxk;TT;>;
            0      40     3   $$2   Ljava/util/function/Predicate<-TT;>;
           17      23     4   $$3   Ljava/util/List<TT;>;
    Signature: #714                         // <T:Laxk;>(Lcsn<Laxk;TT;>;Ldpj;Ljava/util/function/Predicate<-TT;>;)Ljava/util/List<TT;>;

  public abstract axk a(int);
    descriptor: (I)Laxk;
    flags: (0x0401) ACC_PUBLIC, ACC_ABSTRACT
    RuntimeVisibleAnnotations:
      0: #193()
        javax.annotation.Nullable

  public void o(gj);
    descriptor: (Lgj;)V
    flags: (0x0001) ACC_PUBLIC
    Code:
      stack=2, locals=2, args_size=2
         0: aload_0
         1: aload_1
         2: invokevirtual #731                // Method C:(Lgj;)Z
         5: ifeq          17
         8: aload_0
         9: aload_1
        10: invokevirtual #257                // Method l:(Lgj;)Lcra;
        13: iconst_1
        14: invokevirtual #732                // Method cra.a:(Z)V
        17: return
      StackMapTable: number_of_entries = 1
        frame_type = 249 /* chop */
          offset_delta = 17
      LineNumberTable:
        line 662: 0
        line 663: 8
        line 665: 17
      LocalVariableTable:
        Start  Length  Slot  Name   Signature
            0      18     0  this   Lcav;
            0      18     1   $$0   Lgj;

  public int m_();
    descriptor: ()I
    flags: (0x0001) ACC_PUBLIC
    Code:
      stack=1, locals=1, args_size=1
         0: bipush        63
         2: ireturn
      LineNumberTable:
        line 669: 0
      LocalVariableTable:
        Start  Length  Slot  Name   Signature
            0       3     0  this   Lcav;

  public int p(gj);
    descriptor: (Lgj;)I
    flags: (0x0001) ACC_PUBLIC
    Code:
      stack=4, locals=3, args_size=2
         0: iconst_0
         1: istore_2
         2: iload_2
         3: aload_0
         4: aload_1
         5: invokevirtual #395                // Method gj.c:()Lgj;
         8: getstatic     #409                // Field go.a:Lgo;
        11: invokevirtual #736                // Method c:(Lgj;Lgo;)I
        14: invokestatic  #742                // Method java/lang/Math.max:(II)I
        17: istore_2
        18: iload_2
        19: bipush        15
        21: if_icmplt     26
        24: iload_2
        25: ireturn
        26: iload_2
        27: aload_0
        28: aload_1
        29: invokevirtual #397                // Method gj.b:()Lgj;
        32: getstatic     #411                // Field go.b:Lgo;
        35: invokevirtual #736                // Method c:(Lgj;Lgo;)I
        38: invokestatic  #742                // Method java/lang/Math.max:(II)I
        41: istore_2
        42: iload_2
        43: bipush        15
        45: if_icmplt     50
        48: iload_2
        49: ireturn
        50: iload_2
        51: aload_0
        52: aload_1
        53: invokevirtual #399                // Method gj.d:()Lgj;
        56: getstatic     #413                // Field go.c:Lgo;
        59: invokevirtual #736                // Method c:(Lgj;Lgo;)I
        62: invokestatic  #742                // Method java/lang/Math.max:(II)I
        65: istore_2
        66: iload_2
        67: bipush        15
        69: if_icmplt     74
        72: iload_2
        73: ireturn
        74: iload_2
        75: aload_0
        76: aload_1
        77: invokevirtual #401                // Method gj.e:()Lgj;
        80: getstatic     #415                // Field go.d:Lgo;
        83: invokevirtual #736                // Method c:(Lgj;Lgo;)I
        86: invokestatic  #742                // Method java/lang/Math.max:(II)I
        89: istore_2
        90: iload_2
        91: bipush        15
        93: if_icmplt     98
        96: iload_2
        97: ireturn
        98: iload_2
        99: aload_0
       100: aload_1
       101: invokevirtual #388                // Method gj.f:()Lgj;
       104: getstatic     #405                // Field go.e:Lgo;
       107: invokevirtual #736                // Method c:(Lgj;Lgo;)I
       110: invokestatic  #742                // Method java/lang/Math.max:(II)I
       113: istore_2
       114: iload_2
       115: bipush        15
       117: if_icmplt     122
       120: iload_2
       121: ireturn
       122: iload_2
       123: aload_0
       124: aload_1
       125: invokevirtual #393                // Method gj.g:()Lgj;
       128: getstatic     #407                // Field go.f:Lgo;
       131: invokevirtual #736                // Method c:(Lgj;Lgo;)I
       134: invokestatic  #742                // Method java/lang/Math.max:(II)I
       137: istore_2
       138: iload_2
       139: bipush        15
       141: if_icmplt     146
       144: iload_2
       145: ireturn
       146: iload_2
       147: ireturn
      StackMapTable: number_of_entries = 6
        frame_type = 252 /* append */
          offset_delta = 26
          locals = [ int ]
        frame_type = 23 /* same */
        frame_type = 23 /* same */
        frame_type = 23 /* same */
        frame_type = 23 /* same */
        frame_type = 255 /* full_frame */
          offset_delta = 23
          locals = [ top, top, int ]
          stack = []
      LineNumberTable:
        line 673: 0
        line 674: 2
        line 675: 18
        line 676: 24
        line 678: 26
        line 679: 42
        line 680: 48
        line 682: 50
        line 683: 66
        line 684: 72
        line 686: 74
        line 687: 90
        line 688: 96
        line 690: 98
        line 691: 114
        line 692: 120
        line 694: 122
        line 695: 138
        line 696: 144
        line 698: 146
      LocalVariableTable:
        Start  Length  Slot  Name   Signature
            0     148     0  this   Lcav;
            0     148     1   $$0   Lgj;
            2     146     2   $$1   I

  public boolean a(gj, go);
    descriptor: (Lgj;Lgo;)Z
    flags: (0x0001) ACC_PUBLIC
    Code:
      stack=3, locals=3, args_size=3
         0: aload_0
         1: aload_1
         2: aload_2
         3: invokevirtual #745                // Method b:(Lgj;Lgo;)I
         6: ifle          13
         9: iconst_1
        10: goto          14
        13: iconst_0
        14: ireturn
      StackMapTable: number_of_entries = 2
        frame_type = 248 /* chop */
          offset_delta = 13
        frame_type = 64 /* same_locals_1_stack_item */
          stack = [ int ]
      LineNumberTable:
        line 702: 0
      LocalVariableTable:
        Start  Length  Slot  Name   Signature
            0      15     0  this   Lcav;
            0      15     1   $$0   Lgj;
            0      15     2   $$1   Lgo;

  public int b(gj, go);
    descriptor: (Lgj;Lgo;)I
    flags: (0x0001) ACC_PUBLIC
    Code:
      stack=4, locals=5, args_size=3
         0: aload_0
         1: aload_1
         2: invokevirtual #271                // Method a_:(Lgj;)Lcov;
         5: astore_3
         6: aload_3
         7: aload_0
         8: aload_1
         9: aload_2
        10: invokevirtual #748                // Method cov.b:(Lcab;Lgj;Lgo;)I
        13: istore        4
        15: aload_3
        16: aload_0
        17: aload_1
        18: invokevirtual #751                // Method cov.g:(Lcab;Lgj;)Z
        21: ifeq          35
        24: iload         4
        26: aload_0
        27: aload_1
        28: invokevirtual #753                // Method p:(Lgj;)I
        31: invokestatic  #742                // Method java/lang/Math.max:(II)I
        34: ireturn
        35: iload         4
        37: ireturn
      StackMapTable: number_of_entries = 1
        frame_type = 255 /* full_frame */
          offset_delta = 35
          locals = [ top, top, top, top, int ]
          stack = []
      LineNumberTable:
        line 706: 0
        line 708: 6
        line 709: 15
        line 710: 24
        line 712: 35
      LocalVariableTable:
        Start  Length  Slot  Name   Signature
            0      38     0  this   Lcav;
            0      38     1   $$0   Lgj;
            0      38     2   $$1   Lgo;
            6      32     3   $$2   Lcov;
           15      23     4   $$3   I

  public boolean q(gj);
    descriptor: (Lgj;)Z
    flags: (0x0001) ACC_PUBLIC
    Code:
      stack=3, locals=2, args_size=2
         0: aload_0
         1: aload_1
         2: invokevirtual #395                // Method gj.c:()Lgj;
         5: getstatic     #409                // Field go.a:Lgo;
         8: invokevirtual #745                // Method b:(Lgj;Lgo;)I
        11: ifle          16
        14: iconst_1
        15: ireturn
        16: aload_0
        17: aload_1
        18: invokevirtual #397                // Method gj.b:()Lgj;
        21: getstatic     #411                // Field go.b:Lgo;
        24: invokevirtual #745                // Method b:(Lgj;Lgo;)I
        27: ifle          32
        30: iconst_1
        31: ireturn
        32: aload_0
        33: aload_1
        34: invokevirtual #399                // Method gj.d:()Lgj;
        37: getstatic     #413                // Field go.c:Lgo;
        40: invokevirtual #745                // Method b:(Lgj;Lgo;)I
        43: ifle          48
        46: iconst_1
        47: ireturn
        48: aload_0
        49: aload_1
        50: invokevirtual #401                // Method gj.e:()Lgj;
        53: getstatic     #415                // Field go.d:Lgo;
        56: invokevirtual #745                // Method b:(Lgj;Lgo;)I
        59: ifle          64
        62: iconst_1
        63: ireturn
        64: aload_0
        65: aload_1
        66: invokevirtual #388                // Method gj.f:()Lgj;
        69: getstatic     #405                // Field go.e:Lgo;
        72: invokevirtual #745                // Method b:(Lgj;Lgo;)I
        75: ifle          80
        78: iconst_1
        79: ireturn
        80: aload_0
        81: aload_1
        82: invokevirtual #393                // Method gj.g:()Lgj;
        85: getstatic     #407                // Field go.f:Lgo;
        88: invokevirtual #745                // Method b:(Lgj;Lgo;)I
        91: ifle          96
        94: iconst_1
        95: ireturn
        96: iconst_0
        97: ireturn
      StackMapTable: number_of_entries = 6
        frame_type = 16 /* same */
        frame_type = 15 /* same */
        frame_type = 15 /* same */
        frame_type = 15 /* same */
        frame_type = 15 /* same */
        frame_type = 249 /* chop */
          offset_delta = 15
      LineNumberTable:
        line 716: 0
        line 717: 14
        line 719: 16
        line 720: 30
        line 722: 32
        line 723: 46
        line 725: 48
        line 726: 62
        line 728: 64
        line 729: 78
        line 731: 80
        line 732: 94
        line 734: 96
      LocalVariableTable:
        Start  Length  Slot  Name   Signature
            0      98     0  this   Lcav;
            0      98     1   $$0   Lgj;

  public int r(gj);
    descriptor: (Lgj;)I
    flags: (0x0001) ACC_PUBLIC
    Code:
      stack=3, locals=8, args_size=2
         0: iconst_0
         1: istore_2
         2: getstatic     #755                // Field a:[Lgo;
         5: astore_3
         6: aload_3
         7: arraylength
         8: istore        4
        10: iconst_0
        11: istore        5
        13: iload         5
        15: iload         4
        17: if_icmpge     65
        20: aload_3
        21: iload         5
        23: aaload
        24: astore        6
        26: aload_0
        27: aload_1
        28: aload         6
        30: invokevirtual #759                // Method gj.a:(Lgo;)Lgj;
        33: aload         6
        35: invokevirtual #745                // Method b:(Lgj;Lgo;)I
        38: istore        7
        40: iload         7
        42: bipush        15
        44: if_icmplt     50
        47: bipush        15
        49: ireturn
        50: iload         7
        52: iload_2
        53: if_icmple     59
        56: iload         7
        58: istore_2
        59: iinc          5, 1
        62: goto          13
        65: iload_2
        66: ireturn
      StackMapTable: number_of_entries = 4
        frame_type = 255 /* full_frame */
          offset_delta = 13
          locals = [ class cav, class gj, int, class "[Lgo;", int, int ]
          stack = []
        frame_type = 253 /* append */
          offset_delta = 36
          locals = [ top, int ]
        frame_type = 249 /* chop */
          offset_delta = 8
        frame_type = 255 /* full_frame */
          offset_delta = 5
          locals = [ top, top, int ]
          stack = []
      LineNumberTable:
        line 738: 0
        line 740: 2
        line 741: 26
        line 743: 40
        line 744: 47
        line 746: 50
        line 747: 56
        line 740: 59
        line 751: 65
      LocalVariableTable:
        Start  Length  Slot  Name   Signature
            0      67     0  this   Lcav;
            0      67     1   $$0   Lgj;
            2      65     2   $$1   I
           26      33     6   $$2   Lgo;
           40      19     7   $$3   I

  public void T();
    descriptor: ()V
    flags: (0x0001) ACC_PUBLIC
    Code:
      stack=0, locals=1, args_size=1
         0: return
      LineNumberTable:
        line 755: 0
      LocalVariableTable:
        Start  Length  Slot  Name   Signature
            0       1     0  this   Lcav;

  public long U();
    descriptor: ()J
    flags: (0x0001) ACC_PUBLIC
    Code:
      stack=2, locals=1, args_size=1
         0: aload_0
         1: getfield      #139                // Field w:Ldkw;
         4: invokeinterface #764,  1          // InterfaceMethod dkw.e:()J
         9: lreturn
      LineNumberTable:
        line 761: 0
      LocalVariableTable:
        Start  Length  Slot  Name   Signature
            0      10     0  this   Lcav;

  public long V();
    descriptor: ()J
    flags: (0x0001) ACC_PUBLIC
    Code:
      stack=2, locals=1, args_size=1
         0: aload_0
         1: getfield      #139                // Field w:Ldkw;
         4: invokeinterface #767,  1          // InterfaceMethod dkw.f:()J
         9: lreturn
      LineNumberTable:
        line 769: 0
      LocalVariableTable:
        Start  Length  Slot  Name   Signature
            0      10     0  this   Lcav;

  public boolean a(boj, gj);
    descriptor: (Lboj;Lgj;)Z
    flags: (0x0001) ACC_PUBLIC
    Code:
      stack=1, locals=3, args_size=3
         0: iconst_1
         1: ireturn
      LineNumberTable:
        line 773: 0
      LocalVariableTable:
        Start  Length  Slot  Name   Signature
            0       2     0  this   Lcav;
            0       2     1   $$0   Lboj;
            0       2     2   $$1   Lgj;

  public void a(axk, byte);
    descriptor: (Laxk;B)V
    flags: (0x0001) ACC_PUBLIC
    Code:
      stack=0, locals=3, args_size=3
         0: return
      LineNumberTable:
        line 777: 0
      LocalVariableTable:
        Start  Length  Slot  Name   Signature
            0       1     0  this   Lcav;
            0       1     1   $$0   Laxk;
            0       1     2   $$1   B

  public void a(gj, cdq, int, int);
    descriptor: (Lgj;Lcdq;II)V
    flags: (0x0001) ACC_PUBLIC
    Code:
      stack=5, locals=5, args_size=5
         0: aload_0
         1: aload_1
         2: invokevirtual #271                // Method a_:(Lgj;)Lcov;
         5: aload_0
         6: aload_1
         7: iload_3
         8: iload         4
        10: invokevirtual #773                // Method cov.a:(Lcav;Lgj;II)Z
        13: pop
        14: return
      LineNumberTable:
        line 780: 0
        line 781: 14
      LocalVariableTable:
        Start  Length  Slot  Name   Signature
            0      15     0  this   Lcav;
            0      15     1   $$0   Lgj;
            0      15     2   $$1   Lcdq;
            0      15     3   $$2   I
            0      15     4   $$3   I

  public dkm n_();
    descriptor: ()Ldkm;
    flags: (0x0001) ACC_PUBLIC
    Code:
      stack=1, locals=1, args_size=1
         0: aload_0
         1: getfield      #139                // Field w:Ldkw;
         4: areturn
      LineNumberTable:
        line 785: 0
      LocalVariableTable:
        Start  Length  Slot  Name   Signature
            0       5     0  this   Lcav;

  public car W();
    descriptor: ()Lcar;
    flags: (0x0001) ACC_PUBLIC
    Code:
      stack=1, locals=1, args_size=1
         0: aload_0
         1: getfield      #139                // Field w:Ldkw;
         4: invokeinterface #779,  1          // InterfaceMethod dkw.q:()Lcar;
         9: areturn
      LineNumberTable:
        line 789: 0
      LocalVariableTable:
        Start  Length  Slot  Name   Signature
            0      10     0  this   Lcav;

  public float b(float);
    descriptor: (F)F
    flags: (0x0001) ACC_PUBLIC
    Code:
      stack=3, locals=2, args_size=2
         0: fload_1
         1: aload_0
         2: getfield      #781                // Field t:F
         5: aload_0
         6: getfield      #678                // Field u:F
         9: invokestatic  #784                // Method ajl.i:(FFF)F
        12: aload_0
        13: fload_1
        14: invokevirtual #645                // Method d:(F)F
        17: fmul
        18: freturn
      LineNumberTable:
        line 793: 0
      LocalVariableTable:
        Start  Length  Slot  Name   Signature
            0      19     0  this   Lcav;
            0      19     1   $$0   F

  public void c(float);
    descriptor: (F)V
    flags: (0x0001) ACC_PUBLIC
    Code:
      stack=3, locals=3, args_size=2
         0: fload_1
         1: fconst_0
         2: fconst_1
         3: invokestatic  #787                // Method ajl.a:(FFF)F
         6: fstore_2
         7: aload_0
         8: fload_2
         9: putfield      #781                // Field t:F
        12: aload_0
        13: fload_2
        14: putfield      #678                // Field u:F
        17: return
      LineNumberTable:
        line 797: 0
        line 798: 7
        line 799: 12
        line 800: 17
      LocalVariableTable:
        Start  Length  Slot  Name   Signature
            0      18     0  this   Lcav;
            0      18     1   $$0   F
            7      11     2   $$1   F

  public float d(float);
    descriptor: (F)F
    flags: (0x0001) ACC_PUBLIC
    Code:
      stack=3, locals=2, args_size=2
         0: fload_1
         1: aload_0
         2: getfield      #789                // Field r:F
         5: aload_0
         6: getfield      #674                // Field s:F
         9: invokestatic  #784                // Method ajl.i:(FFF)F
        12: freturn
      LineNumberTable:
        line 803: 0
      LocalVariableTable:
        Start  Length  Slot  Name   Signature
            0      13     0  this   Lcav;
            0      13     1   $$0   F

  public void e(float);
    descriptor: (F)V
    flags: (0x0001) ACC_PUBLIC
    Code:
      stack=3, locals=3, args_size=2
         0: fload_1
         1: fconst_0
         2: fconst_1
         3: invokestatic  #787                // Method ajl.a:(FFF)F
         6: fstore_2
         7: aload_0
         8: fload_2
         9: putfield      #789                // Field r:F
        12: aload_0
        13: fload_2
        14: putfield      #674                // Field s:F
        17: return
      LineNumberTable:
        line 807: 0
        line 808: 7
        line 809: 12
        line 810: 17
      LocalVariableTable:
        Start  Length  Slot  Name   Signature
            0      18     0  this   Lcav;
            0      18     1   $$0   F
            7      11     2   $$1   F

  public boolean X();
    descriptor: ()Z
    flags: (0x0001) ACC_PUBLIC
    Code:
      stack=4, locals=1, args_size=1
         0: aload_0
         1: invokevirtual #503                // Method q_:()Lcry;
         4: invokevirtual #792                // Method cry.a:()Z
         7: ifeq          20
        10: aload_0
        11: invokevirtual #503                // Method q_:()Lcry;
        14: invokevirtual #793                // Method cry.b:()Z
        17: ifeq          22
        20: iconst_0
        21: ireturn
        22: aload_0
        23: fconst_1
        24: invokevirtual #650                // Method b:(F)F
        27: f2d
        28: ldc2_w        #794                // double 0.9d
        31: dcmpl
        32: ifle          39
        35: iconst_1
        36: goto          40
        39: iconst_0
        40: ireturn
      StackMapTable: number_of_entries = 4
        frame_type = 250 /* chop */
          offset_delta = 20
        frame_type = 252 /* append */
          offset_delta = 1
          locals = [ class cav ]
        frame_type = 250 /* chop */
          offset_delta = 16
        frame_type = 64 /* same_locals_1_stack_item */
          stack = [ int ]
      LineNumberTable:
        line 813: 0
        line 814: 20
        line 816: 22
      LocalVariableTable:
        Start  Length  Slot  Name   Signature
            0      41     0  this   Lcav;

  public boolean Y();
    descriptor: ()Z
    flags: (0x0001) ACC_PUBLIC
    Code:
      stack=4, locals=1, args_size=1
         0: aload_0
         1: fconst_1
         2: invokevirtual #645                // Method d:(F)F
         5: f2d
         6: ldc2_w        #797                // double 0.2d
         9: dcmpl
        10: ifle          17
        13: iconst_1
        14: goto          18
        17: iconst_0
        18: ireturn
      StackMapTable: number_of_entries = 2
        frame_type = 250 /* chop */
          offset_delta = 17
        frame_type = 64 /* same_locals_1_stack_item */
          stack = [ int ]
      LineNumberTable:
        line 820: 0
      LocalVariableTable:
        Start  Length  Slot  Name   Signature
            0      19     0  this   Lcav;

  public boolean s(gj);
    descriptor: (Lgj;)Z
    flags: (0x0001) ACC_PUBLIC
    Code:
      stack=3, locals=3, args_size=2
         0: aload_0
         1: invokevirtual #800                // Method Y:()Z
         4: ifne          9
         7: iconst_0
         8: ireturn
         9: aload_0
        10: aload_1
        11: invokevirtual #802                // Method g:(Lgj;)Z
        14: ifne          19
        17: iconst_0
        18: ireturn
        19: aload_0
        20: getstatic     #804                // Field ctw$a.e:Lctw$a;
        23: aload_1
        24: invokevirtual #807                // Method a:(Lctw$a;Lgj;)Lgj;
        27: invokevirtual #203                // Method gj.v:()I
        30: aload_1
        31: invokevirtual #203                // Method gj.v:()I
        34: if_icmple     39
        37: iconst_0
        38: ireturn
        39: aload_0
        40: aload_1
        41: invokevirtual #810                // Method v:(Lgj;)Lgs;
        44: invokeinterface #146,  1          // InterfaceMethod gs.a:()Ljava/lang/Object;
        49: checkcast     #38                 // class cbr
        52: astore_2
        53: aload_2
        54: invokevirtual #813                // Method cbr.c:()Lcbr$d;
        57: getstatic     #816                // Field cbr$d.b:Lcbr$d;
        60: if_acmpne     75
        63: aload_2
        64: aload_1
        65: invokevirtual #818                // Method cbr.b:(Lgj;)Z
        68: ifeq          75
        71: iconst_1
        72: goto          76
        75: iconst_0
        76: ireturn
      StackMapTable: number_of_entries = 5
        frame_type = 9 /* same */
        frame_type = 9 /* same */
        frame_type = 19 /* same */
        frame_type = 249 /* chop */
          offset_delta = 35
        frame_type = 64 /* same_locals_1_stack_item */
          stack = [ int ]
      LineNumberTable:
        line 824: 0
        line 825: 7
        line 827: 9
        line 828: 17
        line 830: 19
        line 831: 37
        line 834: 39
        line 836: 53
      LocalVariableTable:
        Start  Length  Slot  Name   Signature
            0      77     0  this   Lcav;
            0      77     1   $$0   Lgj;
           53      24     2   $$1   Lcbr;

  public boolean t(gj);
    descriptor: (Lgj;)Z
    flags: (0x0001) ACC_PUBLIC
    Code:
      stack=2, locals=3, args_size=2
         0: aload_0
         1: aload_1
         2: invokevirtual #810                // Method v:(Lgj;)Lgs;
         5: invokeinterface #146,  1          // InterfaceMethod gs.a:()Ljava/lang/Object;
        10: checkcast     #38                 // class cbr
        13: astore_2
        14: aload_2
        15: invokevirtual #821                // Method cbr.d:()Z
        18: ireturn
      LineNumberTable:
        line 840: 0
        line 841: 14
      LocalVariableTable:
        Start  Length  Slot  Name   Signature
            0      19     0  this   Lcav;
            0      19     1   $$0   Lgj;
           14       5     2   $$1   Lcbr;

  public abstract dkf a(java.lang.String);
    descriptor: (Ljava/lang/String;)Ldkf;
    flags: (0x0401) ACC_PUBLIC, ACC_ABSTRACT
    RuntimeVisibleAnnotations:
      0: #193()
        javax.annotation.Nullable

  public abstract void a(java.lang.String, dkf);
    descriptor: (Ljava/lang/String;Ldkf;)V
    flags: (0x0401) ACC_PUBLIC, ACC_ABSTRACT

  public abstract int u();
    descriptor: ()I
    flags: (0x0401) ACC_PUBLIC, ACC_ABSTRACT

  public void b(int, gj, int);
    descriptor: (ILgj;I)V
    flags: (0x0001) ACC_PUBLIC
    Code:
      stack=0, locals=4, args_size=4
         0: return
      LineNumberTable:
        line 852: 0
      LocalVariableTable:
        Start  Length  Slot  Name   Signature
            0       1     0  this   Lcav;
            0       1     1   $$0   I
            0       1     2   $$1   Lgj;
            0       1     3   $$2   I

  public r a(q);
    descriptor: (Lq;)Lr;
    flags: (0x0001) ACC_PUBLIC
    Code:
      stack=4, locals=4, args_size=2
         0: aload_1
         1: ldc_w         #826                // String Affected level
         4: iconst_1
         5: invokevirtual #829                // Method q.a:(Ljava/lang/String;I)Lr;
         8: astore_2
         9: aload_2
        10: ldc_w         #831                // String All players
        13: aload_0
        14: invokedynamic #837,  0            // InvokeDynamic #3:call:(Lcav;)Ls;
        19: invokevirtual #455                // Method r.a:(Ljava/lang/String;Ls;)Lr;
        22: pop
        23: aload_2
        24: ldc_w         #839                // String Chunk stats
        27: aload_0
        28: invokevirtual #233                // Method K:()Lcqs;
        31: dup
        32: invokestatic  #845                // Method java/util/Objects.requireNonNull:(Ljava/lang/Object;)Ljava/lang/Object;
        35: pop
        36: invokedynamic #851,  0            // InvokeDynamic #4:call:(Lcqs;)Ls;
        41: invokevirtual #455                // Method r.a:(Ljava/lang/String;Ls;)Lr;
        44: pop
        45: aload_2
        46: ldc_w         #853                // String Level dimension
        49: aload_0
        50: invokedynamic #857,  0            // InvokeDynamic #5:call:(Lcav;)Ls;
        55: invokevirtual #455                // Method r.a:(Ljava/lang/String;Ls;)Lr;
        58: pop
        59: aload_0
        60: getfield      #139                // Field w:Ldkw;
        63: aload_2
        64: aload_0
        65: invokeinterface #860,  3          // InterfaceMethod dkw.a:(Lr;Lcax;)V
        70: goto          82
        73: astore_3
        74: aload_2
        75: ldc_w         #862                // String Level Data Unobtainable
        78: aload_3
        79: invokevirtual #865                // Method r.a:(Ljava/lang/String;Ljava/lang/Throwable;)V
        82: aload_2
        83: areturn
      Exception table:
         from    to  target type
            59    70    73   Class java/lang/Throwable
      StackMapTable: number_of_entries = 2
        frame_type = 255 /* full_frame */
          offset_delta = 73
          locals = [ top, top, class r ]
          stack = [ class java/lang/Throwable ]
        frame_type = 8 /* same */
      LineNumberTable:
        line 855: 0
        line 857: 9
        line 858: 23
        line 859: 45
        line 862: 59
        line 865: 70
        line 863: 73
        line 864: 74
        line 867: 82
      LocalVariableTable:
        Start  Length  Slot  Name   Signature
            0      84     0  this   Lcav;
            0      84     1   $$0   Lq;
            9      75     2   $$1   Lr;
           74       8     3   $$2   Ljava/lang/Throwable;

  public abstract void a(int, gj, int);
    descriptor: (ILgj;I)V
    flags: (0x0401) ACC_PUBLIC, ACC_ABSTRACT

  public void a(double, double, double, double, double, double, ok);
    descriptor: (DDDDDDLok;)V
    flags: (0x0001) ACC_PUBLIC
    Code:
      stack=0, locals=14, args_size=8
         0: return
      LineNumberTable:
        line 873: 0
      LocalVariableTable:
        Start  Length  Slot  Name   Signature
            0       1     0  this   Lcav;
            0       1     1   $$0   D
            0       1     3   $$1   D
            0       1     5   $$2   D
            0       1     7   $$3   D
            0       1     9   $$4   D
            0       1    11   $$5   D
            0       1    13   $$6   Lok;
    RuntimeVisibleParameterAnnotations:
      parameter 0:
      parameter 1:
      parameter 2:
      parameter 3:
      parameter 4:
      parameter 5:
      parameter 6:
        0: #193()
          javax.annotation.Nullable

  public abstract dqm J();
    descriptor: ()Ldqm;
    flags: (0x0401) ACC_PUBLIC, ACC_ABSTRACT

  public void c(gj, cdq);
    descriptor: (Lgj;Lcdq;)V
    flags: (0x0001) ACC_PUBLIC
    Code:
      stack=6, locals=7, args_size=3
         0: getstatic     #871                // Field go$c.a:Lgo$c;
         3: invokevirtual #872                // Method go$c.iterator:()Ljava/util/Iterator;
         6: astore_3
         7: aload_3
         8: invokeinterface #561,  1          // InterfaceMethod java/util/Iterator.hasNext:()Z
        13: ifeq          130
        16: aload_3
        17: invokeinterface #564,  1          // InterfaceMethod java/util/Iterator.next:()Ljava/lang/Object;
        22: checkcast     #43                 // class go
        25: astore        4
        27: aload_1
        28: aload         4
        30: invokevirtual #759                // Method gj.a:(Lgo;)Lgj;
        33: astore        5
        35: aload_0
        36: aload         5
        38: invokevirtual #731                // Method C:(Lgj;)Z
        41: ifeq          127
        44: aload_0
        45: aload         5
        47: invokevirtual #271                // Method a_:(Lgj;)Lcov;
        50: astore        6
        52: aload         6
        54: getstatic     #875                // Field cdr.fH:Lcdq;
        57: invokevirtual #878                // Method cov.a:(Lcdq;)Z
        60: ifeq          77
        63: aload         6
        65: aload_0
        66: aload         5
        68: aload_2
        69: aload_1
        70: iconst_0
        71: invokevirtual #420                // Method cov.a:(Lcav;Lgj;Lcdq;Lgj;Z)V
        74: goto          127
        77: aload         6
        79: aload_0
        80: aload         5
        82: invokevirtual #751                // Method cov.g:(Lcab;Lgj;)Z
        85: ifeq          127
        88: aload         5
        90: aload         4
        92: invokevirtual #759                // Method gj.a:(Lgo;)Lgj;
        95: astore        5
        97: aload_0
        98: aload         5
       100: invokevirtual #271                // Method a_:(Lgj;)Lcov;
       103: astore        6
       105: aload         6
       107: getstatic     #875                // Field cdr.fH:Lcdq;
       110: invokevirtual #878                // Method cov.a:(Lcdq;)Z
       113: ifeq          127
       116: aload         6
       118: aload_0
       119: aload         5
       121: aload_2
       122: aload_1
       123: iconst_0
       124: invokevirtual #420                // Method cov.a:(Lcav;Lgj;Lcdq;Lgj;Z)V
       127: goto          7
       130: return
      StackMapTable: number_of_entries = 4
        frame_type = 252 /* append */
          offset_delta = 7
          locals = [ class java/util/Iterator ]
        frame_type = 254 /* append */
          offset_delta = 69
          locals = [ class go, class gj, class cov ]
        frame_type = 248 /* chop */
          offset_delta = 49
        frame_type = 255 /* full_frame */
          offset_delta = 2
          locals = []
          stack = []
      LineNumberTable:
        line 878: 0
        line 879: 27
        line 881: 35
        line 882: 44
        line 883: 52
        line 884: 63
        line 885: 77
        line 886: 88
        line 887: 97
        line 889: 105
        line 890: 116
        line 894: 127
        line 895: 130
      LocalVariableTable:
        Start  Length  Slot  Name   Signature
            0     131     0  this   Lcav;
            0     131     1   $$0   Lgj;
            0     131     2   $$1   Lcdq;
           27     100     4   $$2   Lgo;
           35      92     5   $$3   Lgj;
           52      75     6   $$4   Lcov;

  public awf d_(gj);
    descriptor: (Lgj;)Lawf;
    flags: (0x0001) ACC_PUBLIC
    Code:
      stack=8, locals=5, args_size=2
         0: lconst_0
         1: lstore_2
         2: fconst_0
         3: fstore        4
         5: aload_0
         6: aload_1
         7: invokevirtual #731                // Method C:(Lgj;)Z
        10: ifeq          28
        13: aload_0
        14: invokevirtual #884                // Method ak:()F
        17: fstore        4
        19: aload_0
        20: aload_1
        21: invokevirtual #257                // Method l:(Lgj;)Lcra;
        24: invokevirtual #886                // Method cra.u:()J
        27: lstore_2
        28: new           #888                // class awf
        31: dup
        32: aload_0
        33: invokevirtual #892                // Method af:()Lawe;
        36: aload_0
        37: invokevirtual #894                // Method V:()J
        40: lload_2
        41: fload         4
        43: invokespecial #897                // Method awf."<init>":(Lawe;JJF)V
        46: areturn
      StackMapTable: number_of_entries = 1
        frame_type = 255 /* full_frame */
          offset_delta = 28
          locals = [ class cav, top, long, float ]
          stack = []
      LineNumberTable:
        line 899: 0
        line 900: 2
        line 901: 5
        line 902: 13
        line 903: 19
        line 906: 28
      LocalVariableTable:
        Start  Length  Slot  Name   Signature
            0      47     0  this   Lcav;
            0      47     1   $$0   Lgj;
            2      45     2   $$1   J
            5      42     4   $$2   F

  public int o_();
    descriptor: ()I
    flags: (0x0001) ACC_PUBLIC
    Code:
      stack=1, locals=1, args_size=1
         0: aload_0
         1: getfield      #506                // Field A:I
         4: ireturn
      LineNumberTable:
        line 911: 0
      LocalVariableTable:
        Start  Length  Slot  Name   Signature
            0       5     0  this   Lcav;

  public void c(int);
    descriptor: (I)V
    flags: (0x0001) ACC_PUBLIC
    Code:
      stack=0, locals=2, args_size=2
         0: return
      LineNumberTable:
        line 915: 0
      LocalVariableTable:
        Start  Length  Slot  Name   Signature
            0       1     0  this   Lcav;
            0       1     1   $$0   I

  public cql p_();
    descriptor: ()Lcql;
    flags: (0x0001) ACC_PUBLIC
    Code:
      stack=1, locals=1, args_size=1
         0: aload_0
         1: getfield      #162                // Field E:Lcql;
         4: areturn
      LineNumberTable:
        line 919: 0
      LocalVariableTable:
        Start  Length  Slot  Name   Signature
            0       5     0  this   Lcav;

  public void a(rc<?>);
    descriptor: (Lrc;)V
    flags: (0x0001) ACC_PUBLIC
    Code:
      stack=3, locals=2, args_size=2
         0: new           #905                // class java/lang/UnsupportedOperationException
         3: dup
         4: ldc_w         #907                // String Can\'t send packets to server unless you\'re on the client.
         7: invokespecial #908                // Method java/lang/UnsupportedOperationException."<init>":(Ljava/lang/String;)V
        10: athrow
      LineNumberTable:
        line 923: 0
      LocalVariableTable:
        Start  Length  Slot  Name   Signature
            0      11     0  this   Lcav;
            0      11     1   $$0   Lrc;
      LocalVariableTypeTable:
        Start  Length  Slot  Name   Signature
            0      11     1   $$0   Lrc<*>;
    Signature: #903                         // (Lrc<*>;)V

  public cry q_();
    descriptor: ()Lcry;
    flags: (0x0001) ACC_PUBLIC
    Code:
      stack=1, locals=1, args_size=1
         0: aload_0
         1: getfield      #150                // Field B:Lcry;
         4: areturn
      LineNumberTable:
        line 928: 0
      LocalVariableTable:
        Start  Length  Slot  Name   Signature
            0       5     0  this   Lcav;

  public gs<cry> Z();
    descriptor: ()Lgs;
    flags: (0x0001) ACC_PUBLIC
    Code:
      stack=1, locals=1, args_size=1
         0: aload_0
         1: getfield      #141                // Field C:Lgs;
         4: areturn
      LineNumberTable:
        line 932: 0
      LocalVariableTable:
        Start  Length  Slot  Name   Signature
            0       5     0  this   Lcav;
    Signature: #912                         // ()Lgs<Lcry;>;

  public ys<cav> aa();
    descriptor: ()Lys;
    flags: (0x0001) ACC_PUBLIC
    Code:
      stack=1, locals=1, args_size=1
         0: aload_0
         1: getfield      #152                // Field G:Lys;
         4: areturn
      LineNumberTable:
        line 936: 0
      LocalVariableTable:
        Start  Length  Slot  Name   Signature
            0       5     0  this   Lcav;
    Signature: #915                         // ()Lys<Lcav;>;

  public java.util.Random r_();
    descriptor: ()Ljava/util/Random;
    flags: (0x0001) ACC_PUBLIC
    Code:
      stack=1, locals=1, args_size=1
         0: aload_0
         1: getfield      #135                // Field v:Ljava/util/Random;
         4: areturn
      LineNumberTable:
        line 941: 0
      LocalVariableTable:
        Start  Length  Slot  Name   Signature
            0       5     0  this   Lcav;

  public boolean a(gj, java.util.function.Predicate<cov>);
    descriptor: (Lgj;Ljava/util/function/Predicate;)Z
    flags: (0x0001) ACC_PUBLIC
    Code:
      stack=3, locals=3, args_size=3
         0: aload_2
         1: aload_0
         2: aload_1
         3: invokevirtual #271                // Method a_:(Lgj;)Lcov;
         6: invokeinterface #924,  2          // InterfaceMethod java/util/function/Predicate.test:(Ljava/lang/Object;)Z
        11: ireturn
      LineNumberTable:
        line 946: 0
      LocalVariableTable:
        Start  Length  Slot  Name   Signature
            0      12     0  this   Lcav;
            0      12     1   $$0   Lgj;
            0      12     2   $$1   Ljava/util/function/Predicate;
      LocalVariableTypeTable:
        Start  Length  Slot  Name   Signature
            0      12     2   $$1   Ljava/util/function/Predicate<Lcov;>;
    Signature: #919                         // (Lgj;Ljava/util/function/Predicate<Lcov;>;)Z

  public boolean b(gj, java.util.function.Predicate<dix>);
    descriptor: (Lgj;Ljava/util/function/Predicate;)Z
    flags: (0x0001) ACC_PUBLIC
    Code:
      stack=3, locals=3, args_size=3
         0: aload_2
         1: aload_0
         2: aload_1
         3: invokevirtual #336                // Method b_:(Lgj;)Ldix;
         6: invokeinterface #924,  2          // InterfaceMethod java/util/function/Predicate.test:(Ljava/lang/Object;)Z
        11: ireturn
      LineNumberTable:
        line 951: 0
      LocalVariableTable:
        Start  Length  Slot  Name   Signature
            0      12     0  this   Lcav;
            0      12     1   $$0   Lgj;
            0      12     2   $$1   Ljava/util/function/Predicate;
      LocalVariableTypeTable:
        Start  Length  Slot  Name   Signature
            0      12     2   $$1   Ljava/util/function/Predicate<Ldix;>;
    Signature: #926                         // (Lgj;Ljava/util/function/Predicate<Ldix;>;)Z

  public abstract bxp q();
    descriptor: ()Lbxp;
    flags: (0x0401) ACC_PUBLIC, ACC_ABSTRACT

  public gj a(int, int, int, int);
    descriptor: (IIII)Lgj;
    flags: (0x0001) ACC_PUBLIC
    Code:
      stack=7, locals=6, args_size=5
         0: aload_0
         1: aload_0
         2: getfield      #131                // Field p:I
         5: iconst_3
         6: imul
         7: ldc           #82                 // int 1013904223
         9: iadd
        10: putfield      #131                // Field p:I
        13: aload_0
        14: getfield      #131                // Field p:I
        17: iconst_2
        18: ishr
        19: istore        5
        21: new           #201                // class gj
        24: dup
        25: iload_1
        26: iload         5
        28: bipush        15
        30: iand
        31: iadd
        32: iload_2
        33: iload         5
        35: bipush        16
        37: ishr
        38: iload         4
        40: iand
        41: iadd
        42: iload_3
        43: iload         5
        45: bipush        8
        47: ishr
        48: bipush        15
        50: iand
        51: iadd
        52: invokespecial #932                // Method gj."<init>":(III)V
        55: areturn
      LineNumberTable:
        line 957: 0
        line 958: 13
        line 960: 21
      LocalVariableTable:
        Start  Length  Slot  Name   Signature
            0      56     0  this   Lcav;
            0      56     1   $$0   I
            0      56     2   $$1   I
            0      56     3   $$2   I
            0      56     4   $$3   I
           21      35     5   $$4   I

  public boolean r();
    descriptor: ()Z
    flags: (0x0001) ACC_PUBLIC
    Code:
      stack=1, locals=1, args_size=1
         0: iconst_0
         1: ireturn
      LineNumberTable:
        line 964: 0
      LocalVariableTable:
        Start  Length  Slot  Name   Signature
            0       2     0  this   Lcav;

  public asy ab();
    descriptor: ()Lasy;
    flags: (0x0001) ACC_PUBLIC
    Code:
      stack=1, locals=1, args_size=1
         0: aload_0
         1: getfield      #137                // Field D:Ljava/util/function/Supplier;
         4: invokeinterface #937,  1          // InterfaceMethod java/util/function/Supplier.get:()Ljava/lang/Object;
         9: checkcast     #286                // class asy
        12: areturn
      LineNumberTable:
        line 968: 0
      LocalVariableTable:
        Start  Length  Slot  Name   Signature
            0      13     0  this   Lcav;

  public java.util.function.Supplier<asy> ac();
    descriptor: ()Ljava/util/function/Supplier;
    flags: (0x0001) ACC_PUBLIC
    Code:
      stack=1, locals=1, args_size=1
         0: aload_0
         1: getfield      #137                // Field D:Ljava/util/function/Supplier;
         4: areturn
      LineNumberTable:
        line 972: 0
      LocalVariableTable:
        Start  Length  Slot  Name   Signature
            0       5     0  this   Lcav;
    Signature: #940                         // ()Ljava/util/function/Supplier<Lasy;>;

  public cbt s_();
    descriptor: ()Lcbt;
    flags: (0x0001) ACC_PUBLIC
    Code:
      stack=1, locals=1, args_size=1
         0: aload_0
         1: getfield      #178                // Field F:Lcbt;
         4: areturn
      LineNumberTable:
        line 977: 0
      LocalVariableTable:
        Start  Length  Slot  Name   Signature
            0       5     0  this   Lcav;

  public final boolean ad();
    descriptor: ()Z
    flags: (0x0011) ACC_PUBLIC, ACC_FINAL
    Code:
      stack=1, locals=1, args_size=1
         0: aload_0
         1: getfield      #180                // Field z:Z
         4: ireturn
      LineNumberTable:
        line 981: 0
      LocalVariableTable:
        Start  Length  Slot  Name   Signature
            0       5     0  this   Lcav;

  protected abstract csp<axk> H();
    descriptor: ()Lcsp;
    flags: (0x0404) ACC_PROTECTED, ACC_ABSTRACT
    Signature: #943                         // ()Lcsp<Laxk;>;

  protected void a(axk, csy, gj, int);
    descriptor: (Laxk;Lcsy;Lgj;I)V
    flags: (0x0004) ACC_PROTECTED
    Code:
      stack=4, locals=15, args_size=5
         0: aload_3
         1: invokevirtual #208                // Method gj.u:()I
         4: iload         4
         6: isub
         7: invokestatic  #217                // Method hf.a:(I)I
        10: istore        5
        12: aload_3
        13: invokevirtual #211                // Method gj.w:()I
        16: iload         4
        18: isub
        19: invokestatic  #217                // Method hf.a:(I)I
        22: istore        6
        24: aload_3
        25: invokevirtual #208                // Method gj.u:()I
        28: iload         4
        30: iadd
        31: invokestatic  #217                // Method hf.a:(I)I
        34: istore        7
        36: aload_3
        37: invokevirtual #211                // Method gj.w:()I
        40: iload         4
        42: iadd
        43: invokestatic  #217                // Method hf.a:(I)I
        46: istore        8
        48: aload_3
        49: invokevirtual #203                // Method gj.v:()I
        52: iload         4
        54: isub
        55: invokestatic  #217                // Method hf.a:(I)I
        58: istore        9
        60: aload_3
        61: invokevirtual #203                // Method gj.v:()I
        64: iload         4
        66: iadd
        67: invokestatic  #217                // Method hf.a:(I)I
        70: istore        10
        72: iload         5
        74: istore        11
        76: iload         11
        78: iload         7
        80: if_icmpgt     156
        83: iload         6
        85: istore        12
        87: iload         12
        89: iload         8
        91: if_icmpgt     150
        94: aload_0
        95: invokevirtual #233                // Method K:()Lcqs;
        98: iload         11
       100: iload         12
       102: invokevirtual #946                // Method cqs.a:(II)Lcra;
       105: astore        13
       107: aload         13
       109: ifnull        144
       112: iload         9
       114: istore        14
       116: iload         14
       118: iload         10
       120: if_icmpgt     144
       123: aload         13
       125: iload         14
       127: invokevirtual #949                // Method cqq.a:(I)Lcsz;
       130: aload_2
       131: aload_1
       132: aload_3
       133: invokeinterface #954,  4          // InterfaceMethod csz.a:(Lcsy;Laxk;Lgj;)V
       138: iinc          14, 1
       141: goto          116
       144: iinc          12, 1
       147: goto          87
       150: iinc          11, 1
       153: goto          76
       156: return
      StackMapTable: number_of_entries = 6
        frame_type = 255 /* full_frame */
          offset_delta = 76
          locals = [ class cav, class axk, class csy, class gj, top, top, int, int, int, int, int, int ]
          stack = []
        frame_type = 252 /* append */
          offset_delta = 10
          locals = [ int ]
        frame_type = 253 /* append */
          offset_delta = 28
          locals = [ class cra, int ]
        frame_type = 249 /* chop */
          offset_delta = 27
        frame_type = 250 /* chop */
          offset_delta = 5
        frame_type = 255 /* full_frame */
          offset_delta = 5
          locals = []
          stack = []
      LineNumberTable:
        line 987: 0
        line 988: 12
        line 989: 24
        line 990: 36
        line 991: 48
        line 992: 60
        line 994: 72
        line 995: 83
        line 996: 94
        line 998: 107
        line 999: 112
        line 1000: 123
        line 999: 138
        line 995: 144
        line 994: 150
        line 1005: 156
      LocalVariableTable:
        Start  Length  Slot  Name   Signature
            0     157     0  this   Lcav;
            0     157     1   $$0   Laxk;
            0     157     2   $$1   Lcsy;
            0     157     3   $$2   Lgj;
            0     157     4   $$3   I
           12     145     5   $$4   I
           24     133     6   $$5   I
           36     121     7   $$6   I
           48     109     8   $$7   I
           60      97     9   $$8   I
           72      85    10   $$9   I
           76      80    11  $$10   I
           87      63    12  $$11   I
          107      37    13  $$12   Lcqq;
          116      28    14  $$13   I
    RuntimeVisibleParameterAnnotations:
      parameter 0:
        0: #193()
          javax.annotation.Nullable
      parameter 1:
      parameter 2:
      parameter 3:

  public long t_();
    descriptor: ()J
    flags: (0x0001) ACC_PUBLIC
    Code:
      stack=7, locals=1, args_size=1
         0: aload_0
         1: dup
         2: getfield      #961                // Field H:J
         5: dup2_x1
         6: lconst_1
         7: ladd
         8: putfield      #961                // Field H:J
        11: lreturn
      LineNumberTable:
        line 1009: 0
      LocalVariableTable:
        Start  Length  Slot  Name   Signature
            0      12     0  this   Lcav;

  public cqq a(int, int);
    descriptor: (II)Lcqq;
    flags: (0x1001) ACC_PUBLIC, ACC_SYNTHETIC
    Code:
      stack=3, locals=3, args_size=3
         0: aload_0
         1: iload_1
         2: iload_2
         3: invokevirtual #220                // Method d:(II)Lcra;
         6: areturn
      LineNumberTable:
        line 71: 0
      LocalVariableTable:
        Start  Length  Slot  Name   Signature
            0       7     0  this   Lcav;

  private java.lang.String a() throws java.lang.Exception;
    descriptor: ()Ljava/lang/String;
    flags: (0x1002) ACC_PRIVATE, ACC_SYNTHETIC
    Code:
      stack=1, locals=1, args_size=1
         0: aload_0
         1: invokevirtual #966                // Method aa:()Lys;
         4: invokevirtual #971                // Method ys.a:()Lyt;
         7: invokevirtual #976                // Method yt.toString:()Ljava/lang/String;
        10: areturn
      LineNumberTable:
        line 859: 0
      LocalVariableTable:
        Start  Length  Slot  Name   Signature
            0      11     0  this   Lcav;
    Exceptions:
      throws java.lang.Exception

  private java.lang.String o() throws java.lang.Exception;
    descriptor: ()Ljava/lang/String;
    flags: (0x1002) ACC_PRIVATE, ACC_SYNTHETIC
    Code:
      stack=2, locals=1, args_size=1
         0: aload_0
         1: invokevirtual #979                // Method y:()Ljava/util/List;
         4: invokeinterface #982,  1          // InterfaceMethod java/util/List.size:()I
         9: aload_0
        10: invokevirtual #979                // Method y:()Ljava/util/List;
        13: invokedynamic #994,  0            // InvokeDynamic #6:makeConcatWithConstants:(ILjava/util/List;)Ljava/lang/String;
        18: areturn
      LineNumberTable:
        line 857: 0
      LocalVariableTable:
        Start  Length  Slot  Name   Signature
            0      19     0  this   Lcav;
    Exceptions:
      throws java.lang.Exception

  private static void a(java.util.function.Predicate, java.util.List, csn, axk);
    descriptor: (Ljava/util/function/Predicate;Ljava/util/List;Lcsn;Laxk;)V
    flags: (0x100a) ACC_PRIVATE, ACC_STATIC, ACC_SYNTHETIC
    Code:
      stack=2, locals=10, args_size=4
         0: aload_0
         1: aload_3
         2: invokeinterface #924,  2          // InterfaceMethod java/util/function/Predicate.test:(Ljava/lang/Object;)Z
         7: ifeq          18
        10: aload_1
        11: aload_3
        12: invokeinterface #538,  2          // InterfaceMethod java/util/List.add:(Ljava/lang/Object;)Z
        17: pop
        18: aload_3
        19: instanceof    #996                // class bkd
        22: ifeq          104
        25: aload_3
        26: checkcast     #996                // class bkd
        29: astore        4
        31: aload         4
        33: invokevirtual #999                // Method bkd.t:()[Lbkb;
        36: astore        5
        38: aload         5
        40: arraylength
        41: istore        6
        43: iconst_0
        44: istore        7
        46: iload         7
        48: iload         6
        50: if_icmpge     104
        53: aload         5
        55: iload         7
        57: aaload
        58: astore        8
        60: aload_2
        61: aload         8
        63: invokeinterface #1005,  2         // InterfaceMethod csn.a:(Ljava/lang/Object;)Ljava/lang/Object;
        68: checkcast     #363                // class axk
        71: astore        9
        73: aload         9
        75: ifnull        98
        78: aload_0
        79: aload         9
        81: invokeinterface #924,  2          // InterfaceMethod java/util/function/Predicate.test:(Ljava/lang/Object;)Z
        86: ifeq          98
        89: aload_1
        90: aload         9
        92: invokeinterface #538,  2          // InterfaceMethod java/util/List.add:(Ljava/lang/Object;)Z
        97: pop
        98: iinc          7, 1
       101: goto          46
       104: return
      StackMapTable: number_of_entries = 4
        frame_type = 18 /* same */
        frame_type = 255 /* full_frame */
          offset_delta = 27
          locals = [ class java/util/function/Predicate, class java/util/List, class csn, top, top, class "[Lbkb;", int, int ]
          stack = []
        frame_type = 51 /* same */
        frame_type = 255 /* full_frame */
          offset_delta = 5
          locals = []
          stack = []
      LineNumberTable:
        line 642: 0
        line 643: 10
        line 646: 18
        line 647: 31
        line 648: 60
        line 649: 73
        line 650: 89
        line 647: 98
        line 654: 104
      LocalVariableTable:
        Start  Length  Slot  Name   Signature
            0     105     0   $$0   Ljava/util/function/Predicate;
            0     105     1   $$1   Ljava/util/List;
            0     105     2   $$2   Lcsn;
            0     105     3   $$3   Laxk;
           31      73     4   $$4   Lbkd;
           60      38     8   $$5   Lbkb;
           73      25     9   $$6   Laxk;
      LocalVariableTypeTable:
        Start  Length  Slot  Name   Signature
           73      25     9   $$6   TT;

  private static void a(axk, java.util.function.Predicate, java.util.List, axk);
    descriptor: (Laxk;Ljava/util/function/Predicate;Ljava/util/List;Laxk;)V
    flags: (0x100a) ACC_PRIVATE, ACC_STATIC, ACC_SYNTHETIC
    Code:
      stack=2, locals=8, args_size=4
         0: aload_3
         1: aload_0
         2: if_acmpeq     23
         5: aload_1
         6: aload_3
         7: invokeinterface #924,  2          // InterfaceMethod java/util/function/Predicate.test:(Ljava/lang/Object;)Z
        12: ifeq          23
        15: aload_2
        16: aload_3
        17: invokeinterface #538,  2          // InterfaceMethod java/util/List.add:(Ljava/lang/Object;)Z
        22: pop
        23: aload_3
        24: instanceof    #996                // class bkd
        27: ifeq          92
        30: aload_3
        31: checkcast     #996                // class bkd
        34: invokevirtual #999                // Method bkd.t:()[Lbkb;
        37: astore        4
        39: aload         4
        41: arraylength
        42: istore        5
        44: iconst_0
        45: istore        6
        47: iload         6
        49: iload         5
        51: if_icmpge     92
        54: aload         4
        56: iload         6
        58: aaload
        59: astore        7
        61: aload_3
        62: aload_0
        63: if_acmpeq     86
        66: aload_1
        67: aload         7
        69: invokeinterface #924,  2          // InterfaceMethod java/util/function/Predicate.test:(Ljava/lang/Object;)Z
        74: ifeq          86
        77: aload_2
        78: aload         7
        80: invokeinterface #538,  2          // InterfaceMethod java/util/List.add:(Ljava/lang/Object;)Z
        85: pop
        86: iinc          6, 1
        89: goto          47
        92: return
      StackMapTable: number_of_entries = 4
        frame_type = 23 /* same */
        frame_type = 254 /* append */
          offset_delta = 23
          locals = [ class "[Lbkb;", int, int ]
        frame_type = 38 /* same */
        frame_type = 255 /* full_frame */
          offset_delta = 5
          locals = []
          stack = []
      LineNumberTable:
        line 621: 0
        line 622: 15
        line 625: 23
        line 626: 30
        line 627: 61
        line 628: 77
        line 626: 86
        line 632: 92
      LocalVariableTable:
        Start  Length  Slot  Name   Signature
            0      93     0   $$0   Laxk;
            0      93     1   $$1   Ljava/util/function/Predicate;
            0      93     2   $$2   Ljava/util/List;
            0      93     3   $$3   Laxk;
           61      25     7   $$4   Lbkb;

  private static java.lang.String a(cdq) throws java.lang.Exception;
    descriptor: (Lcdq;)Ljava/lang/String;
    flags: (0x100a) ACC_PRIVATE, ACC_STATIC, ACC_SYNTHETIC
    Code:
      stack=6, locals=2, args_size=1
         0: ldc_w         #1009               // String ID #%s (%s // %s)
         3: iconst_3
         4: anewarray     #4                  // class java/lang/Object
         7: dup
         8: iconst_0
         9: getstatic     #1014               // Field hb.U:Lgn;
        12: aload_0
        13: invokevirtual #1019               // Method gn.b:(Ljava/lang/Object;)Lyt;
        16: aastore
        17: dup
        18: iconst_1
        19: aload_0
        20: invokevirtual #1021               // Method cdq.h:()Ljava/lang/String;
        23: aastore
        24: dup
        25: iconst_2
        26: aload_0
        27: invokevirtual #1025               // Method java/lang/Object.getClass:()Ljava/lang/Class;
        30: invokevirtual #1030               // Method java/lang/Class.getCanonicalName:()Ljava/lang/String;
        33: aastore
        34: invokestatic  #1036               // Method java/lang/String.format:(Ljava/lang/String;[Ljava/lang/Object;)Ljava/lang/String;
        37: areturn
        38: astore_1
        39: getstatic     #1014               // Field hb.U:Lgn;
        42: aload_0
        43: invokevirtual #1019               // Method gn.b:(Ljava/lang/Object;)Lyt;
        46: invokedynamic #1041,  0           // InvokeDynamic #7:makeConcatWithConstants:(Lyt;)Ljava/lang/String;
        51: areturn
      Exception table:
         from    to  target type
             0    37    38   Class java/lang/Throwable
      StackMapTable: number_of_entries = 1
        frame_type = 102 /* same_locals_1_stack_item */
          stack = [ class java/lang/Throwable ]
      LineNumberTable:
        line 363: 0
        line 364: 38
        line 365: 39
      LocalVariableTable:
        Start  Length  Slot  Name   Signature
            0      52     0   $$0   Lcdq;
           39      13     1   $$1   Ljava/lang/Throwable;
    Exceptions:
      throws java.lang.Exception

  static {};
    descriptor: ()V
    flags: (0x0008) ACC_STATIC
    Code:
      stack=4, locals=0, args_size=0
         0: getstatic     #1044               // Field yt.a:Lcom/mojang/serialization/Codec;
         3: getstatic     #1046               // Field hb.O:Lys;
         6: invokestatic  #1049               // Method ys.d:(Lys;)Ljava/util/function/Function;
         9: invokedynamic #1057,  0           // InvokeDynamic #8:apply:()Ljava/util/function/Function;
        14: invokeinterface #1063,  3         // InterfaceMethod com/mojang/serialization/Codec.xmap:(Ljava/util/function/Function;Ljava/util/function/Function;)Lcom/mojang/serialization/Codec;
        19: putstatic     #1065               // Field d:Lcom/mojang/serialization/Codec;
        22: getstatic     #1046               // Field hb.O:Lys;
        25: new           #973                // class yt
        28: dup
        29: ldc_w         #1067               // String overworld
        32: invokespecial #1068               // Method yt."<init>":(Ljava/lang/String;)V
        35: invokestatic  #1071               // Method ys.a:(Lys;Lyt;)Lys;
        38: putstatic     #1073               // Field e:Lys;
        41: getstatic     #1046               // Field hb.O:Lys;
        44: new           #973                // class yt
        47: dup
        48: ldc_w         #1075               // String the_nether
        51: invokespecial #1068               // Method yt."<init>":(Ljava/lang/String;)V
        54: invokestatic  #1071               // Method ys.a:(Lys;Lyt;)Lys;
        57: putstatic     #1077               // Field f:Lys;
        60: getstatic     #1046               // Field hb.O:Lys;
        63: new           #973                // class yt
        66: dup
        67: ldc_w         #1079               // String the_end
        70: invokespecial #1068               // Method yt."<init>":(Ljava/lang/String;)V
        73: invokestatic  #1071               // Method ys.a:(Lys;Lyt;)Lys;
        76: putstatic     #1081               // Field g:Lys;
        79: invokestatic  #1085               // Method go.values:()[Lgo;
        82: putstatic     #755                // Field a:[Lgo;
        85: return
      LineNumberTable:
        line 72: 0
        line 74: 22
        line 75: 41
        line 76: 60
        line 82: 79
}
InnerClasses:
  #11;                                    // class cav$1
  public static #16= #13 of #15;          // a=class cbt$a of class cbt
  public static final #21= #18 of #20;    // c=class adi$c of class adi
  public static final #16= #23 of #25;    // a=class ctw$a of class ctw
  public static final #16= #27 of #29;    // a=class can$a of class can
  public static final #34= #31 of #33;    // b=class cra$b of class cra
  public static final #39= #36 of #38;    // d=class cbr$d of class cbr
  public static final #21= #41 of #43;    // c=class go$c of class go
  public static final #48= #45 of #47;    // Lookup=class java/lang/invoke/MethodHandles$Lookup of class java/lang/invoke/MethodHandles
SourceFile: "SourceFile"
BootstrapMethods:
  0: #447 REF_invokeStatic java/lang/invoke/LambdaMetafactory.metafactory:(Ljava/lang/invoke/MethodHandles$Lookup;Ljava/lang/String;Ljava/lang/invoke/MethodType;Ljava/lang/invoke/MethodType;Ljava/lang/invoke/MethodHandle;Ljava/lang/invoke/MethodType;)Ljava/lang/invoke/CallSite;
    Method arguments:
      #434 ()Ljava/lang/Object;
      #438 REF_invokeStatic cav.a:(Lcdq;)Ljava/lang/String;
      #440 ()Ljava/lang/String;
  1: #447 REF_invokeStatic java/lang/invoke/LambdaMetafactory.metafactory:(Ljava/lang/invoke/MethodHandles$Lookup;Ljava/lang/String;Ljava/lang/invoke/MethodType;Ljava/lang/invoke/MethodType;Ljava/lang/invoke/MethodHandle;Ljava/lang/invoke/MethodType;)Ljava/lang/invoke/CallSite;
    Method arguments:
      #694 (Ljava/lang/Object;)V
      #698 REF_invokeStatic cav.a:(Laxk;Ljava/util/function/Predicate;Ljava/util/List;Laxk;)V
      #700 (Laxk;)V
  2: #447 REF_invokeStatic java/lang/invoke/LambdaMetafactory.metafactory:(Ljava/lang/invoke/MethodHandles$Lookup;Ljava/lang/String;Ljava/lang/invoke/MethodType;Ljava/lang/invoke/MethodType;Ljava/lang/invoke/MethodHandle;Ljava/lang/invoke/MethodType;)Ljava/lang/invoke/CallSite;
    Method arguments:
      #694 (Ljava/lang/Object;)V
      #718 REF_invokeStatic cav.a:(Ljava/util/function/Predicate;Ljava/util/List;Lcsn;Laxk;)V
      #700 (Laxk;)V
  3: #447 REF_invokeStatic java/lang/invoke/LambdaMetafactory.metafactory:(Ljava/lang/invoke/MethodHandles$Lookup;Ljava/lang/String;Ljava/lang/invoke/MethodType;Ljava/lang/invoke/MethodType;Ljava/lang/invoke/MethodHandle;Ljava/lang/invoke/MethodType;)Ljava/lang/invoke/CallSite;
    Method arguments:
      #434 ()Ljava/lang/Object;
      #834 REF_invokeVirtual cav.o:()Ljava/lang/String;
      #440 ()Ljava/lang/String;
  4: #447 REF_invokeStatic java/lang/invoke/LambdaMetafactory.metafactory:(Ljava/lang/invoke/MethodHandles$Lookup;Ljava/lang/String;Ljava/lang/invoke/MethodType;Ljava/lang/invoke/MethodType;Ljava/lang/invoke/MethodHandle;Ljava/lang/invoke/MethodType;)Ljava/lang/invoke/CallSite;
    Method arguments:
      #434 ()Ljava/lang/Object;
      #848 REF_invokeVirtual cqs.e:()Ljava/lang/String;
      #440 ()Ljava/lang/String;
  5: #447 REF_invokeStatic java/lang/invoke/LambdaMetafactory.metafactory:(Ljava/lang/invoke/MethodHandles$Lookup;Ljava/lang/String;Ljava/lang/invoke/MethodType;Ljava/lang/invoke/MethodType;Ljava/lang/invoke/MethodHandle;Ljava/lang/invoke/MethodType;)Ljava/lang/invoke/CallSite;
    Method arguments:
      #434 ()Ljava/lang/Object;
      #856 REF_invokeVirtual cav.a:()Ljava/lang/String;
      #440 ()Ljava/lang/String;
  6: #991 REF_invokeStatic java/lang/invoke/StringConcatFactory.makeConcatWithConstants:(Ljava/lang/invoke/MethodHandles$Lookup;Ljava/lang/String;Ljava/lang/invoke/MethodType;Ljava/lang/String;[Ljava/lang/Object;)Ljava/lang/invoke/CallSite;
    Method arguments:
      #984 \u0001 total; \u0001
  7: #991 REF_invokeStatic java/lang/invoke/StringConcatFactory.makeConcatWithConstants:(Ljava/lang/invoke/MethodHandles$Lookup;Ljava/lang/String;Ljava/lang/invoke/MethodType;Ljava/lang/String;[Ljava/lang/Object;)Ljava/lang/invoke/CallSite;
    Method arguments:
      #1038 ID #\u0001
  8: #447 REF_invokeStatic java/lang/invoke/LambdaMetafactory.metafactory:(Ljava/lang/invoke/MethodHandles$Lookup;Ljava/lang/String;Ljava/lang/invoke/MethodType;Ljava/lang/invoke/MethodType;Ljava/lang/invoke/MethodHandle;Ljava/lang/invoke/MethodType;)Ljava/lang/invoke/CallSite;
    Method arguments:
      #1050 (Ljava/lang/Object;)Ljava/lang/Object;
      #1051 REF_invokeVirtual ys.a:()Lyt;
      #1053 (Lys;)Lyt;
NestMembers:
  cav$1
