Classfile /F:/My_Minecraft_Expansion_3/_forge_mod_dev/test_mod/_temp_decomp/cou$a.class
  Last modified Feb 28, 2022; size 14479 bytes
  SHA-256 checksum 191103feac0212f6669be88626f0a4c6202cc4c821a7436e5841f612761ebec6
  Compiled from "SourceFile"
public abstract class cou$a extends cox<cdq, cov>
  minor version: 0
  major version: 61
  flags: (0x0421) ACC_PUBLIC, ACC_SUPER, ACC_ABSTRACT
  this_class: #2                          // cou$a
  super_class: #5                         // cox
  interfaces: 0, fields: 14, methods: 82, attributes: 4
Constant pool:
    #1 = Utf8               cou$a
    #2 = Class              #1            // cou$a
    #3 = Utf8               Lcox<Lcdq;Lcov;>;
    #4 = Utf8               cox
    #5 = Class              #4            // cox
    #6 = Utf8               SourceFile
    #7 = Utf8               cou
    #8 = Class              #7            // cou
    #9 = Utf8               cou$c
   #10 = Class              #9            // cou$c
   #11 = Utf8               c
   #12 = Utf8               a
   #13 = Utf8               cou$e
   #14 = Class              #13           // cou$e
   #15 = Utf8               e
   #16 = Utf8               cou$a$a
   #17 = Class              #16           // cou$a$a
   #18 = Utf8               cou$d
   #19 = Class              #18           // cou$d
   #20 = Utf8               d
   #21 = Utf8               cou$b
   #22 = Class              #21           // cou$b
   #23 = Utf8               b
   #24 = Utf8               gj$a
   #25 = Class              #24           // gj$a
   #26 = Utf8               gj
   #27 = Class              #26           // gj
   #28 = Utf8               dlc$a
   #29 = Class              #28           // dlc$a
   #30 = Utf8               dlc
   #31 = Class              #30           // dlc
   #32 = Utf8               gs$c
   #33 = Class              #32           // gs$c
   #34 = Utf8               gs
   #35 = Class              #34           // gs
   #36 = Utf8               I
   #37 = Utf8               g
   #38 = Utf8               Z
   #39 = Utf8               h
   #40 = Utf8               i
   #41 = Utf8               Ldjb;
   #42 = Utf8               j
   #43 = Utf8               Ldjc;
   #44 = Utf8               k
   #45 = Utf8               F
   #46 = Utf8               l
   #47 = Utf8               m
   #48 = Utf8               n
   #49 = Utf8               Lcou$e;
   #50 = Utf8               o
   #51 = Utf8               p
   #52 = Utf8               q
   #53 = Utf8               r
   #54 = Utf8               Lcou$a$a;
   #55 = Utf8               Ljavax/annotation/Nullable;
   #56 = Utf8               <init>
   #57 = Utf8               (Lcdq;Lcom/google/common/collect/ImmutableMap;Lcom/mojang/serialization/MapCodec;)V
   #58 = Utf8               (Lcdq;Lcom/google/common/collect/ImmutableMap<Lcpy<*>;Ljava/lang/Comparable<*>;>;Lcom/mojang/serialization/MapCodec<Lcov;>;)V
   #59 = Utf8               (Ljava/lang/Object;Lcom/google/common/collect/ImmutableMap;Lcom/mojang/serialization/MapCodec;)V
   #60 = NameAndType        #56:#59       // "<init>":(Ljava/lang/Object;Lcom/google/common/collect/ImmutableMap;Lcom/mojang/serialization/MapCodec;)V
   #61 = Methodref          #5.#60        // cox."<init>":(Ljava/lang/Object;Lcom/google/common/collect/ImmutableMap;Lcom/mojang/serialization/MapCodec;)V
   #62 = Utf8               cdq
   #63 = Class              #62           // cdq
   #64 = Utf8               aO
   #65 = Utf8               Lcou$c;
   #66 = NameAndType        #64:#65       // aO:Lcou$c;
   #67 = Fieldref           #63.#66       // cdq.aO:Lcou$c;
   #68 = Utf8               Ljava/util/function/ToIntFunction;
   #69 = NameAndType        #15:#68       // e:Ljava/util/function/ToIntFunction;
   #70 = Fieldref           #10.#69       // cou$c.e:Ljava/util/function/ToIntFunction;
   #71 = Utf8               ()Lcov;
   #72 = NameAndType        #53:#71       // r:()Lcov;
   #73 = Methodref          #2.#72        // cou$a.r:()Lcov;
   #74 = Utf8               java/util/function/ToIntFunction
   #75 = Class              #74           // java/util/function/ToIntFunction
   #76 = Utf8               applyAsInt
   #77 = Utf8               (Ljava/lang/Object;)I
   #78 = NameAndType        #76:#77       // applyAsInt:(Ljava/lang/Object;)I
   #79 = InterfaceMethodref #75.#78       // java/util/function/ToIntFunction.applyAsInt:(Ljava/lang/Object;)I
   #80 = NameAndType        #23:#36       // b:I
   #81 = Fieldref           #2.#80        // cou$a.b:I
   #82 = Utf8               g_
   #83 = Utf8               (Lcov;)Z
   #84 = NameAndType        #82:#83       // g_:(Lcov;)Z
   #85 = Methodref          #63.#84       // cdq.g_:(Lcov;)Z
   #86 = NameAndType        #37:#38       // g:Z
   #87 = Fieldref           #2.#86        // cou$a.g:Z
   #88 = NameAndType        #50:#38       // o:Z
   #89 = Fieldref           #10.#88       // cou$c.o:Z
   #90 = NameAndType        #39:#38       // h:Z
   #91 = Fieldref           #2.#90        // cou$a.h:Z
   #92 = NameAndType        #12:#41       // a:Ldjb;
   #93 = Fieldref           #10.#92       // cou$c.a:Ldjb;
   #94 = NameAndType        #40:#41       // i:Ldjb;
   #95 = Fieldref           #2.#94        // cou$a.i:Ldjb;
   #96 = Utf8               Ljava/util/function/Function;
   #97 = NameAndType        #23:#96       // b:Ljava/util/function/Function;
   #98 = Fieldref           #10.#97       // cou$c.b:Ljava/util/function/Function;
   #99 = Utf8               java/util/function/Function
  #100 = Class              #99           // java/util/function/Function
  #101 = Utf8               apply
  #102 = Utf8               (Ljava/lang/Object;)Ljava/lang/Object;
  #103 = NameAndType        #101:#102     // apply:(Ljava/lang/Object;)Ljava/lang/Object;
  #104 = InterfaceMethodref #100.#103     // java/util/function/Function.apply:(Ljava/lang/Object;)Ljava/lang/Object;
  #105 = Utf8               djc
  #106 = Class              #105          // djc
  #107 = NameAndType        #42:#43       // j:Ldjc;
  #108 = Fieldref           #2.#107       // cou$a.j:Ldjc;
  #109 = NameAndType        #37:#45       // g:F
  #110 = Fieldref           #10.#109      // cou$c.g:F
  #111 = NameAndType        #44:#45       // k:F
  #112 = Fieldref           #2.#111       // cou$a.k:F
  #113 = Fieldref           #10.#90       // cou$c.h:Z
  #114 = NameAndType        #46:#38       // l:Z
  #115 = Fieldref           #2.#114       // cou$a.l:Z
  #116 = NameAndType        #48:#38       // n:Z
  #117 = Fieldref           #10.#116      // cou$c.n:Z
  #118 = NameAndType        #47:#38       // m:Z
  #119 = Fieldref           #2.#118       // cou$a.m:Z
  #120 = NameAndType        #52:#49       // q:Lcou$e;
  #121 = Fieldref           #10.#120      // cou$c.q:Lcou$e;
  #122 = NameAndType        #48:#49       // n:Lcou$e;
  #123 = Fieldref           #2.#122       // cou$a.n:Lcou$e;
  #124 = NameAndType        #53:#49       // r:Lcou$e;
  #125 = Fieldref           #10.#124      // cou$c.r:Lcou$e;
  #126 = NameAndType        #50:#49       // o:Lcou$e;
  #127 = Fieldref           #2.#126       // cou$a.o:Lcou$e;
  #128 = Utf8               s
  #129 = NameAndType        #128:#49      // s:Lcou$e;
  #130 = Fieldref           #10.#129      // cou$c.s:Lcou$e;
  #131 = NameAndType        #51:#49       // p:Lcou$e;
  #132 = Fieldref           #2.#131       // cou$a.p:Lcou$e;
  #133 = Utf8               t
  #134 = NameAndType        #133:#49      // t:Lcou$e;
  #135 = Fieldref           #10.#134      // cou$c.t:Lcou$e;
  #136 = Fieldref           #2.#120       // cou$a.q:Lcou$e;
  #137 = Utf8               u
  #138 = NameAndType        #137:#49      // u:Lcou$e;
  #139 = Fieldref           #10.#138      // cou$c.u:Lcou$e;
  #140 = Fieldref           #2.#124       // cou$a.r:Lcou$e;
  #141 = Utf8               this
  #142 = Utf8               Lcou$a;
  #143 = Utf8               $$0
  #144 = Utf8               Lcdq;
  #145 = Utf8               $$1
  #146 = Utf8               Lcom/google/common/collect/ImmutableMap<Lcpy<*>;Ljava/lang/Comparable<*>;>;
  #147 = Utf8               Lcom/google/common/collect/ImmutableMap;
  #148 = Utf8               $$2
  #149 = Utf8               Lcom/mojang/serialization/MapCodec<Lcov;>;
  #150 = Utf8               Lcom/mojang/serialization/MapCodec;
  #151 = Utf8               $$3
  #152 = Utf8               ()V
  #153 = Utf8               ()Lcdq;
  #154 = NameAndType        #23:#153      // b:()Lcdq;
  #155 = Methodref          #2.#154       // cou$a.b:()Lcdq;
  #156 = Utf8               ()Z
  #157 = NameAndType        #50:#156      // o:()Z
  #158 = Methodref          #63.#157      // cdq.o:()Z
  #159 = Utf8               (Lcov;)V
  #160 = NameAndType        #56:#159      // "<init>":(Lcov;)V
  #161 = Methodref          #17.#160      // cou$a$a."<init>":(Lcov;)V
  #162 = NameAndType        #12:#54       // a:Lcou$a$a;
  #163 = Fieldref           #2.#162       // cou$a.a:Lcou$a$a;
  #164 = Utf8               Ljava/lang/Object;
  #165 = NameAndType        #15:#164      // e:Ljava/lang/Object;
  #166 = Fieldref           #2.#165       // cou$a.e:Ljava/lang/Object;
  #167 = Utf8               ()Ldjb;
  #168 = Utf8               (Lcab;Lgj;Laxo;)Z
  #169 = Utf8               (Lcab;Lgj;Laxo<*>;)Z
  #170 = Utf8               Lcou$d;
  #171 = NameAndType        #51:#170      // p:Lcou$d;
  #172 = Fieldref           #10.#171      // cou$c.p:Lcou$d;
  #173 = Utf8               test
  #174 = Utf8               (Lcov;Lcab;Lgj;Ljava/lang/Object;)Z
  #175 = NameAndType        #173:#174     // test:(Lcov;Lcab;Lgj;Ljava/lang/Object;)Z
  #176 = InterfaceMethodref #19.#175      // cou$d.test:(Lcov;Lcab;Lgj;Ljava/lang/Object;)Z
  #177 = Utf8               Lcab;
  #178 = Utf8               Lgj;
  #179 = Utf8               Laxo<*>;
  #180 = Utf8               Laxo;
  #181 = Utf8               (Lcab;Lgj;)Z
  #182 = Fieldref           #17.#86       // cou$a$a.g:Z
  #183 = Utf8               (Lcov;Lcab;Lgj;)Z
  #184 = NameAndType        #11:#183      // c:(Lcov;Lcab;Lgj;)Z
  #185 = Methodref          #63.#184      // cdq.c:(Lcov;Lcab;Lgj;)Z
  #186 = Utf8               (Lcab;Lgj;)I
  #187 = NameAndType        #39:#36       // h:I
  #188 = Fieldref           #17.#187      // cou$a$a.h:I
  #189 = Utf8               (Lcov;Lcab;Lgj;)I
  #190 = NameAndType        #37:#189      // g:(Lcov;Lcab;Lgj;)I
  #191 = Methodref          #63.#190      // cdq.g:(Lcov;Lcab;Lgj;)I
  #192 = Utf8               (Lcab;Lgj;Lgo;)Ldqh;
  #193 = Utf8               [Ldqh;
  #194 = NameAndType        #40:#193      // i:[Ldqh;
  #195 = Fieldref           #17.#194      // cou$a$a.i:[Ldqh;
  #196 = Utf8               go
  #197 = Class              #196          // go
  #198 = Utf8               ordinal
  #199 = Utf8               ()I
  #200 = NameAndType        #198:#199     // ordinal:()I
  #201 = Methodref          #197.#200     // go.ordinal:()I
  #202 = Utf8               (Lcab;Lgj;)Ldqh;
  #203 = NameAndType        #11:#202      // c:(Lcab;Lgj;)Ldqh;
  #204 = Methodref          #2.#203       // cou$a.c:(Lcab;Lgj;)Ldqh;
  #205 = Utf8               dqe
  #206 = Class              #205          // dqe
  #207 = Utf8               (Ldqh;Lgo;)Ldqh;
  #208 = NameAndType        #12:#207      // a:(Ldqh;Lgo;)Ldqh;
  #209 = Methodref          #206.#208     // dqe.a:(Ldqh;Lgo;)Ldqh;
  #210 = Utf8               Lgo;
  #211 = Utf8               b_
  #212 = Utf8               (Lcov;Lcab;Lgj;)Ldqh;
  #213 = NameAndType        #211:#212     // b_:(Lcov;Lcab;Lgj;)Ldqh;
  #214 = Methodref          #63.#213      // cdq.b_:(Lcov;Lcab;Lgj;)Ldqh;
  #215 = NameAndType        #11:#38       // c:Z
  #216 = Fieldref           #17.#215      // cou$a$a.c:Z
  #217 = Utf8               f
  #218 = Utf8               (Lcab;Lgj;)Ldjc;
  #219 = Utf8               (Lcjm;)Lcov;
  #220 = Utf8               (Lcov;Lcjm;)Lcov;
  #221 = NameAndType        #12:#220      // a:(Lcov;Lcjm;)Lcov;
  #222 = Methodref          #63.#221      // cdq.a:(Lcov;Lcjm;)Lcov;
  #223 = Utf8               Lcjm;
  #224 = Utf8               (Lchz;)Lcov;
  #225 = Utf8               (Lcov;Lchz;)Lcov;
  #226 = NameAndType        #12:#225      // a:(Lcov;Lchz;)Lcov;
  #227 = Methodref          #63.#226      // cdq.a:(Lcov;Lchz;)Lcov;
  #228 = Utf8               Lchz;
  #229 = Utf8               ()Lcjf;
  #230 = Utf8               (Lcov;)Lcjf;
  #231 = NameAndType        #211:#230     // b_:(Lcov;)Lcjf;
  #232 = Methodref          #63.#231      // cdq.b_:(Lcov;)Lcjf;
  #233 = NameAndType        #173:#183     // test:(Lcov;Lcab;Lgj;)Z
  #234 = InterfaceMethodref #14.#233      // cou$e.test:(Lcov;Lcab;Lgj;)Z
  #235 = Utf8               (Lcab;Lgj;)F
  #236 = Utf8               (Lcov;Lcab;Lgj;)F
  #237 = NameAndType        #23:#236      // b:(Lcov;Lcab;Lgj;)F
  #238 = Methodref          #63.#237      // cdq.b:(Lcov;Lcab;Lgj;)F
  #239 = Utf8               f_
  #240 = NameAndType        #239:#83      // f_:(Lcov;)Z
  #241 = Methodref          #63.#240      // cdq.f_:(Lcov;)Z
  #242 = Utf8               (Lcab;Lgj;Lgo;)I
  #243 = Utf8               (Lcov;Lcab;Lgj;Lgo;)I
  #244 = NameAndType        #12:#243      // a:(Lcov;Lcab;Lgj;Lgo;)I
  #245 = Methodref          #63.#244      // cdq.a:(Lcov;Lcab;Lgj;Lgo;)I
  #246 = Utf8               d_
  #247 = NameAndType        #246:#83      // d_:(Lcov;)Z
  #248 = Methodref          #63.#247      // cdq.d_:(Lcov;)Z
  #249 = Utf8               (Lcav;Lgj;)I
  #250 = Utf8               (Lcov;Lcav;Lgj;)I
  #251 = NameAndType        #12:#250      // a:(Lcov;Lcav;Lgj;)I
  #252 = Methodref          #63.#251      // cdq.a:(Lcov;Lcav;Lgj;)I
  #253 = Utf8               Lcav;
  #254 = Utf8               (Lboj;Lcab;Lgj;)F
  #255 = Utf8               (Lcov;Lboj;Lcab;Lgj;)F
  #256 = NameAndType        #12:#255      // a:(Lcov;Lboj;Lcab;Lgj;)F
  #257 = Methodref          #63.#256      // cdq.a:(Lcov;Lboj;Lcab;Lgj;)F
  #258 = Utf8               Lboj;
  #259 = NameAndType        #23:#243      // b:(Lcov;Lcab;Lgj;Lgo;)I
  #260 = Methodref          #63.#259      // cdq.b:(Lcov;Lcab;Lgj;Lgo;)I
  #261 = Utf8               ()Ldjd;
  #262 = Utf8               (Lcov;)Ldjd;
  #263 = NameAndType        #20:#262      // d:(Lcov;)Ldjd;
  #264 = Methodref          #63.#263      // cdq.d:(Lcov;)Ldjd;
  #265 = NameAndType        #12:#38       // a:Z
  #266 = Fieldref           #17.#265      // cou$a$a.a:Z
  #267 = Utf8               cov
  #268 = Class              #267          // cov
  #269 = NameAndType        #46:#156      // l:()Z
  #270 = Methodref          #268.#269     // cov.l:()Z
  #271 = Methodref          #268.#203     // cov.c:(Lcab;Lgj;)Ldqh;
  #272 = Utf8               (Ldqh;)Z
  #273 = NameAndType        #12:#272      // a:(Ldqh;)Z
  #274 = Methodref          #63.#273      // cdq.a:(Ldqh;)Z
  #275 = Utf8               Lcov;
  #276 = Utf8               (Lcov;Lgo;)Z
  #277 = Utf8               (Lcov;Lcov;Lgo;)Z
  #278 = NameAndType        #12:#277      // a:(Lcov;Lcov;Lgo;)Z
  #279 = Methodref          #63.#278      // cdq.a:(Lcov;Lcov;Lgo;)Z
  #280 = Utf8               dpt
  #281 = Class              #280          // dpt
  #282 = Utf8               ()Ldpt;
  #283 = NameAndType        #12:#282      // a:()Ldpt;
  #284 = InterfaceMethodref #281.#283     // dpt.a:()Ldpt;
  #285 = Utf8               (Lcab;Lgj;Ldpt;)Ldqh;
  #286 = NameAndType        #12:#285      // a:(Lcab;Lgj;Ldpt;)Ldqh;
  #287 = Methodref          #2.#286       // cou$a.a:(Lcab;Lgj;Ldpt;)Ldqh;
  #288 = Utf8               (Lcov;Lcab;Lgj;Ldpt;)Ldqh;
  #289 = NameAndType        #12:#288      // a:(Lcov;Lcab;Lgj;Ldpt;)Ldqh;
  #290 = Methodref          #63.#289      // cdq.a:(Lcov;Lcab;Lgj;Ldpt;)Ldqh;
  #291 = Utf8               Ldpt;
  #292 = Utf8               Ldqh;
  #293 = NameAndType        #23:#292      // b:Ldqh;
  #294 = Fieldref           #17.#293      // cou$a$a.b:Ldqh;
  #295 = NameAndType        #23:#285      // b:(Lcab;Lgj;Ldpt;)Ldqh;
  #296 = Methodref          #2.#295       // cou$a.b:(Lcab;Lgj;Ldpt;)Ldqh;
  #297 = NameAndType        #11:#288      // c:(Lcov;Lcab;Lgj;Ldpt;)Ldqh;
  #298 = Methodref          #63.#297      // cdq.c:(Lcov;Lcab;Lgj;Ldpt;)Ldqh;
  #299 = NameAndType        #217:#212     // f:(Lcov;Lcab;Lgj;)Ldqh;
  #300 = Methodref          #63.#299      // cdq.f:(Lcov;Lcab;Lgj;)Ldqh;
  #301 = NameAndType        #23:#288      // b:(Lcov;Lcab;Lgj;Ldpt;)Ldqh;
  #302 = Methodref          #63.#301      // cdq.b:(Lcov;Lcab;Lgj;Ldpt;)Ldqh;
  #303 = NameAndType        #12:#212      // a:(Lcov;Lcab;Lgj;)Ldqh;
  #304 = Methodref          #63.#303      // cdq.a:(Lcov;Lcab;Lgj;)Ldqh;
  #305 = Utf8               (Lcab;Lgj;Laxk;)Z
  #306 = NameAndType        #23:#210      // b:Lgo;
  #307 = Fieldref           #197.#306     // go.b:Lgo;
  #308 = Utf8               (Lcab;Lgj;Laxk;Lgo;)Z
  #309 = NameAndType        #12:#308      // a:(Lcab;Lgj;Laxk;Lgo;)Z
  #310 = Methodref          #2.#309       // cou$a.a:(Lcab;Lgj;Laxk;Lgo;)Z
  #311 = Utf8               Laxk;
  #312 = Utf8               (Laxk;)Ldpt;
  #313 = NameAndType        #12:#312      // a:(Laxk;)Ldpt;
  #314 = InterfaceMethodref #281.#313     // dpt.a:(Laxk;)Ldpt;
  #315 = Utf8               (Ldqh;Lgo;)Z
  #316 = NameAndType        #12:#315      // a:(Ldqh;Lgo;)Z
  #317 = Methodref          #63.#316      // cdq.a:(Ldqh;Lgo;)Z
  #318 = Utf8               (Lcab;Lgj;)Ldpo;
  #319 = Utf8               U_
  #320 = Utf8               ()Lcou$b;
  #321 = NameAndType        #319:#320     // U_:()Lcou$b;
  #322 = Methodref          #63.#321      // cdq.U_:()Lcou$b;
  #323 = Utf8               Lcou$b;
  #324 = NameAndType        #12:#323      // a:Lcou$b;
  #325 = Fieldref           #22.#324      // cou$b.a:Lcou$b;
  #326 = Utf8               dpo
  #327 = Class              #326          // dpo
  #328 = Utf8               Ldpo;
  #329 = NameAndType        #12:#328      // a:Ldpo;
  #330 = Fieldref           #327.#329     // dpo.a:Ldpo;
  #331 = NameAndType        #137:#199     // u:()I
  #332 = Methodref          #27.#331      // gj.u:()I
  #333 = Utf8               w
  #334 = NameAndType        #333:#199     // w:()I
  #335 = Methodref          #27.#334      // gj.w:()I
  #336 = Utf8               ajl
  #337 = Class              #336          // ajl
  #338 = Utf8               (III)J
  #339 = NameAndType        #11:#338      // c:(III)J
  #340 = Methodref          #337.#339     // ajl.c:(III)J
  #341 = Utf8               W_
  #342 = Utf8               ()F
  #343 = NameAndType        #341:#342     // W_:()F
  #344 = Methodref          #63.#343      // cdq.W_:()F
  #345 = Long               15l
  #347 = Float              15.0f
  #348 = Double             0.5d
  #350 = Utf8               (DDD)D
  #351 = NameAndType        #12:#350      // a:(DDD)D
  #352 = Methodref          #337.#351     // ajl.a:(DDD)D
  #353 = NameAndType        #11:#323      // c:Lcou$b;
  #354 = Fieldref           #22.#353      // cou$b.c:Lcou$b;
  #355 = Utf8               Z_
  #356 = NameAndType        #355:#342     // Z_:()F
  #357 = Methodref          #63.#356      // cdq.Z_:()F
  #358 = Utf8               (DDD)V
  #359 = NameAndType        #56:#358      // "<init>":(DDD)V
  #360 = Methodref          #327.#359     // dpo."<init>":(DDD)V
  #361 = Utf8               $$4
  #362 = Utf8               J
  #363 = Utf8               $$5
  #364 = Utf8               $$6
  #365 = Utf8               D
  #366 = Utf8               $$7
  #367 = Utf8               $$8
  #368 = Utf8               (Lcav;Lgj;II)Z
  #369 = Utf8               (Lcov;Lcav;Lgj;II)Z
  #370 = NameAndType        #12:#369      // a:(Lcov;Lcav;Lgj;II)Z
  #371 = Methodref          #63.#370      // cdq.a:(Lcov;Lcav;Lgj;II)Z
  #372 = Utf8               (Lcav;Lgj;Lcdq;Lgj;Z)V
  #373 = Utf8               (Lcov;Lcav;Lgj;Lcdq;Lgj;Z)V
  #374 = NameAndType        #12:#373      // a:(Lcov;Lcav;Lgj;Lcdq;Lgj;Z)V
  #375 = Methodref          #63.#374      // cdq.a:(Lcov;Lcav;Lgj;Lcdq;Lgj;Z)V
  #376 = Utf8               (Lcaw;Lgj;I)V
  #377 = Utf8               (Lcaw;Lgj;II)V
  #378 = NameAndType        #12:#377      // a:(Lcaw;Lgj;II)V
  #379 = Methodref          #2.#378       // cou$a.a:(Lcaw;Lgj;II)V
  #380 = Utf8               Lcaw;
  #381 = NameAndType        #56:#152      // "<init>":()V
  #382 = Methodref          #25.#381      // gj$a."<init>":()V
  #383 = Utf8               aE
  #384 = Utf8               [Lgo;
  #385 = NameAndType        #383:#384     // aE:[Lgo;
  #386 = Fieldref           #8.#385       // cou.aE:[Lgo;
  #387 = Utf8               caw
  #388 = Class              #387          // caw
  #389 = Class              #384          // "[Lgo;"
  #390 = Utf8               (Lhh;Lgo;)Lgj$a;
  #391 = NameAndType        #12:#390      // a:(Lhh;Lgo;)Lgj$a;
  #392 = Methodref          #25.#391      // gj$a.a:(Lhh;Lgo;)Lgj$a;
  #393 = Utf8               a_
  #394 = Utf8               (Lgj;)Lcov;
  #395 = NameAndType        #393:#394     // a_:(Lgj;)Lcov;
  #396 = InterfaceMethodref #388.#395     // caw.a_:(Lgj;)Lcov;
  #397 = Utf8               ()Lgo;
  #398 = NameAndType        #217:#397     // f:()Lgo;
  #399 = Methodref          #197.#398     // go.f:()Lgo;
  #400 = Utf8               (Lgo;Lcov;Lcaw;Lgj;Lgj;)Lcov;
  #401 = NameAndType        #12:#400      // a:(Lgo;Lcov;Lcaw;Lgj;Lgj;)Lcov;
  #402 = Methodref          #268.#401     // cov.a:(Lgo;Lcov;Lcaw;Lgj;Lgj;)Lcov;
  #403 = Utf8               (Lcov;Lcov;Lcaw;Lgj;II)V
  #404 = NameAndType        #12:#403      // a:(Lcov;Lcov;Lcaw;Lgj;II)V
  #405 = Methodref          #63.#404      // cdq.a:(Lcov;Lcov;Lcaw;Lgj;II)V
  #406 = Utf8               Lgj$a;
  #407 = NameAndType        #23:#377      // b:(Lcaw;Lgj;II)V
  #408 = Methodref          #2.#407       // cou$a.b:(Lcaw;Lgj;II)V
  #409 = Utf8               (Lcov;Lcaw;Lgj;II)V
  #410 = NameAndType        #12:#409      // a:(Lcov;Lcaw;Lgj;II)V
  #411 = Methodref          #63.#410      // cdq.a:(Lcov;Lcaw;Lgj;II)V
  #412 = Utf8               (Lcav;Lgj;Lcov;Z)V
  #413 = Utf8               (Lcov;Lcav;Lgj;Lcov;Z)V
  #414 = NameAndType        #23:#413      // b:(Lcov;Lcav;Lgj;Lcov;Z)V
  #415 = Methodref          #63.#414      // cdq.b:(Lcov;Lcav;Lgj;Lcov;Z)V
  #416 = NameAndType        #12:#413      // a:(Lcov;Lcav;Lgj;Lcov;Z)V
  #417 = Methodref          #63.#416      // cdq.a:(Lcov;Lcav;Lgj;Lcov;Z)V
  #418 = Utf8               (Ladw;Lgj;Ljava/util/Random;)V
  #419 = Utf8               (Lcov;Ladw;Lgj;Ljava/util/Random;)V
  #420 = NameAndType        #12:#419      // a:(Lcov;Ladw;Lgj;Ljava/util/Random;)V
  #421 = Methodref          #63.#420      // cdq.a:(Lcov;Ladw;Lgj;Ljava/util/Random;)V
  #422 = Utf8               Ladw;
  #423 = Utf8               Ljava/util/Random;
  #424 = NameAndType        #23:#419      // b:(Lcov;Ladw;Lgj;Ljava/util/Random;)V
  #425 = Methodref          #63.#424      // cdq.b:(Lcov;Ladw;Lgj;Ljava/util/Random;)V
  #426 = Utf8               (Lcav;Lgj;Laxk;)V
  #427 = Utf8               (Lcov;Lcav;Lgj;Laxk;)V
  #428 = NameAndType        #12:#427      // a:(Lcov;Lcav;Lgj;Laxk;)V
  #429 = Methodref          #63.#428      // cdq.a:(Lcov;Lcav;Lgj;Laxk;)V
  #430 = Utf8               (Ladw;Lgj;Lbuw;)V
  #431 = Utf8               (Lcov;Ladw;Lgj;Lbuw;)V
  #432 = NameAndType        #12:#431      // a:(Lcov;Ladw;Lgj;Lbuw;)V
  #433 = Methodref          #63.#432      // cdq.a:(Lcov;Ladw;Lgj;Lbuw;)V
  #434 = Utf8               Lbuw;
  #435 = Utf8               (Ldlc$a;)Ljava/util/List;
  #436 = Utf8               (Ldlc$a;)Ljava/util/List<Lbuw;>;
  #437 = Utf8               (Lcov;Ldlc$a;)Ljava/util/List;
  #438 = NameAndType        #12:#437      // a:(Lcov;Ldlc$a;)Ljava/util/List;
  #439 = Methodref          #63.#438      // cdq.a:(Lcov;Ldlc$a;)Ljava/util/List;
  #440 = Utf8               Ldlc$a;
  #441 = Utf8               (Lcav;Lboj;Lawg;Ldpk;)Lawh;
  #442 = Utf8               dpk
  #443 = Class              #442          // dpk
  #444 = Utf8               ()Lgj;
  #445 = NameAndType        #12:#444      // a:()Lgj;
  #446 = Methodref          #443.#445     // dpk.a:()Lgj;
  #447 = Utf8               (Lcov;Lcav;Lgj;Lboj;Lawg;Ldpk;)Lawh;
  #448 = NameAndType        #12:#447      // a:(Lcov;Lcav;Lgj;Lboj;Lawg;Ldpk;)Lawh;
  #449 = Methodref          #63.#448      // cdq.a:(Lcov;Lcav;Lgj;Lboj;Lawg;Ldpk;)Lawh;
  #450 = Utf8               Lawg;
  #451 = Utf8               Ldpk;
  #452 = Utf8               (Lcav;Lgj;Lboj;)V
  #453 = Utf8               (Lcov;Lcav;Lgj;Lboj;)V
  #454 = NameAndType        #12:#453      // a:(Lcov;Lcav;Lgj;Lboj;)V
  #455 = Methodref          #63.#454      // cdq.a:(Lcov;Lcav;Lgj;Lboj;)V
  #456 = Utf8               (Lcov;Lgo;Lcov;Lcaw;Lgj;Lgj;)Lcov;
  #457 = NameAndType        #12:#456      // a:(Lcov;Lgo;Lcov;Lcaw;Lgj;Lgj;)Lcov;
  #458 = Methodref          #63.#457      // cdq.a:(Lcov;Lgo;Lcov;Lcaw;Lgj;Lgj;)Lcov;
  #459 = Utf8               (Lcab;Lgj;Ldjo;)Z
  #460 = Utf8               (Lcov;Lcab;Lgj;Ldjo;)Z
  #461 = NameAndType        #12:#460      // a:(Lcov;Lcab;Lgj;Ldjo;)Z
  #462 = Methodref          #63.#461      // cdq.a:(Lcov;Lcab;Lgj;Ldjo;)Z
  #463 = Utf8               Ldjo;
  #464 = Utf8               (Lbww;)Z
  #465 = Utf8               (Lcov;Lbww;)Z
  #466 = NameAndType        #12:#465      // a:(Lcov;Lbww;)Z
  #467 = Methodref          #63.#466      // cdq.a:(Lcov;Lbww;)Z
  #468 = Utf8               Lbww;
  #469 = Utf8               (Ldiw;)Z
  #470 = Utf8               (Lcov;Ldiw;)Z
  #471 = NameAndType        #12:#470      // a:(Lcov;Ldiw;)Z
  #472 = Methodref          #63.#471      // cdq.a:(Lcov;Ldiw;)Z
  #473 = Utf8               Ldiw;
  #474 = Utf8               (Lcay;Lgj;)Z
  #475 = Utf8               (Lcov;Lcay;Lgj;)Z
  #476 = NameAndType        #12:#475      // a:(Lcov;Lcay;Lgj;)Z
  #477 = Methodref          #63.#476      // cdq.a:(Lcov;Lcay;Lgj;)Z
  #478 = Utf8               Lcay;
  #479 = Utf8               (Lcav;Lgj;)Lawk;
  #480 = Utf8               (Lcov;Lcav;Lgj;)Lawk;
  #481 = NameAndType        #23:#480      // b:(Lcov;Lcav;Lgj;)Lawk;
  #482 = Methodref          #63.#481      // cdq.b:(Lcov;Lcav;Lgj;)Lawk;
  #483 = Utf8               (Laif;)Z
  #484 = Utf8               (Laif<Lcdq;>;)Z
  #485 = Utf8               ()Lgs$c;
  #486 = NameAndType        #52:#485      // q:()Lgs$c;
  #487 = Methodref          #63.#486      // cdq.q:()Lgs$c;
  #488 = NameAndType        #12:#483      // a:(Laif;)Z
  #489 = Methodref          #33.#488      // gs$c.a:(Laif;)Z
  #490 = Utf8               Laif<Lcdq;>;
  #491 = Utf8               Laif;
  #492 = Utf8               (Laif;Ljava/util/function/Predicate;)Z
  #493 = Utf8               (Laif<Lcdq;>;Ljava/util/function/Predicate<Lcou$a;>;)Z
  #494 = Methodref          #2.#488       // cou$a.a:(Laif;)Z
  #495 = Utf8               java/util/function/Predicate
  #496 = Class              #495          // java/util/function/Predicate
  #497 = Utf8               (Ljava/lang/Object;)Z
  #498 = NameAndType        #173:#497     // test:(Ljava/lang/Object;)Z
  #499 = InterfaceMethodref #496.#498     // java/util/function/Predicate.test:(Ljava/lang/Object;)Z
  #500 = Utf8               Ljava/util/function/Predicate<Lcou$a;>;
  #501 = Utf8               Ljava/util/function/Predicate;
  #502 = Utf8               (Lgt;)Z
  #503 = Utf8               (Lgt<Lcdq;>;)Z
  #504 = Utf8               gt
  #505 = Class              #504          // gt
  #506 = Utf8               (Lgs;)Z
  #507 = NameAndType        #12:#506      // a:(Lgs;)Z
  #508 = InterfaceMethodref #505.#507     // gt.a:(Lgs;)Z
  #509 = Utf8               Lgt<Lcdq;>;
  #510 = Utf8               Lgt;
  #511 = Utf8               ()Ljava/util/stream/Stream;
  #512 = Utf8               ()Ljava/util/stream/Stream<Laif<Lcdq;>;>;
  #513 = NameAndType        #11:#511      // c:()Ljava/util/stream/Stream;
  #514 = Methodref          #33.#513      // gs$c.c:()Ljava/util/stream/Stream;
  #515 = Utf8               cfx
  #516 = Class              #515          // cfx
  #517 = Utf8               (Lcav;Lcmt;)Lcms;
  #518 = Utf8               <T:Lcmr;>(Lcav;Lcmt<TT;>;)Lcms<TT;>;
  #519 = Utf8               (Lcav;Lcov;Lcmt;)Lcms;
  #520 = NameAndType        #12:#519      // a:(Lcav;Lcov;Lcmt;)Lcms;
  #521 = InterfaceMethodref #516.#520     // cfx.a:(Lcav;Lcov;Lcmt;)Lcms;
  #522 = Utf8               Lcmt<TT;>;
  #523 = Utf8               Lcmt;
  #524 = Utf8               (Lcdq;)Z
  #525 = Utf8               ()Ldix;
  #526 = Utf8               c_
  #527 = Utf8               (Lcov;)Ldix;
  #528 = NameAndType        #526:#527     // c_:(Lcov;)Ldix;
  #529 = Methodref          #63.#528      // cdq.c_:(Lcov;)Ldix;
  #530 = Utf8               e_
  #531 = NameAndType        #530:#83      // e_:(Lcov;)Z
  #532 = Methodref          #63.#531      // cdq.e_:(Lcov;)Z
  #533 = Utf8               (Lgj;)J
  #534 = Utf8               (Lcov;Lgj;)J
  #535 = NameAndType        #12:#534      // a:(Lcov;Lgj;)J
  #536 = Methodref          #63.#535      // cdq.a:(Lcov;Lgj;)J
  #537 = Utf8               ()Lckg;
  #538 = Utf8               (Lcov;)Lckg;
  #539 = NameAndType        #47:#538      // m:(Lcov;)Lckg;
  #540 = Methodref          #63.#539      // cdq.m:(Lcov;)Lckg;
  #541 = Utf8               (Lcav;Lcov;Ldpk;Lboz;)V
  #542 = NameAndType        #12:#541      // a:(Lcav;Lcov;Ldpk;Lboz;)V
  #543 = Methodref          #63.#542      // cdq.a:(Lcav;Lcov;Ldpk;Lboz;)V
  #544 = Utf8               Lboz;
  #545 = Utf8               (Lcab;Lgj;Lgo;)Z
  #546 = Utf8               ckw
  #547 = Class              #546          // ckw
  #548 = Utf8               Lckw;
  #549 = NameAndType        #12:#548      // a:Lckw;
  #550 = Fieldref           #547.#549     // ckw.a:Lckw;
  #551 = Utf8               (Lcab;Lgj;Lgo;Lckw;)Z
  #552 = NameAndType        #12:#551      // a:(Lcab;Lgj;Lgo;Lckw;)Z
  #553 = Methodref          #2.#552       // cou$a.a:(Lcab;Lgj;Lgo;Lckw;)Z
  #554 = Utf8               (Lgo;Lckw;)Z
  #555 = NameAndType        #12:#554      // a:(Lgo;Lckw;)Z
  #556 = Methodref          #17.#555      // cou$a$a.a:(Lgo;Lckw;)Z
  #557 = Utf8               (Lcov;Lcab;Lgj;Lgo;)Z
  #558 = NameAndType        #12:#557      // a:(Lcov;Lcab;Lgj;Lgo;)Z
  #559 = Methodref          #547.#558     // ckw.a:(Lcov;Lcab;Lgj;Lgo;)Z
  #560 = NameAndType        #20:#38       // d:Z
  #561 = Fieldref           #17.#560      // cou$a$a.d:Z
  #562 = NameAndType        #393:#183     // a_:(Lcov;Lcab;Lgj;)Z
  #563 = Methodref          #63.#562      // cdq.a_:(Lcov;Lcab;Lgj;)Z
  #564 = Utf8               RuntimeVisibleAnnotations
  #565 = Utf8               Code
  #566 = Utf8               LineNumberTable
  #567 = Utf8               LocalVariableTable
  #568 = Utf8               LocalVariableTypeTable
  #569 = Utf8               Signature
  #570 = Utf8               StackMapTable
  #571 = Utf8               InnerClasses
  #572 = Utf8               NestHost
{
  private final int b;
    descriptor: I
    flags: (0x0012) ACC_PRIVATE, ACC_FINAL

  private final boolean g;
    descriptor: Z
    flags: (0x0012) ACC_PRIVATE, ACC_FINAL

  private final boolean h;
    descriptor: Z
    flags: (0x0012) ACC_PRIVATE, ACC_FINAL

  private final djb i;
    descriptor: Ldjb;
    flags: (0x0012) ACC_PRIVATE, ACC_FINAL

  private final djc j;
    descriptor: Ldjc;
    flags: (0x0012) ACC_PRIVATE, ACC_FINAL

  private final float k;
    descriptor: F
    flags: (0x0012) ACC_PRIVATE, ACC_FINAL

  private final boolean l;
    descriptor: Z
    flags: (0x0012) ACC_PRIVATE, ACC_FINAL

  private final boolean m;
    descriptor: Z
    flags: (0x0012) ACC_PRIVATE, ACC_FINAL

  private final cou$e n;
    descriptor: Lcou$e;
    flags: (0x0012) ACC_PRIVATE, ACC_FINAL

  private final cou$e o;
    descriptor: Lcou$e;
    flags: (0x0012) ACC_PRIVATE, ACC_FINAL

  private final cou$e p;
    descriptor: Lcou$e;
    flags: (0x0012) ACC_PRIVATE, ACC_FINAL

  private final cou$e q;
    descriptor: Lcou$e;
    flags: (0x0012) ACC_PRIVATE, ACC_FINAL

  private final cou$e r;
    descriptor: Lcou$e;
    flags: (0x0012) ACC_PRIVATE, ACC_FINAL

  protected cou$a$a a;
    descriptor: Lcou$a$a;
    flags: (0x0004) ACC_PROTECTED
    RuntimeVisibleAnnotations:
      0: #55()
        javax.annotation.Nullable

  protected cou$a(cdq, com.google.common.collect.ImmutableMap<cpy<?>, java.lang.Comparable<?>>, com.mojang.serialization.MapCodec<cov>);
    descriptor: (Lcdq;Lcom/google/common/collect/ImmutableMap;Lcom/mojang/serialization/MapCodec;)V
    flags: (0x0004) ACC_PROTECTED
    Code:
      stack=4, locals=5, args_size=4
         0: aload_0
         1: aload_1
         2: aload_2
         3: aload_3
         4: invokespecial #61                 // Method cox."<init>":(Ljava/lang/Object;Lcom/google/common/collect/ImmutableMap;Lcom/mojang/serialization/MapCodec;)V
         7: aload_1
         8: getfield      #67                 // Field cdq.aO:Lcou$c;
        11: astore        4
        13: aload_0
        14: aload         4
        16: getfield      #70                 // Field cou$c.e:Ljava/util/function/ToIntFunction;
        19: aload_0
        20: invokevirtual #73                 // Method r:()Lcov;
        23: invokeinterface #79,  2           // InterfaceMethod java/util/function/ToIntFunction.applyAsInt:(Ljava/lang/Object;)I
        28: putfield      #81                 // Field b:I
        31: aload_0
        32: aload_1
        33: aload_0
        34: invokevirtual #73                 // Method r:()Lcov;
        37: invokevirtual #85                 // Method cdq.g_:(Lcov;)Z
        40: putfield      #87                 // Field g:Z
        43: aload_0
        44: aload         4
        46: getfield      #89                 // Field cou$c.o:Z
        49: putfield      #91                 // Field h:Z
        52: aload_0
        53: aload         4
        55: getfield      #93                 // Field cou$c.a:Ldjb;
        58: putfield      #95                 // Field i:Ldjb;
        61: aload_0
        62: aload         4
        64: getfield      #98                 // Field cou$c.b:Ljava/util/function/Function;
        67: aload_0
        68: invokevirtual #73                 // Method r:()Lcov;
        71: invokeinterface #104,  2          // InterfaceMethod java/util/function/Function.apply:(Ljava/lang/Object;)Ljava/lang/Object;
        76: checkcast     #106                // class djc
        79: putfield      #108                // Field j:Ldjc;
        82: aload_0
        83: aload         4
        85: getfield      #110                // Field cou$c.g:F
        88: putfield      #112                // Field k:F
        91: aload_0
        92: aload         4
        94: getfield      #113                // Field cou$c.h:Z
        97: putfield      #115                // Field l:Z
       100: aload_0
       101: aload         4
       103: getfield      #117                // Field cou$c.n:Z
       106: putfield      #119                // Field m:Z
       109: aload_0
       110: aload         4
       112: getfield      #121                // Field cou$c.q:Lcou$e;
       115: putfield      #123                // Field n:Lcou$e;
       118: aload_0
       119: aload         4
       121: getfield      #125                // Field cou$c.r:Lcou$e;
       124: putfield      #127                // Field o:Lcou$e;
       127: aload_0
       128: aload         4
       130: getfield      #130                // Field cou$c.s:Lcou$e;
       133: putfield      #132                // Field p:Lcou$e;
       136: aload_0
       137: aload         4
       139: getfield      #135                // Field cou$c.t:Lcou$e;
       142: putfield      #136                // Field q:Lcou$e;
       145: aload_0
       146: aload         4
       148: getfield      #139                // Field cou$c.u:Lcou$e;
       151: putfield      #140                // Field r:Lcou$e;
       154: return
      LineNumberTable:
        line 667: 0
        line 668: 7
        line 670: 13
        line 671: 31
        line 672: 43
        line 673: 52
        line 674: 61
        line 675: 82
        line 676: 91
        line 677: 100
        line 678: 109
        line 679: 118
        line 680: 127
        line 681: 136
        line 682: 145
        line 683: 154
      LocalVariableTable:
        Start  Length  Slot  Name   Signature
            0     155     0  this   Lcou$a;
            0     155     1   $$0   Lcdq;
            0     155     2   $$1   Lcom/google/common/collect/ImmutableMap;
            0     155     3   $$2   Lcom/mojang/serialization/MapCodec;
           13     142     4   $$3   Lcou$c;
      LocalVariableTypeTable:
        Start  Length  Slot  Name   Signature
            0     155     2   $$1   Lcom/google/common/collect/ImmutableMap<Lcpy<*>;Ljava/lang/Comparable<*>;>;
            0     155     3   $$2   Lcom/mojang/serialization/MapCodec<Lcov;>;
    Signature: #58                          // (Lcdq;Lcom/google/common/collect/ImmutableMap<Lcpy<*>;Ljava/lang/Comparable<*>;>;Lcom/mojang/serialization/MapCodec<Lcov;>;)V

  public void a();
    descriptor: ()V
    flags: (0x0001) ACC_PUBLIC
    Code:
      stack=4, locals=1, args_size=1
         0: aload_0
         1: invokevirtual #155                // Method b:()Lcdq;
         4: invokevirtual #158                // Method cdq.o:()Z
         7: ifne          25
        10: aload_0
        11: new           #17                 // class cou$a$a
        14: dup
        15: aload_0
        16: invokevirtual #73                 // Method r:()Lcov;
        19: invokespecial #161                // Method cou$a$a."<init>":(Lcov;)V
        22: putfield      #163                // Field a:Lcou$a$a;
        25: return
      StackMapTable: number_of_entries = 1
        frame_type = 250 /* chop */
          offset_delta = 25
      LineNumberTable:
        line 686: 0
        line 687: 10
        line 689: 25
      LocalVariableTable:
        Start  Length  Slot  Name   Signature
            0      26     0  this   Lcou$a;

  public cdq b();
    descriptor: ()Lcdq;
    flags: (0x0001) ACC_PUBLIC
    Code:
      stack=1, locals=1, args_size=1
         0: aload_0
         1: getfield      #166                // Field e:Ljava/lang/Object;
         4: checkcast     #63                 // class cdq
         7: areturn
      LineNumberTable:
        line 692: 0
      LocalVariableTable:
        Start  Length  Slot  Name   Signature
            0       8     0  this   Lcou$a;

  public djb c();
    descriptor: ()Ldjb;
    flags: (0x0001) ACC_PUBLIC
    Code:
      stack=1, locals=1, args_size=1
         0: aload_0
         1: getfield      #95                 // Field i:Ldjb;
         4: areturn
      LineNumberTable:
        line 696: 0
      LocalVariableTable:
        Start  Length  Slot  Name   Signature
            0       5     0  this   Lcou$a;

  public boolean a(cab, gj, axo<?>);
    descriptor: (Lcab;Lgj;Laxo;)Z
    flags: (0x0001) ACC_PUBLIC
    Code:
      stack=5, locals=4, args_size=4
         0: aload_0
         1: invokevirtual #155                // Method b:()Lcdq;
         4: getfield      #67                 // Field cdq.aO:Lcou$c;
         7: getfield      #172                // Field cou$c.p:Lcou$d;
        10: aload_0
        11: invokevirtual #73                 // Method r:()Lcov;
        14: aload_1
        15: aload_2
        16: aload_3
        17: invokeinterface #176,  5          // InterfaceMethod cou$d.test:(Lcov;Lcab;Lgj;Ljava/lang/Object;)Z
        22: ireturn
      LineNumberTable:
        line 700: 0
      LocalVariableTable:
        Start  Length  Slot  Name   Signature
            0      23     0  this   Lcou$a;
            0      23     1   $$0   Lcab;
            0      23     2   $$1   Lgj;
            0      23     3   $$2   Laxo;
      LocalVariableTypeTable:
        Start  Length  Slot  Name   Signature
            0      23     3   $$2   Laxo<*>;
    Signature: #169                         // (Lcab;Lgj;Laxo<*>;)Z

  public boolean a(cab, gj);
    descriptor: (Lcab;Lgj;)Z
    flags: (0x0001) ACC_PUBLIC
    Code:
      stack=4, locals=3, args_size=3
         0: aload_0
         1: getfield      #163                // Field a:Lcou$a$a;
         4: ifnull        15
         7: aload_0
         8: getfield      #163                // Field a:Lcou$a$a;
        11: getfield      #182                // Field cou$a$a.g:Z
        14: ireturn
        15: aload_0
        16: invokevirtual #155                // Method b:()Lcdq;
        19: aload_0
        20: invokevirtual #73                 // Method r:()Lcov;
        23: aload_1
        24: aload_2
        25: invokevirtual #185                // Method cdq.c:(Lcov;Lcab;Lgj;)Z
        28: ireturn
      StackMapTable: number_of_entries = 1
        frame_type = 15 /* same */
      LineNumberTable:
        line 704: 0
        line 705: 7
        line 707: 15
      LocalVariableTable:
        Start  Length  Slot  Name   Signature
            0      29     0  this   Lcou$a;
            0      29     1   $$0   Lcab;
            0      29     2   $$1   Lgj;

  public int b(cab, gj);
    descriptor: (Lcab;Lgj;)I
    flags: (0x0001) ACC_PUBLIC
    Code:
      stack=4, locals=3, args_size=3
         0: aload_0
         1: getfield      #163                // Field a:Lcou$a$a;
         4: ifnull        15
         7: aload_0
         8: getfield      #163                // Field a:Lcou$a$a;
        11: getfield      #188                // Field cou$a$a.h:I
        14: ireturn
        15: aload_0
        16: invokevirtual #155                // Method b:()Lcdq;
        19: aload_0
        20: invokevirtual #73                 // Method r:()Lcov;
        23: aload_1
        24: aload_2
        25: invokevirtual #191                // Method cdq.g:(Lcov;Lcab;Lgj;)I
        28: ireturn
      StackMapTable: number_of_entries = 1
        frame_type = 15 /* same */
      LineNumberTable:
        line 711: 0
        line 712: 7
        line 714: 15
      LocalVariableTable:
        Start  Length  Slot  Name   Signature
            0      29     0  this   Lcou$a;
            0      29     1   $$0   Lcab;
            0      29     2   $$1   Lgj;

  public dqh a(cab, gj, go);
    descriptor: (Lcab;Lgj;Lgo;)Ldqh;
    flags: (0x0001) ACC_PUBLIC
    Code:
      stack=3, locals=4, args_size=4
         0: aload_0
         1: getfield      #163                // Field a:Lcou$a$a;
         4: ifnull        30
         7: aload_0
         8: getfield      #163                // Field a:Lcou$a$a;
        11: getfield      #195                // Field cou$a$a.i:[Ldqh;
        14: ifnull        30
        17: aload_0
        18: getfield      #163                // Field a:Lcou$a$a;
        21: getfield      #195                // Field cou$a$a.i:[Ldqh;
        24: aload_3
        25: invokevirtual #201                // Method go.ordinal:()I
        28: aaload
        29: areturn
        30: aload_0
        31: aload_1
        32: aload_2
        33: invokevirtual #204                // Method c:(Lcab;Lgj;)Ldqh;
        36: aload_3
        37: invokestatic  #209                // Method dqe.a:(Ldqh;Lgo;)Ldqh;
        40: areturn
      StackMapTable: number_of_entries = 1
        frame_type = 30 /* same */
      LineNumberTable:
        line 718: 0
        line 719: 17
        line 722: 30
      LocalVariableTable:
        Start  Length  Slot  Name   Signature
            0      41     0  this   Lcou$a;
            0      41     1   $$0   Lcab;
            0      41     2   $$1   Lgj;
            0      41     3   $$2   Lgo;

  public dqh c(cab, gj);
    descriptor: (Lcab;Lgj;)Ldqh;
    flags: (0x0001) ACC_PUBLIC
    Code:
      stack=4, locals=3, args_size=3
         0: aload_0
         1: invokevirtual #155                // Method b:()Lcdq;
         4: aload_0
         5: invokevirtual #73                 // Method r:()Lcov;
         8: aload_1
         9: aload_2
        10: invokevirtual #214                // Method cdq.b_:(Lcov;Lcab;Lgj;)Ldqh;
        13: areturn
      LineNumberTable:
        line 726: 0
      LocalVariableTable:
        Start  Length  Slot  Name   Signature
            0      14     0  this   Lcou$a;
            0      14     1   $$0   Lcab;
            0      14     2   $$1   Lgj;

  public boolean d();
    descriptor: ()Z
    flags: (0x0001) ACC_PUBLIC
    Code:
      stack=1, locals=1, args_size=1
         0: aload_0
         1: getfield      #163                // Field a:Lcou$a$a;
         4: ifnull        17
         7: aload_0
         8: getfield      #163                // Field a:Lcou$a$a;
        11: getfield      #216                // Field cou$a$a.c:Z
        14: ifeq          21
        17: iconst_1
        18: goto          22
        21: iconst_0
        22: ireturn
      StackMapTable: number_of_entries = 3
        frame_type = 250 /* chop */
          offset_delta = 17
        frame_type = 3 /* same */
        frame_type = 64 /* same_locals_1_stack_item */
          stack = [ int ]
      LineNumberTable:
        line 731: 0
      LocalVariableTable:
        Start  Length  Slot  Name   Signature
            0      23     0  this   Lcou$a;

  public boolean e();
    descriptor: ()Z
    flags: (0x0001) ACC_PUBLIC
    Code:
      stack=1, locals=1, args_size=1
         0: aload_0
         1: getfield      #87                 // Field g:Z
         4: ireturn
      LineNumberTable:
        line 735: 0
      LocalVariableTable:
        Start  Length  Slot  Name   Signature
            0       5     0  this   Lcou$a;

  public int f();
    descriptor: ()I
    flags: (0x0001) ACC_PUBLIC
    Code:
      stack=1, locals=1, args_size=1
         0: aload_0
         1: getfield      #81                 // Field b:I
         4: ireturn
      LineNumberTable:
        line 739: 0
      LocalVariableTable:
        Start  Length  Slot  Name   Signature
            0       5     0  this   Lcou$a;

  public boolean g();
    descriptor: ()Z
    flags: (0x0001) ACC_PUBLIC
    Code:
      stack=1, locals=1, args_size=1
         0: aload_0
         1: getfield      #91                 // Field h:Z
         4: ireturn
      LineNumberTable:
        line 743: 0
      LocalVariableTable:
        Start  Length  Slot  Name   Signature
            0       5     0  this   Lcou$a;

  public djc d(cab, gj);
    descriptor: (Lcab;Lgj;)Ldjc;
    flags: (0x0001) ACC_PUBLIC
    Code:
      stack=1, locals=3, args_size=3
         0: aload_0
         1: getfield      #108                // Field j:Ldjc;
         4: areturn
      LineNumberTable:
        line 747: 0
      LocalVariableTable:
        Start  Length  Slot  Name   Signature
            0       5     0  this   Lcou$a;
            0       5     1   $$0   Lcab;
            0       5     2   $$1   Lgj;

  public cov a(cjm);
    descriptor: (Lcjm;)Lcov;
    flags: (0x0001) ACC_PUBLIC
    Code:
      stack=3, locals=2, args_size=2
         0: aload_0
         1: invokevirtual #155                // Method b:()Lcdq;
         4: aload_0
         5: invokevirtual #73                 // Method r:()Lcov;
         8: aload_1
         9: invokevirtual #222                // Method cdq.a:(Lcov;Lcjm;)Lcov;
        12: areturn
      LineNumberTable:
        line 751: 0
      LocalVariableTable:
        Start  Length  Slot  Name   Signature
            0      13     0  this   Lcou$a;
            0      13     1   $$0   Lcjm;

  public cov a(chz);
    descriptor: (Lchz;)Lcov;
    flags: (0x0001) ACC_PUBLIC
    Code:
      stack=3, locals=2, args_size=2
         0: aload_0
         1: invokevirtual #155                // Method b:()Lcdq;
         4: aload_0
         5: invokevirtual #73                 // Method r:()Lcov;
         8: aload_1
         9: invokevirtual #227                // Method cdq.a:(Lcov;Lchz;)Lcov;
        12: areturn
      LineNumberTable:
        line 755: 0
      LocalVariableTable:
        Start  Length  Slot  Name   Signature
            0      13     0  this   Lcou$a;
            0      13     1   $$0   Lchz;

  public cjf h();
    descriptor: ()Lcjf;
    flags: (0x0001) ACC_PUBLIC
    Code:
      stack=2, locals=1, args_size=1
         0: aload_0
         1: invokevirtual #155                // Method b:()Lcdq;
         4: aload_0
         5: invokevirtual #73                 // Method r:()Lcov;
         8: invokevirtual #232                // Method cdq.b_:(Lcov;)Lcjf;
        11: areturn
      LineNumberTable:
        line 759: 0
      LocalVariableTable:
        Start  Length  Slot  Name   Signature
            0      12     0  this   Lcou$a;

  public boolean e(cab, gj);
    descriptor: (Lcab;Lgj;)Z
    flags: (0x0001) ACC_PUBLIC
    Code:
      stack=4, locals=3, args_size=3
         0: aload_0
         1: getfield      #140                // Field r:Lcou$e;
         4: aload_0
         5: invokevirtual #73                 // Method r:()Lcov;
         8: aload_1
         9: aload_2
        10: invokeinterface #234,  4          // InterfaceMethod cou$e.test:(Lcov;Lcab;Lgj;)Z
        15: ireturn
      LineNumberTable:
        line 763: 0
      LocalVariableTable:
        Start  Length  Slot  Name   Signature
            0      16     0  this   Lcou$a;
            0      16     1   $$0   Lcab;
            0      16     2   $$1   Lgj;

  public float f(cab, gj);
    descriptor: (Lcab;Lgj;)F
    flags: (0x0001) ACC_PUBLIC
    Code:
      stack=4, locals=3, args_size=3
         0: aload_0
         1: invokevirtual #155                // Method b:()Lcdq;
         4: aload_0
         5: invokevirtual #73                 // Method r:()Lcov;
         8: aload_1
         9: aload_2
        10: invokevirtual #238                // Method cdq.b:(Lcov;Lcab;Lgj;)F
        13: freturn
      LineNumberTable:
        line 767: 0
      LocalVariableTable:
        Start  Length  Slot  Name   Signature
            0      14     0  this   Lcou$a;
            0      14     1   $$0   Lcab;
            0      14     2   $$1   Lgj;

  public boolean g(cab, gj);
    descriptor: (Lcab;Lgj;)Z
    flags: (0x0001) ACC_PUBLIC
    Code:
      stack=4, locals=3, args_size=3
         0: aload_0
         1: getfield      #123                // Field n:Lcou$e;
         4: aload_0
         5: invokevirtual #73                 // Method r:()Lcov;
         8: aload_1
         9: aload_2
        10: invokeinterface #234,  4          // InterfaceMethod cou$e.test:(Lcov;Lcab;Lgj;)Z
        15: ireturn
      LineNumberTable:
        line 771: 0
      LocalVariableTable:
        Start  Length  Slot  Name   Signature
            0      16     0  this   Lcou$a;
            0      16     1   $$0   Lcab;
            0      16     2   $$1   Lgj;

  public boolean i();
    descriptor: ()Z
    flags: (0x0001) ACC_PUBLIC
    Code:
      stack=2, locals=1, args_size=1
         0: aload_0
         1: invokevirtual #155                // Method b:()Lcdq;
         4: aload_0
         5: invokevirtual #73                 // Method r:()Lcov;
         8: invokevirtual #241                // Method cdq.f_:(Lcov;)Z
        11: ireturn
      LineNumberTable:
        line 775: 0
      LocalVariableTable:
        Start  Length  Slot  Name   Signature
            0      12     0  this   Lcou$a;

  public int b(cab, gj, go);
    descriptor: (Lcab;Lgj;Lgo;)I
    flags: (0x0001) ACC_PUBLIC
    Code:
      stack=5, locals=4, args_size=4
         0: aload_0
         1: invokevirtual #155                // Method b:()Lcdq;
         4: aload_0
         5: invokevirtual #73                 // Method r:()Lcov;
         8: aload_1
         9: aload_2
        10: aload_3
        11: invokevirtual #245                // Method cdq.a:(Lcov;Lcab;Lgj;Lgo;)I
        14: ireturn
      LineNumberTable:
        line 779: 0
      LocalVariableTable:
        Start  Length  Slot  Name   Signature
            0      15     0  this   Lcou$a;
            0      15     1   $$0   Lcab;
            0      15     2   $$1   Lgj;
            0      15     3   $$2   Lgo;

  public boolean j();
    descriptor: ()Z
    flags: (0x0001) ACC_PUBLIC
    Code:
      stack=2, locals=1, args_size=1
         0: aload_0
         1: invokevirtual #155                // Method b:()Lcdq;
         4: aload_0
         5: invokevirtual #73                 // Method r:()Lcov;
         8: invokevirtual #248                // Method cdq.d_:(Lcov;)Z
        11: ireturn
      LineNumberTable:
        line 783: 0
      LocalVariableTable:
        Start  Length  Slot  Name   Signature
            0      12     0  this   Lcou$a;

  public int a(cav, gj);
    descriptor: (Lcav;Lgj;)I
    flags: (0x0001) ACC_PUBLIC
    Code:
      stack=4, locals=3, args_size=3
         0: aload_0
         1: invokevirtual #155                // Method b:()Lcdq;
         4: aload_0
         5: invokevirtual #73                 // Method r:()Lcov;
         8: aload_1
         9: aload_2
        10: invokevirtual #252                // Method cdq.a:(Lcov;Lcav;Lgj;)I
        13: ireturn
      LineNumberTable:
        line 787: 0
      LocalVariableTable:
        Start  Length  Slot  Name   Signature
            0      14     0  this   Lcou$a;
            0      14     1   $$0   Lcav;
            0      14     2   $$1   Lgj;

  public float h(cab, gj);
    descriptor: (Lcab;Lgj;)F
    flags: (0x0001) ACC_PUBLIC
    Code:
      stack=1, locals=3, args_size=3
         0: aload_0
         1: getfield      #112                // Field k:F
         4: freturn
      LineNumberTable:
        line 791: 0
      LocalVariableTable:
        Start  Length  Slot  Name   Signature
            0       5     0  this   Lcou$a;
            0       5     1   $$0   Lcab;
            0       5     2   $$1   Lgj;

  public float a(boj, cab, gj);
    descriptor: (Lboj;Lcab;Lgj;)F
    flags: (0x0001) ACC_PUBLIC
    Code:
      stack=5, locals=4, args_size=4
         0: aload_0
         1: invokevirtual #155                // Method b:()Lcdq;
         4: aload_0
         5: invokevirtual #73                 // Method r:()Lcov;
         8: aload_1
         9: aload_2
        10: aload_3
        11: invokevirtual #257                // Method cdq.a:(Lcov;Lboj;Lcab;Lgj;)F
        14: freturn
      LineNumberTable:
        line 795: 0
      LocalVariableTable:
        Start  Length  Slot  Name   Signature
            0      15     0  this   Lcou$a;
            0      15     1   $$0   Lboj;
            0      15     2   $$1   Lcab;
            0      15     3   $$2   Lgj;

  public int c(cab, gj, go);
    descriptor: (Lcab;Lgj;Lgo;)I
    flags: (0x0001) ACC_PUBLIC
    Code:
      stack=5, locals=4, args_size=4
         0: aload_0
         1: invokevirtual #155                // Method b:()Lcdq;
         4: aload_0
         5: invokevirtual #73                 // Method r:()Lcov;
         8: aload_1
         9: aload_2
        10: aload_3
        11: invokevirtual #260                // Method cdq.b:(Lcov;Lcab;Lgj;Lgo;)I
        14: ireturn
      LineNumberTable:
        line 799: 0
      LocalVariableTable:
        Start  Length  Slot  Name   Signature
            0      15     0  this   Lcou$a;
            0      15     1   $$0   Lcab;
            0      15     2   $$1   Lgj;
            0      15     3   $$2   Lgo;

  public djd k();
    descriptor: ()Ldjd;
    flags: (0x0001) ACC_PUBLIC
    Code:
      stack=2, locals=1, args_size=1
         0: aload_0
         1: invokevirtual #155                // Method b:()Lcdq;
         4: aload_0
         5: invokevirtual #73                 // Method r:()Lcov;
         8: invokevirtual #264                // Method cdq.d:(Lcov;)Ldjd;
        11: areturn
      LineNumberTable:
        line 803: 0
      LocalVariableTable:
        Start  Length  Slot  Name   Signature
            0      12     0  this   Lcou$a;

  public boolean i(cab, gj);
    descriptor: (Lcab;Lgj;)Z
    flags: (0x0001) ACC_PUBLIC
    Code:
      stack=3, locals=4, args_size=3
         0: aload_0
         1: getfield      #163                // Field a:Lcou$a$a;
         4: ifnull        15
         7: aload_0
         8: getfield      #163                // Field a:Lcou$a$a;
        11: getfield      #266                // Field cou$a$a.a:Z
        14: ireturn
        15: aload_0
        16: invokevirtual #73                 // Method r:()Lcov;
        19: astore_3
        20: aload_3
        21: invokevirtual #270                // Method cov.l:()Z
        24: ifeq          37
        27: aload_3
        28: aload_1
        29: aload_2
        30: invokevirtual #271                // Method cov.c:(Lcab;Lgj;)Ldqh;
        33: invokestatic  #274                // Method cdq.a:(Ldqh;)Z
        36: ireturn
        37: iconst_0
        38: ireturn
      StackMapTable: number_of_entries = 2
        frame_type = 15 /* same */
        frame_type = 248 /* chop */
          offset_delta = 21
      LineNumberTable:
        line 807: 0
        line 808: 7
        line 810: 15
        line 811: 20
        line 812: 27
        line 814: 37
      LocalVariableTable:
        Start  Length  Slot  Name   Signature
            0      39     0  this   Lcou$a;
            0      39     1   $$0   Lcab;
            0      39     2   $$1   Lgj;
           20      19     3   $$2   Lcov;

  public boolean l();
    descriptor: ()Z
    flags: (0x0001) ACC_PUBLIC
    Code:
      stack=1, locals=1, args_size=1
         0: aload_0
         1: getfield      #119                // Field m:Z
         4: ireturn
      LineNumberTable:
        line 818: 0
      LocalVariableTable:
        Start  Length  Slot  Name   Signature
            0       5     0  this   Lcou$a;

  public boolean a(cov, go);
    descriptor: (Lcov;Lgo;)Z
    flags: (0x0001) ACC_PUBLIC
    Code:
      stack=4, locals=3, args_size=3
         0: aload_0
         1: invokevirtual #155                // Method b:()Lcdq;
         4: aload_0
         5: invokevirtual #73                 // Method r:()Lcov;
         8: aload_1
         9: aload_2
        10: invokevirtual #279                // Method cdq.a:(Lcov;Lcov;Lgo;)Z
        13: ireturn
      LineNumberTable:
        line 822: 0
      LocalVariableTable:
        Start  Length  Slot  Name   Signature
            0      14     0  this   Lcou$a;
            0      14     1   $$0   Lcov;
            0      14     2   $$1   Lgo;

  public dqh j(cab, gj);
    descriptor: (Lcab;Lgj;)Ldqh;
    flags: (0x0001) ACC_PUBLIC
    Code:
      stack=4, locals=3, args_size=3
         0: aload_0
         1: aload_1
         2: aload_2
         3: invokestatic  #284                // InterfaceMethod dpt.a:()Ldpt;
         6: invokevirtual #287                // Method a:(Lcab;Lgj;Ldpt;)Ldqh;
         9: areturn
      LineNumberTable:
        line 826: 0
      LocalVariableTable:
        Start  Length  Slot  Name   Signature
            0      10     0  this   Lcou$a;
            0      10     1   $$0   Lcab;
            0      10     2   $$1   Lgj;

  public dqh a(cab, gj, dpt);
    descriptor: (Lcab;Lgj;Ldpt;)Ldqh;
    flags: (0x0001) ACC_PUBLIC
    Code:
      stack=5, locals=4, args_size=4
         0: aload_0
         1: invokevirtual #155                // Method b:()Lcdq;
         4: aload_0
         5: invokevirtual #73                 // Method r:()Lcov;
         8: aload_1
         9: aload_2
        10: aload_3
        11: invokevirtual #290                // Method cdq.a:(Lcov;Lcab;Lgj;Ldpt;)Ldqh;
        14: areturn
      LineNumberTable:
        line 830: 0
      LocalVariableTable:
        Start  Length  Slot  Name   Signature
            0      15     0  this   Lcou$a;
            0      15     1   $$0   Lcab;
            0      15     2   $$1   Lgj;
            0      15     3   $$2   Ldpt;

  public dqh k(cab, gj);
    descriptor: (Lcab;Lgj;)Ldqh;
    flags: (0x0001) ACC_PUBLIC
    Code:
      stack=4, locals=3, args_size=3
         0: aload_0
         1: getfield      #163                // Field a:Lcou$a$a;
         4: ifnull        15
         7: aload_0
         8: getfield      #163                // Field a:Lcou$a$a;
        11: getfield      #294                // Field cou$a$a.b:Ldqh;
        14: areturn
        15: aload_0
        16: aload_1
        17: aload_2
        18: invokestatic  #284                // InterfaceMethod dpt.a:()Ldpt;
        21: invokevirtual #296                // Method b:(Lcab;Lgj;Ldpt;)Ldqh;
        24: areturn
      StackMapTable: number_of_entries = 1
        frame_type = 15 /* same */
      LineNumberTable:
        line 834: 0
        line 835: 7
        line 837: 15
      LocalVariableTable:
        Start  Length  Slot  Name   Signature
            0      25     0  this   Lcou$a;
            0      25     1   $$0   Lcab;
            0      25     2   $$1   Lgj;

  public dqh b(cab, gj, dpt);
    descriptor: (Lcab;Lgj;Ldpt;)Ldqh;
    flags: (0x0001) ACC_PUBLIC
    Code:
      stack=5, locals=4, args_size=4
         0: aload_0
         1: invokevirtual #155                // Method b:()Lcdq;
         4: aload_0
         5: invokevirtual #73                 // Method r:()Lcov;
         8: aload_1
         9: aload_2
        10: aload_3
        11: invokevirtual #298                // Method cdq.c:(Lcov;Lcab;Lgj;Ldpt;)Ldqh;
        14: areturn
      LineNumberTable:
        line 841: 0
      LocalVariableTable:
        Start  Length  Slot  Name   Signature
            0      15     0  this   Lcou$a;
            0      15     1   $$0   Lcab;
            0      15     2   $$1   Lgj;
            0      15     3   $$2   Ldpt;

  public dqh l(cab, gj);
    descriptor: (Lcab;Lgj;)Ldqh;
    flags: (0x0001) ACC_PUBLIC
    Code:
      stack=4, locals=3, args_size=3
         0: aload_0
         1: invokevirtual #155                // Method b:()Lcdq;
         4: aload_0
         5: invokevirtual #73                 // Method r:()Lcov;
         8: aload_1
         9: aload_2
        10: invokevirtual #300                // Method cdq.f:(Lcov;Lcab;Lgj;)Ldqh;
        13: areturn
      LineNumberTable:
        line 845: 0
      LocalVariableTable:
        Start  Length  Slot  Name   Signature
            0      14     0  this   Lcou$a;
            0      14     1   $$0   Lcab;
            0      14     2   $$1   Lgj;

  public dqh c(cab, gj, dpt);
    descriptor: (Lcab;Lgj;Ldpt;)Ldqh;
    flags: (0x0001) ACC_PUBLIC
    Code:
      stack=5, locals=4, args_size=4
         0: aload_0
         1: invokevirtual #155                // Method b:()Lcdq;
         4: aload_0
         5: invokevirtual #73                 // Method r:()Lcov;
         8: aload_1
         9: aload_2
        10: aload_3
        11: invokevirtual #302                // Method cdq.b:(Lcov;Lcab;Lgj;Ldpt;)Ldqh;
        14: areturn
      LineNumberTable:
        line 849: 0
      LocalVariableTable:
        Start  Length  Slot  Name   Signature
            0      15     0  this   Lcou$a;
            0      15     1   $$0   Lcab;
            0      15     2   $$1   Lgj;
            0      15     3   $$2   Ldpt;

  public dqh m(cab, gj);
    descriptor: (Lcab;Lgj;)Ldqh;
    flags: (0x0001) ACC_PUBLIC
    Code:
      stack=4, locals=3, args_size=3
         0: aload_0
         1: invokevirtual #155                // Method b:()Lcdq;
         4: aload_0
         5: invokevirtual #73                 // Method r:()Lcov;
         8: aload_1
         9: aload_2
        10: invokevirtual #304                // Method cdq.a:(Lcov;Lcab;Lgj;)Ldqh;
        13: areturn
      LineNumberTable:
        line 853: 0
      LocalVariableTable:
        Start  Length  Slot  Name   Signature
            0      14     0  this   Lcou$a;
            0      14     1   $$0   Lcab;
            0      14     2   $$1   Lgj;

  public final boolean a(cab, gj, axk);
    descriptor: (Lcab;Lgj;Laxk;)Z
    flags: (0x0011) ACC_PUBLIC, ACC_FINAL
    Code:
      stack=5, locals=4, args_size=4
         0: aload_0
         1: aload_1
         2: aload_2
         3: aload_3
         4: getstatic     #307                // Field go.b:Lgo;
         7: invokevirtual #310                // Method a:(Lcab;Lgj;Laxk;Lgo;)Z
        10: ireturn
      LineNumberTable:
        line 857: 0
      LocalVariableTable:
        Start  Length  Slot  Name   Signature
            0      11     0  this   Lcou$a;
            0      11     1   $$0   Lcab;
            0      11     2   $$1   Lgj;
            0      11     3   $$2   Laxk;

  public final boolean a(cab, gj, axk, go);
    descriptor: (Lcab;Lgj;Laxk;Lgo;)Z
    flags: (0x0011) ACC_PUBLIC, ACC_FINAL
    Code:
      stack=4, locals=5, args_size=5
         0: aload_0
         1: aload_1
         2: aload_2
         3: aload_3
         4: invokestatic  #314                // InterfaceMethod dpt.a:(Laxk;)Ldpt;
         7: invokevirtual #296                // Method b:(Lcab;Lgj;Ldpt;)Ldqh;
        10: aload         4
        12: invokestatic  #317                // Method cdq.a:(Ldqh;Lgo;)Z
        15: ireturn
      LineNumberTable:
        line 861: 0
      LocalVariableTable:
        Start  Length  Slot  Name   Signature
            0      16     0  this   Lcou$a;
            0      16     1   $$0   Lcab;
            0      16     2   $$1   Lgj;
            0      16     3   $$2   Laxk;
            0      16     4   $$3   Lgo;

  public dpo n(cab, gj);
    descriptor: (Lcab;Lgj;)Ldpo;
    flags: (0x0001) ACC_PUBLIC
    Code:
      stack=8, locals=14, args_size=3
         0: aload_0
         1: invokevirtual #155                // Method b:()Lcdq;
         4: astore_3
         5: aload_3
         6: invokevirtual #322                // Method cdq.U_:()Lcou$b;
         9: astore        4
        11: aload         4
        13: getstatic     #325                // Field cou$b.a:Lcou$b;
        16: if_acmpne     23
        19: getstatic     #330                // Field dpo.a:Ldpo;
        22: areturn
        23: aload_2
        24: invokevirtual #332                // Method gj.u:()I
        27: iconst_0
        28: aload_2
        29: invokevirtual #335                // Method gj.w:()I
        32: invokestatic  #340                // Method ajl.c:(III)J
        35: lstore        5
        37: aload_3
        38: invokevirtual #344                // Method cdq.W_:()F
        41: fstore        7
        43: lload         5
        45: ldc2_w        #345                // long 15l
        48: land
        49: l2f
        50: ldc_w         #347                // float 15.0f
        53: fdiv
        54: f2d
        55: ldc2_w        #348                // double 0.5d
        58: dsub
        59: ldc2_w        #348                // double 0.5d
        62: dmul
        63: fload         7
        65: fneg
        66: f2d
        67: fload         7
        69: f2d
        70: invokestatic  #352                // Method ajl.a:(DDD)D
        73: dstore        8
        75: aload         4
        77: getstatic     #354                // Field cou$b.c:Lcou$b;
        80: if_acmpne     108
        83: lload         5
        85: iconst_4
        86: lshr
        87: ldc2_w        #345                // long 15l
        90: land
        91: l2f
        92: ldc_w         #347                // float 15.0f
        95: fdiv
        96: f2d
        97: dconst_1
        98: dsub
        99: aload_3
       100: invokevirtual #357                // Method cdq.Z_:()F
       103: f2d
       104: dmul
       105: goto          109
       108: dconst_0
       109: dstore        10
       111: lload         5
       113: bipush        8
       115: lshr
       116: ldc2_w        #345                // long 15l
       119: land
       120: l2f
       121: ldc_w         #347                // float 15.0f
       124: fdiv
       125: f2d
       126: ldc2_w        #348                // double 0.5d
       129: dsub
       130: ldc2_w        #348                // double 0.5d
       133: dmul
       134: fload         7
       136: fneg
       137: f2d
       138: fload         7
       140: f2d
       141: invokestatic  #352                // Method ajl.a:(DDD)D
       144: dstore        12
       146: new           #327                // class dpo
       149: dup
       150: dload         8
       152: dload         10
       154: dload         12
       156: invokespecial #360                // Method dpo."<init>":(DDD)V
       159: areturn
      StackMapTable: number_of_entries = 3
        frame_type = 255 /* full_frame */
          offset_delta = 23
          locals = [ top, top, class gj, class cdq, class cou$b ]
          stack = []
        frame_type = 255 /* full_frame */
          offset_delta = 84
          locals = [ top, top, top, top, top, long, float, double ]
          stack = []
        frame_type = 64 /* same_locals_1_stack_item */
          stack = [ double ]
      LineNumberTable:
        line 865: 0
        line 866: 5
        line 867: 11
        line 868: 19
        line 871: 23
        line 872: 37
        line 873: 43
        line 874: 75
        line 875: 111
        line 876: 146
      LocalVariableTable:
        Start  Length  Slot  Name   Signature
            0     160     0  this   Lcou$a;
            0     160     1   $$0   Lcab;
            0     160     2   $$1   Lgj;
            5     155     3   $$2   Lcdq;
           11     149     4   $$3   Lcou$b;
           37     123     5   $$4   J
           43     117     7   $$5   F
           75      85     8   $$6   D
          111      49    10   $$7   D
          146      14    12   $$8   D

  public boolean a(cav, gj, int, int);
    descriptor: (Lcav;Lgj;II)Z
    flags: (0x0001) ACC_PUBLIC
    Code:
      stack=6, locals=5, args_size=5
         0: aload_0
         1: invokevirtual #155                // Method b:()Lcdq;
         4: aload_0
         5: invokevirtual #73                 // Method r:()Lcov;
         8: aload_1
         9: aload_2
        10: iload_3
        11: iload         4
        13: invokevirtual #371                // Method cdq.a:(Lcov;Lcav;Lgj;II)Z
        16: ireturn
      LineNumberTable:
        line 880: 0
      LocalVariableTable:
        Start  Length  Slot  Name   Signature
            0      17     0  this   Lcou$a;
            0      17     1   $$0   Lcav;
            0      17     2   $$1   Lgj;
            0      17     3   $$2   I
            0      17     4   $$3   I

  public void a(cav, gj, cdq, gj, boolean);
    descriptor: (Lcav;Lgj;Lcdq;Lgj;Z)V
    flags: (0x0001) ACC_PUBLIC
    Code:
      stack=7, locals=6, args_size=6
         0: aload_0
         1: invokevirtual #155                // Method b:()Lcdq;
         4: aload_0
         5: invokevirtual #73                 // Method r:()Lcov;
         8: aload_1
         9: aload_2
        10: aload_3
        11: aload         4
        13: iload         5
        15: invokevirtual #375                // Method cdq.a:(Lcov;Lcav;Lgj;Lcdq;Lgj;Z)V
        18: return
      LineNumberTable:
        line 884: 0
        line 885: 18
      LocalVariableTable:
        Start  Length  Slot  Name   Signature
            0      19     0  this   Lcou$a;
            0      19     1   $$0   Lcav;
            0      19     2   $$1   Lgj;
            0      19     3   $$2   Lcdq;
            0      19     4   $$3   Lgj;
            0      19     5   $$4   Z

  public final void a(caw, gj, int);
    descriptor: (Lcaw;Lgj;I)V
    flags: (0x0011) ACC_PUBLIC, ACC_FINAL
    Code:
      stack=5, locals=4, args_size=4
         0: aload_0
         1: aload_1
         2: aload_2
         3: iload_3
         4: sipush        512
         7: invokevirtual #379                // Method a:(Lcaw;Lgj;II)V
        10: return
      LineNumberTable:
        line 888: 0
        line 889: 10
      LocalVariableTable:
        Start  Length  Slot  Name   Signature
            0      11     0  this   Lcou$a;
            0      11     1   $$0   Lcaw;
            0      11     2   $$1   Lgj;
            0      11     3   $$2   I

  public final void a(caw, gj, int, int);
    descriptor: (Lcaw;Lgj;II)V
    flags: (0x0011) ACC_PUBLIC, ACC_FINAL
    Code:
      stack=6, locals=12, args_size=5
         0: aload_0
         1: invokevirtual #155                // Method b:()Lcdq;
         4: pop
         5: new           #25                 // class gj$a
         8: dup
         9: invokespecial #382                // Method gj$a."<init>":()V
        12: astore        5
        14: getstatic     #386                // Field cou.aE:[Lgo;
        17: astore        6
        19: aload         6
        21: arraylength
        22: istore        7
        24: iconst_0
        25: istore        8
        27: iload         8
        29: iload         7
        31: if_icmpge     99
        34: aload         6
        36: iload         8
        38: aaload
        39: astore        9
        41: aload         5
        43: aload_2
        44: aload         9
        46: invokevirtual #392                // Method gj$a.a:(Lhh;Lgo;)Lgj$a;
        49: pop
        50: aload_1
        51: aload         5
        53: invokeinterface #396,  2          // InterfaceMethod caw.a_:(Lgj;)Lcov;
        58: astore        10
        60: aload         10
        62: aload         9
        64: invokevirtual #399                // Method go.f:()Lgo;
        67: aload_0
        68: invokevirtual #73                 // Method r:()Lcov;
        71: aload_1
        72: aload         5
        74: aload_2
        75: invokevirtual #402                // Method cov.a:(Lgo;Lcov;Lcaw;Lgj;Lgj;)Lcov;
        78: astore        11
        80: aload         10
        82: aload         11
        84: aload_1
        85: aload         5
        87: iload_3
        88: iload         4
        90: invokestatic  #405                // Method cdq.a:(Lcov;Lcov;Lcaw;Lgj;II)V
        93: iinc          8, 1
        96: goto          27
        99: return
      StackMapTable: number_of_entries = 2
        frame_type = 255 /* full_frame */
          offset_delta = 27
          locals = [ class cou$a, class caw, class gj, int, int, class gj$a, class "[Lgo;", int, int ]
          stack = []
        frame_type = 255 /* full_frame */
          offset_delta = 71
          locals = []
          stack = []
      LineNumberTable:
        line 892: 0
        line 893: 5
        line 894: 14
        line 895: 41
        line 896: 50
        line 897: 60
        line 898: 80
        line 894: 93
        line 900: 99
      LocalVariableTable:
        Start  Length  Slot  Name   Signature
            0     100     0  this   Lcou$a;
            0     100     1   $$0   Lcaw;
            0     100     2   $$1   Lgj;
            0     100     3   $$2   I
            0     100     4   $$3   I
           14      86     5   $$4   Lgj$a;
           41      52     9   $$5   Lgo;
           60      33    10   $$6   Lcov;
           80      13    11   $$7   Lcov;

  public final void b(caw, gj, int);
    descriptor: (Lcaw;Lgj;I)V
    flags: (0x0011) ACC_PUBLIC, ACC_FINAL
    Code:
      stack=5, locals=4, args_size=4
         0: aload_0
         1: aload_1
         2: aload_2
         3: iload_3
         4: sipush        512
         7: invokevirtual #408                // Method b:(Lcaw;Lgj;II)V
        10: return
      LineNumberTable:
        line 903: 0
        line 904: 10
      LocalVariableTable:
        Start  Length  Slot  Name   Signature
            0      11     0  this   Lcou$a;
            0      11     1   $$0   Lcaw;
            0      11     2   $$1   Lgj;
            0      11     3   $$2   I

  public void b(caw, gj, int, int);
    descriptor: (Lcaw;Lgj;II)V
    flags: (0x0001) ACC_PUBLIC
    Code:
      stack=6, locals=5, args_size=5
         0: aload_0
         1: invokevirtual #155                // Method b:()Lcdq;
         4: aload_0
         5: invokevirtual #73                 // Method r:()Lcov;
         8: aload_1
         9: aload_2
        10: iload_3
        11: iload         4
        13: invokevirtual #411                // Method cdq.a:(Lcov;Lcaw;Lgj;II)V
        16: return
      LineNumberTable:
        line 907: 0
        line 908: 16
      LocalVariableTable:
        Start  Length  Slot  Name   Signature
            0      17     0  this   Lcou$a;
            0      17     1   $$0   Lcaw;
            0      17     2   $$1   Lgj;
            0      17     3   $$2   I
            0      17     4   $$3   I

  public void a(cav, gj, cov, boolean);
    descriptor: (Lcav;Lgj;Lcov;Z)V
    flags: (0x0001) ACC_PUBLIC
    Code:
      stack=6, locals=5, args_size=5
         0: aload_0
         1: invokevirtual #155                // Method b:()Lcdq;
         4: aload_0
         5: invokevirtual #73                 // Method r:()Lcov;
         8: aload_1
         9: aload_2
        10: aload_3
        11: iload         4
        13: invokevirtual #415                // Method cdq.b:(Lcov;Lcav;Lgj;Lcov;Z)V
        16: return
      LineNumberTable:
        line 911: 0
        line 912: 16
      LocalVariableTable:
        Start  Length  Slot  Name   Signature
            0      17     0  this   Lcou$a;
            0      17     1   $$0   Lcav;
            0      17     2   $$1   Lgj;
            0      17     3   $$2   Lcov;
            0      17     4   $$3   Z

  public void b(cav, gj, cov, boolean);
    descriptor: (Lcav;Lgj;Lcov;Z)V
    flags: (0x0001) ACC_PUBLIC
    Code:
      stack=6, locals=5, args_size=5
         0: aload_0
         1: invokevirtual #155                // Method b:()Lcdq;
         4: aload_0
         5: invokevirtual #73                 // Method r:()Lcov;
         8: aload_1
         9: aload_2
        10: aload_3
        11: iload         4
        13: invokevirtual #417                // Method cdq.a:(Lcov;Lcav;Lgj;Lcov;Z)V
        16: return
      LineNumberTable:
        line 915: 0
        line 916: 16
      LocalVariableTable:
        Start  Length  Slot  Name   Signature
            0      17     0  this   Lcou$a;
            0      17     1   $$0   Lcav;
            0      17     2   $$1   Lgj;
            0      17     3   $$2   Lcov;
            0      17     4   $$3   Z

  public void a(adw, gj, java.util.Random);
    descriptor: (Ladw;Lgj;Ljava/util/Random;)V
    flags: (0x0001) ACC_PUBLIC
    Code:
      stack=5, locals=4, args_size=4
         0: aload_0
         1: invokevirtual #155                // Method b:()Lcdq;
         4: aload_0
         5: invokevirtual #73                 // Method r:()Lcov;
         8: aload_1
         9: aload_2
        10: aload_3
        11: invokevirtual #421                // Method cdq.a:(Lcov;Ladw;Lgj;Ljava/util/Random;)V
        14: return
      LineNumberTable:
        line 919: 0
        line 920: 14
      LocalVariableTable:
        Start  Length  Slot  Name   Signature
            0      15     0  this   Lcou$a;
            0      15     1   $$0   Ladw;
            0      15     2   $$1   Lgj;
            0      15     3   $$2   Ljava/util/Random;

  public void b(adw, gj, java.util.Random);
    descriptor: (Ladw;Lgj;Ljava/util/Random;)V
    flags: (0x0001) ACC_PUBLIC
    Code:
      stack=5, locals=4, args_size=4
         0: aload_0
         1: invokevirtual #155                // Method b:()Lcdq;
         4: aload_0
         5: invokevirtual #73                 // Method r:()Lcov;
         8: aload_1
         9: aload_2
        10: aload_3
        11: invokevirtual #425                // Method cdq.b:(Lcov;Ladw;Lgj;Ljava/util/Random;)V
        14: return
      LineNumberTable:
        line 923: 0
        line 924: 14
      LocalVariableTable:
        Start  Length  Slot  Name   Signature
            0      15     0  this   Lcou$a;
            0      15     1   $$0   Ladw;
            0      15     2   $$1   Lgj;
            0      15     3   $$2   Ljava/util/Random;

  public void a(cav, gj, axk);
    descriptor: (Lcav;Lgj;Laxk;)V
    flags: (0x0001) ACC_PUBLIC
    Code:
      stack=5, locals=4, args_size=4
         0: aload_0
         1: invokevirtual #155                // Method b:()Lcdq;
         4: aload_0
         5: invokevirtual #73                 // Method r:()Lcov;
         8: aload_1
         9: aload_2
        10: aload_3
        11: invokevirtual #429                // Method cdq.a:(Lcov;Lcav;Lgj;Laxk;)V
        14: return
      LineNumberTable:
        line 927: 0
        line 928: 14
      LocalVariableTable:
        Start  Length  Slot  Name   Signature
            0      15     0  this   Lcou$a;
            0      15     1   $$0   Lcav;
            0      15     2   $$1   Lgj;
            0      15     3   $$2   Laxk;

  public void a(adw, gj, buw);
    descriptor: (Ladw;Lgj;Lbuw;)V
    flags: (0x0001) ACC_PUBLIC
    Code:
      stack=5, locals=4, args_size=4
         0: aload_0
         1: invokevirtual #155                // Method b:()Lcdq;
         4: aload_0
         5: invokevirtual #73                 // Method r:()Lcov;
         8: aload_1
         9: aload_2
        10: aload_3
        11: invokevirtual #433                // Method cdq.a:(Lcov;Ladw;Lgj;Lbuw;)V
        14: return
      LineNumberTable:
        line 931: 0
        line 932: 14
      LocalVariableTable:
        Start  Length  Slot  Name   Signature
            0      15     0  this   Lcou$a;
            0      15     1   $$0   Ladw;
            0      15     2   $$1   Lgj;
            0      15     3   $$2   Lbuw;

  public java.util.List<buw> a(dlc$a);
    descriptor: (Ldlc$a;)Ljava/util/List;
    flags: (0x0001) ACC_PUBLIC
    Code:
      stack=3, locals=2, args_size=2
         0: aload_0
         1: invokevirtual #155                // Method b:()Lcdq;
         4: aload_0
         5: invokevirtual #73                 // Method r:()Lcov;
         8: aload_1
         9: invokevirtual #439                // Method cdq.a:(Lcov;Ldlc$a;)Ljava/util/List;
        12: areturn
      LineNumberTable:
        line 935: 0
      LocalVariableTable:
        Start  Length  Slot  Name   Signature
            0      13     0  this   Lcou$a;
            0      13     1   $$0   Ldlc$a;
    Signature: #436                         // (Ldlc$a;)Ljava/util/List<Lbuw;>;

  public awh a(cav, boj, awg, dpk);
    descriptor: (Lcav;Lboj;Lawg;Ldpk;)Lawh;
    flags: (0x0001) ACC_PUBLIC
    Code:
      stack=7, locals=5, args_size=5
         0: aload_0
         1: invokevirtual #155                // Method b:()Lcdq;
         4: aload_0
         5: invokevirtual #73                 // Method r:()Lcov;
         8: aload_1
         9: aload         4
        11: invokevirtual #446                // Method dpk.a:()Lgj;
        14: aload_2
        15: aload_3
        16: aload         4
        18: invokevirtual #449                // Method cdq.a:(Lcov;Lcav;Lgj;Lboj;Lawg;Ldpk;)Lawh;
        21: areturn
      LineNumberTable:
        line 939: 0
      LocalVariableTable:
        Start  Length  Slot  Name   Signature
            0      22     0  this   Lcou$a;
            0      22     1   $$0   Lcav;
            0      22     2   $$1   Lboj;
            0      22     3   $$2   Lawg;
            0      22     4   $$3   Ldpk;

  public void a(cav, gj, boj);
    descriptor: (Lcav;Lgj;Lboj;)V
    flags: (0x0001) ACC_PUBLIC
    Code:
      stack=5, locals=4, args_size=4
         0: aload_0
         1: invokevirtual #155                // Method b:()Lcdq;
         4: aload_0
         5: invokevirtual #73                 // Method r:()Lcov;
         8: aload_1
         9: aload_2
        10: aload_3
        11: invokevirtual #455                // Method cdq.a:(Lcov;Lcav;Lgj;Lboj;)V
        14: return
      LineNumberTable:
        line 943: 0
        line 944: 14
      LocalVariableTable:
        Start  Length  Slot  Name   Signature
            0      15     0  this   Lcou$a;
            0      15     1   $$0   Lcav;
            0      15     2   $$1   Lgj;
            0      15     3   $$2   Lboj;

  public boolean o(cab, gj);
    descriptor: (Lcab;Lgj;)Z
    flags: (0x0001) ACC_PUBLIC
    Code:
      stack=4, locals=3, args_size=3
         0: aload_0
         1: getfield      #127                // Field o:Lcou$e;
         4: aload_0
         5: invokevirtual #73                 // Method r:()Lcov;
         8: aload_1
         9: aload_2
        10: invokeinterface #234,  4          // InterfaceMethod cou$e.test:(Lcov;Lcab;Lgj;)Z
        15: ireturn
      LineNumberTable:
        line 947: 0
      LocalVariableTable:
        Start  Length  Slot  Name   Signature
            0      16     0  this   Lcou$a;
            0      16     1   $$0   Lcab;
            0      16     2   $$1   Lgj;

  public boolean p(cab, gj);
    descriptor: (Lcab;Lgj;)Z
    flags: (0x0001) ACC_PUBLIC
    Code:
      stack=4, locals=3, args_size=3
         0: aload_0
         1: getfield      #132                // Field p:Lcou$e;
         4: aload_0
         5: invokevirtual #73                 // Method r:()Lcov;
         8: aload_1
         9: aload_2
        10: invokeinterface #234,  4          // InterfaceMethod cou$e.test:(Lcov;Lcab;Lgj;)Z
        15: ireturn
      LineNumberTable:
        line 951: 0
      LocalVariableTable:
        Start  Length  Slot  Name   Signature
            0      16     0  this   Lcou$a;
            0      16     1   $$0   Lcab;
            0      16     2   $$1   Lgj;

  public cov a(go, cov, caw, gj, gj);
    descriptor: (Lgo;Lcov;Lcaw;Lgj;Lgj;)Lcov;
    flags: (0x0001) ACC_PUBLIC
    Code:
      stack=7, locals=6, args_size=6
         0: aload_0
         1: invokevirtual #155                // Method b:()Lcdq;
         4: aload_0
         5: invokevirtual #73                 // Method r:()Lcov;
         8: aload_1
         9: aload_2
        10: aload_3
        11: aload         4
        13: aload         5
        15: invokevirtual #458                // Method cdq.a:(Lcov;Lgo;Lcov;Lcaw;Lgj;Lgj;)Lcov;
        18: areturn
      LineNumberTable:
        line 955: 0
      LocalVariableTable:
        Start  Length  Slot  Name   Signature
            0      19     0  this   Lcou$a;
            0      19     1   $$0   Lgo;
            0      19     2   $$1   Lcov;
            0      19     3   $$2   Lcaw;
            0      19     4   $$3   Lgj;
            0      19     5   $$4   Lgj;

  public boolean a(cab, gj, djo);
    descriptor: (Lcab;Lgj;Ldjo;)Z
    flags: (0x0001) ACC_PUBLIC
    Code:
      stack=5, locals=4, args_size=4
         0: aload_0
         1: invokevirtual #155                // Method b:()Lcdq;
         4: aload_0
         5: invokevirtual #73                 // Method r:()Lcov;
         8: aload_1
         9: aload_2
        10: aload_3
        11: invokevirtual #462                // Method cdq.a:(Lcov;Lcab;Lgj;Ldjo;)Z
        14: ireturn
      LineNumberTable:
        line 959: 0
      LocalVariableTable:
        Start  Length  Slot  Name   Signature
            0      15     0  this   Lcou$a;
            0      15     1   $$0   Lcab;
            0      15     2   $$1   Lgj;
            0      15     3   $$2   Ldjo;

  public boolean a(bww);
    descriptor: (Lbww;)Z
    flags: (0x0001) ACC_PUBLIC
    Code:
      stack=3, locals=2, args_size=2
         0: aload_0
         1: invokevirtual #155                // Method b:()Lcdq;
         4: aload_0
         5: invokevirtual #73                 // Method r:()Lcov;
         8: aload_1
         9: invokevirtual #467                // Method cdq.a:(Lcov;Lbww;)Z
        12: ireturn
      LineNumberTable:
        line 963: 0
      LocalVariableTable:
        Start  Length  Slot  Name   Signature
            0      13     0  this   Lcou$a;
            0      13     1   $$0   Lbww;

  public boolean a(diw);
    descriptor: (Ldiw;)Z
    flags: (0x0001) ACC_PUBLIC
    Code:
      stack=3, locals=2, args_size=2
         0: aload_0
         1: invokevirtual #155                // Method b:()Lcdq;
         4: aload_0
         5: invokevirtual #73                 // Method r:()Lcov;
         8: aload_1
         9: invokevirtual #472                // Method cdq.a:(Lcov;Ldiw;)Z
        12: ireturn
      LineNumberTable:
        line 967: 0
      LocalVariableTable:
        Start  Length  Slot  Name   Signature
            0      13     0  this   Lcou$a;
            0      13     1   $$0   Ldiw;

  public boolean a(cay, gj);
    descriptor: (Lcay;Lgj;)Z
    flags: (0x0001) ACC_PUBLIC
    Code:
      stack=4, locals=3, args_size=3
         0: aload_0
         1: invokevirtual #155                // Method b:()Lcdq;
         4: aload_0
         5: invokevirtual #73                 // Method r:()Lcov;
         8: aload_1
         9: aload_2
        10: invokevirtual #477                // Method cdq.a:(Lcov;Lcay;Lgj;)Z
        13: ireturn
      LineNumberTable:
        line 971: 0
      LocalVariableTable:
        Start  Length  Slot  Name   Signature
            0      14     0  this   Lcou$a;
            0      14     1   $$0   Lcay;
            0      14     2   $$1   Lgj;

  public boolean q(cab, gj);
    descriptor: (Lcab;Lgj;)Z
    flags: (0x0001) ACC_PUBLIC
    Code:
      stack=4, locals=3, args_size=3
         0: aload_0
         1: getfield      #136                // Field q:Lcou$e;
         4: aload_0
         5: invokevirtual #73                 // Method r:()Lcov;
         8: aload_1
         9: aload_2
        10: invokeinterface #234,  4          // InterfaceMethod cou$e.test:(Lcov;Lcab;Lgj;)Z
        15: ireturn
      LineNumberTable:
        line 975: 0
      LocalVariableTable:
        Start  Length  Slot  Name   Signature
            0      16     0  this   Lcou$a;
            0      16     1   $$0   Lcab;
            0      16     2   $$1   Lgj;

  public awk b(cav, gj);
    descriptor: (Lcav;Lgj;)Lawk;
    flags: (0x0001) ACC_PUBLIC
    Code:
      stack=4, locals=3, args_size=3
         0: aload_0
         1: invokevirtual #155                // Method b:()Lcdq;
         4: aload_0
         5: invokevirtual #73                 // Method r:()Lcov;
         8: aload_1
         9: aload_2
        10: invokevirtual #482                // Method cdq.b:(Lcov;Lcav;Lgj;)Lawk;
        13: areturn
      LineNumberTable:
        line 980: 0
      LocalVariableTable:
        Start  Length  Slot  Name   Signature
            0      14     0  this   Lcou$a;
            0      14     1   $$0   Lcav;
            0      14     2   $$1   Lgj;
    RuntimeVisibleAnnotations:
      0: #55()
        javax.annotation.Nullable

  public boolean a(aif<cdq>);
    descriptor: (Laif;)Z
    flags: (0x0001) ACC_PUBLIC
    Code:
      stack=2, locals=2, args_size=2
         0: aload_0
         1: invokevirtual #155                // Method b:()Lcdq;
         4: invokevirtual #487                // Method cdq.q:()Lgs$c;
         7: aload_1
         8: invokevirtual #489                // Method gs$c.a:(Laif;)Z
        11: ireturn
      LineNumberTable:
        line 984: 0
      LocalVariableTable:
        Start  Length  Slot  Name   Signature
            0      12     0  this   Lcou$a;
            0      12     1   $$0   Laif;
      LocalVariableTypeTable:
        Start  Length  Slot  Name   Signature
            0      12     1   $$0   Laif<Lcdq;>;
    Signature: #484                         // (Laif<Lcdq;>;)Z

  public boolean a(aif<cdq>, java.util.function.Predicate<cou$a>);
    descriptor: (Laif;Ljava/util/function/Predicate;)Z
    flags: (0x0001) ACC_PUBLIC
    Code:
      stack=2, locals=3, args_size=3
         0: aload_0
         1: aload_1
         2: invokevirtual #494                // Method a:(Laif;)Z
         5: ifeq          22
         8: aload_2
         9: aload_0
        10: invokeinterface #499,  2          // InterfaceMethod java/util/function/Predicate.test:(Ljava/lang/Object;)Z
        15: ifeq          22
        18: iconst_1
        19: goto          23
        22: iconst_0
        23: ireturn
      StackMapTable: number_of_entries = 2
        frame_type = 248 /* chop */
          offset_delta = 22
        frame_type = 64 /* same_locals_1_stack_item */
          stack = [ int ]
      LineNumberTable:
        line 988: 0
      LocalVariableTable:
        Start  Length  Slot  Name   Signature
            0      24     0  this   Lcou$a;
            0      24     1   $$0   Laif;
            0      24     2   $$1   Ljava/util/function/Predicate;
      LocalVariableTypeTable:
        Start  Length  Slot  Name   Signature
            0      24     1   $$0   Laif<Lcdq;>;
            0      24     2   $$1   Ljava/util/function/Predicate<Lcou$a;>;
    Signature: #493                         // (Laif<Lcdq;>;Ljava/util/function/Predicate<Lcou$a;>;)Z

  public boolean a(gt<cdq>);
    descriptor: (Lgt;)Z
    flags: (0x0001) ACC_PUBLIC
    Code:
      stack=2, locals=2, args_size=2
         0: aload_1
         1: aload_0
         2: invokevirtual #155                // Method b:()Lcdq;
         5: invokevirtual #487                // Method cdq.q:()Lgs$c;
         8: invokeinterface #508,  2          // InterfaceMethod gt.a:(Lgs;)Z
        13: ireturn
      LineNumberTable:
        line 992: 0
      LocalVariableTable:
        Start  Length  Slot  Name   Signature
            0      14     0  this   Lcou$a;
            0      14     1   $$0   Lgt;
      LocalVariableTypeTable:
        Start  Length  Slot  Name   Signature
            0      14     1   $$0   Lgt<Lcdq;>;
    Signature: #503                         // (Lgt<Lcdq;>;)Z

  public java.util.stream.Stream<aif<cdq>> m();
    descriptor: ()Ljava/util/stream/Stream;
    flags: (0x0001) ACC_PUBLIC
    Code:
      stack=1, locals=1, args_size=1
         0: aload_0
         1: invokevirtual #155                // Method b:()Lcdq;
         4: invokevirtual #487                // Method cdq.q:()Lgs$c;
         7: invokevirtual #514                // Method gs$c.c:()Ljava/util/stream/Stream;
        10: areturn
      LineNumberTable:
        line 996: 0
      LocalVariableTable:
        Start  Length  Slot  Name   Signature
            0      11     0  this   Lcou$a;
    Signature: #512                         // ()Ljava/util/stream/Stream<Laif<Lcdq;>;>;

  public boolean n();
    descriptor: ()Z
    flags: (0x0001) ACC_PUBLIC
    Code:
      stack=1, locals=1, args_size=1
         0: aload_0
         1: invokevirtual #155                // Method b:()Lcdq;
         4: instanceof    #516                // class cfx
         7: ireturn
      LineNumberTable:
        line 1000: 0
      LocalVariableTable:
        Start  Length  Slot  Name   Signature
            0       8     0  this   Lcou$a;

  public <T extends cmr> cms<T> a(cav, cmt<T>);
    descriptor: (Lcav;Lcmt;)Lcms;
    flags: (0x0001) ACC_PUBLIC
    Code:
      stack=4, locals=3, args_size=3
         0: aload_0
         1: invokevirtual #155                // Method b:()Lcdq;
         4: instanceof    #516                // class cfx
         7: ifeq          29
        10: aload_0
        11: invokevirtual #155                // Method b:()Lcdq;
        14: checkcast     #516                // class cfx
        17: aload_1
        18: aload_0
        19: invokevirtual #73                 // Method r:()Lcov;
        22: aload_2
        23: invokeinterface #521,  4          // InterfaceMethod cfx.a:(Lcav;Lcov;Lcmt;)Lcms;
        28: areturn
        29: aconst_null
        30: areturn
      StackMapTable: number_of_entries = 1
        frame_type = 248 /* chop */
          offset_delta = 29
      LineNumberTable:
        line 1005: 0
        line 1006: 10
        line 1008: 29
      LocalVariableTable:
        Start  Length  Slot  Name   Signature
            0      31     0  this   Lcou$a;
            0      31     1   $$0   Lcav;
            0      31     2   $$1   Lcmt;
      LocalVariableTypeTable:
        Start  Length  Slot  Name   Signature
            0      31     2   $$1   Lcmt<TT;>;
    Signature: #518                         // <T:Lcmr;>(Lcav;Lcmt<TT;>;)Lcms<TT;>;
    RuntimeVisibleAnnotations:
      0: #55()
        javax.annotation.Nullable

  public boolean a(cdq);
    descriptor: (Lcdq;)Z
    flags: (0x0001) ACC_PUBLIC
    Code:
      stack=2, locals=2, args_size=2
         0: aload_0
         1: invokevirtual #155                // Method b:()Lcdq;
         4: aload_1
         5: if_acmpne     12
         8: iconst_1
         9: goto          13
        12: iconst_0
        13: ireturn
      StackMapTable: number_of_entries = 2
        frame_type = 249 /* chop */
          offset_delta = 12
        frame_type = 64 /* same_locals_1_stack_item */
          stack = [ int ]
      LineNumberTable:
        line 1012: 0
      LocalVariableTable:
        Start  Length  Slot  Name   Signature
            0      14     0  this   Lcou$a;
            0      14     1   $$0   Lcdq;

  public dix o();
    descriptor: ()Ldix;
    flags: (0x0001) ACC_PUBLIC
    Code:
      stack=2, locals=1, args_size=1
         0: aload_0
         1: invokevirtual #155                // Method b:()Lcdq;
         4: aload_0
         5: invokevirtual #73                 // Method r:()Lcov;
         8: invokevirtual #529                // Method cdq.c_:(Lcov;)Ldix;
        11: areturn
      LineNumberTable:
        line 1016: 0
      LocalVariableTable:
        Start  Length  Slot  Name   Signature
            0      12     0  this   Lcou$a;

  public boolean p();
    descriptor: ()Z
    flags: (0x0001) ACC_PUBLIC
    Code:
      stack=2, locals=1, args_size=1
         0: aload_0
         1: invokevirtual #155                // Method b:()Lcdq;
         4: aload_0
         5: invokevirtual #73                 // Method r:()Lcov;
         8: invokevirtual #532                // Method cdq.e_:(Lcov;)Z
        11: ireturn
      LineNumberTable:
        line 1020: 0
      LocalVariableTable:
        Start  Length  Slot  Name   Signature
            0      12     0  this   Lcou$a;

  public long a(gj);
    descriptor: (Lgj;)J
    flags: (0x0001) ACC_PUBLIC
    Code:
      stack=3, locals=2, args_size=2
         0: aload_0
         1: invokevirtual #155                // Method b:()Lcdq;
         4: aload_0
         5: invokevirtual #73                 // Method r:()Lcov;
         8: aload_1
         9: invokevirtual #536                // Method cdq.a:(Lcov;Lgj;)J
        12: lreturn
      LineNumberTable:
        line 1024: 0
      LocalVariableTable:
        Start  Length  Slot  Name   Signature
            0      13     0  this   Lcou$a;
            0      13     1   $$0   Lgj;

  public ckg q();
    descriptor: ()Lckg;
    flags: (0x0001) ACC_PUBLIC
    Code:
      stack=2, locals=1, args_size=1
         0: aload_0
         1: invokevirtual #155                // Method b:()Lcdq;
         4: aload_0
         5: invokevirtual #73                 // Method r:()Lcov;
         8: invokevirtual #540                // Method cdq.m:(Lcov;)Lckg;
        11: areturn
      LineNumberTable:
        line 1028: 0
      LocalVariableTable:
        Start  Length  Slot  Name   Signature
            0      12     0  this   Lcou$a;

  public void a(cav, cov, dpk, boz);
    descriptor: (Lcav;Lcov;Ldpk;Lboz;)V
    flags: (0x0001) ACC_PUBLIC
    Code:
      stack=5, locals=5, args_size=5
         0: aload_0
         1: invokevirtual #155                // Method b:()Lcdq;
         4: aload_1
         5: aload_2
         6: aload_3
         7: aload         4
         9: invokevirtual #543                // Method cdq.a:(Lcav;Lcov;Ldpk;Lboz;)V
        12: return
      LineNumberTable:
        line 1032: 0
        line 1033: 12
      LocalVariableTable:
        Start  Length  Slot  Name   Signature
            0      13     0  this   Lcou$a;
            0      13     1   $$0   Lcav;
            0      13     2   $$1   Lcov;
            0      13     3   $$2   Ldpk;
            0      13     4   $$3   Lboz;

  public boolean d(cab, gj, go);
    descriptor: (Lcab;Lgj;Lgo;)Z
    flags: (0x0001) ACC_PUBLIC
    Code:
      stack=5, locals=4, args_size=4
         0: aload_0
         1: aload_1
         2: aload_2
         3: aload_3
         4: getstatic     #550                // Field ckw.a:Lckw;
         7: invokevirtual #553                // Method a:(Lcab;Lgj;Lgo;Lckw;)Z
        10: ireturn
      LineNumberTable:
        line 1036: 0
      LocalVariableTable:
        Start  Length  Slot  Name   Signature
            0      11     0  this   Lcou$a;
            0      11     1   $$0   Lcab;
            0      11     2   $$1   Lgj;
            0      11     3   $$2   Lgo;

  public boolean a(cab, gj, go, ckw);
    descriptor: (Lcab;Lgj;Lgo;Lckw;)Z
    flags: (0x0001) ACC_PUBLIC
    Code:
      stack=5, locals=5, args_size=5
         0: aload_0
         1: getfield      #163                // Field a:Lcou$a$a;
         4: ifnull        18
         7: aload_0
         8: getfield      #163                // Field a:Lcou$a$a;
        11: aload_3
        12: aload         4
        14: invokevirtual #556                // Method cou$a$a.a:(Lgo;Lckw;)Z
        17: ireturn
        18: aload         4
        20: aload_0
        21: invokevirtual #73                 // Method r:()Lcov;
        24: aload_1
        25: aload_2
        26: aload_3
        27: invokevirtual #559                // Method ckw.a:(Lcov;Lcab;Lgj;Lgo;)Z
        30: ireturn
      StackMapTable: number_of_entries = 1
        frame_type = 18 /* same */
      LineNumberTable:
        line 1040: 0
        line 1041: 7
        line 1043: 18
      LocalVariableTable:
        Start  Length  Slot  Name   Signature
            0      31     0  this   Lcou$a;
            0      31     1   $$0   Lcab;
            0      31     2   $$1   Lgj;
            0      31     3   $$2   Lgo;
            0      31     4   $$3   Lckw;

  public boolean r(cab, gj);
    descriptor: (Lcab;Lgj;)Z
    flags: (0x0001) ACC_PUBLIC
    Code:
      stack=4, locals=3, args_size=3
         0: aload_0
         1: getfield      #163                // Field a:Lcou$a$a;
         4: ifnull        15
         7: aload_0
         8: getfield      #163                // Field a:Lcou$a$a;
        11: getfield      #561                // Field cou$a$a.d:Z
        14: ireturn
        15: aload_0
        16: invokevirtual #155                // Method b:()Lcdq;
        19: aload_0
        20: invokevirtual #73                 // Method r:()Lcov;
        23: aload_1
        24: aload_2
        25: invokevirtual #563                // Method cdq.a_:(Lcov;Lcab;Lgj;)Z
        28: ireturn
      StackMapTable: number_of_entries = 1
        frame_type = 15 /* same */
      LineNumberTable:
        line 1047: 0
        line 1048: 7
        line 1050: 15
      LocalVariableTable:
        Start  Length  Slot  Name   Signature
            0      29     0  this   Lcou$a;
            0      29     1   $$0   Lcab;
            0      29     2   $$1   Lgj;

  protected abstract cov r();
    descriptor: ()Lcov;
    flags: (0x0404) ACC_PROTECTED, ACC_ABSTRACT

  public boolean s();
    descriptor: ()Z
    flags: (0x0001) ACC_PUBLIC
    Code:
      stack=1, locals=1, args_size=1
         0: aload_0
         1: getfield      #115                // Field l:Z
         4: ireturn
      LineNumberTable:
        line 1056: 0
      LocalVariableTable:
        Start  Length  Slot  Name   Signature
            0       5     0  this   Lcou$a;
}
InnerClasses:
  public static #11= #10 of #8;           // c=class cou$c of class cou
  public static abstract #12= #2 of #8;   // a=class cou$a of class cou
  public static #15= #14 of #8;           // e=class cou$e of class cou
  private static final #12= #17 of #2;    // a=class cou$a$a of class cou$a
  public static #20= #19 of #8;           // d=class cou$d of class cou
  public static final #23= #22 of #8;     // b=class cou$b of class cou
  public static #12= #25 of #27;          // a=class gj$a of class gj
  public static #12= #29 of #31;          // a=class dlc$a of class dlc
  public static #11= #33 of #35;          // c=class gs$c of class gs
Signature: #3                           // Lcox<Lcdq;Lcov;>;
SourceFile: "SourceFile"
NestHost: class cou
